Workbook

Sheet PO-Backlog
A1: PO-Backlog
A2: # | B2: Projekttitel | C2: Größe | D2: Value-Bucket | E2: Quartal | F2: MoSCoW | G2: Team | H2: Std. | I2: Bemerkungen
A3: 1 | B3: Doku - LogIn für Kunden | F3: Could | G3: WEB
A4: 2 | B4: Auswertung zur Nutzung / Verhalten MILO | F4: Could | G4: WEB | H4: =IF(C4="XXL (>160h)",168,IF(C4="XL (>40h)",48,IF(C4="L (20-40h)",30,IF(C4="M (10-20h)",15,IF(C4="S (<10h)",5,""))))) | J4: =IF($E4="Q12026",COUNTIF($E$3:$E4,"Q12026"),"") | K4: =IF($E4="Q22026",COUNTIF($E$3:$E4,"Q22026"),"") | L4: =IF($E4="Q32026",COUNTIF($E$3:$E4,"Q32026"),"") | M4: =IF($E4="Q42026",COUNTIF($E$3:$E4,"Q42026"),"") | N4: =IF($E4="Backlog",COUNTIF($E$3:$E4,"Backlog"),"")
A5: 3 | B5: Integration von MILO auf der Homepage | F5: Could | G5: WEB | H5: =IF(C5="XXL (>160h)",168,IF(C5="XL (>40h)",48,IF(C5="L (20-40h)",30,IF(C5="M (10-20h)",15,IF(C5="S (<10h)",5,""))))) | J5: =IF($E5="Q12026",COUNTIF($E$3:$E5,"Q12026"),"") | K5: =IF($E5="Q22026",COUNTIF($E$3:$E5,"Q22026"),"") | L5: =IF($E5="Q32026",COUNTIF($E$3:$E5,"Q32026"),"") | M5: =IF($E5="Q42026",COUNTIF($E$3:$E5,"Q42026"),"") | N5: =IF($E5="Backlog",COUNTIF($E$3:$E5,"Backlog"),"")
A6: 4 | B6: Refactoring / Optimierung MILO | F6: Could | G6: WEB | H6: =IF(C6="XXL (>160h)",168,IF(C6="XL (>40h)",48,IF(C6="L (20-40h)",30,IF(C6="M (10-20h)",15,IF(C6="S (<10h)",5,""))))) | J6: =IF($E6="Q12026",COUNTIF($E$3:$E6,"Q12026"),"") | K6: =IF($E6="Q22026",COUNTIF($E$3:$E6,"Q22026"),"") | L6: =IF($E6="Q32026",COUNTIF($E$3:$E6,"Q32026"),"") | M6: =IF($E6="Q42026",COUNTIF($E$3:$E6,"Q42026"),"") | N6: =IF($E6="Backlog",COUNTIF($E$3:$E6,"Backlog"),"")
A7: 5 | B7: Technical debt / Hypertron -> GitHub -> CI/CD | F7: Should | G7: WEB | H7: =IF(C7="XXL (>160h)",168,IF(C7="XL (>40h)",48,IF(C7="L (20-40h)",30,IF(C7="M (10-20h)",15,IF(C7="S (<10h)",5,""))))) | I7: auch als Basis für AI Maturity -> Volaris | J7: =IF($E7="Q12026",COUNTIF($E$3:$E7,"Q12026"),"") | K7: =IF($E7="Q22026",COUNTIF($E$3:$E7,"Q22026"),"") | L7: =IF($E7="Q32026",COUNTIF($E$3:$E7,"Q32026"),"") | M7: =IF($E7="Q42026",COUNTIF($E$3:$E7,"Q42026"),"") | N7: =IF($E7="Backlog",COUNTIF($E$3:$E7,"Backlog"),"")
A8: 6 | B8: Angular | F8: Must | G8: WEB | H8: =IF(C8="XXL (>160h)",168,IF(C8="XL (>40h)",48,IF(C8="L (20-40h)",30,IF(C8="M (10-20h)",15,IF(C8="S (<10h)",5,""))))) | J8: =IF($E8="Q12026",COUNTIF($E$3:$E8,"Q12026"),"") | K8: =IF($E8="Q22026",COUNTIF($E$3:$E8,"Q22026"),"") | L8: =IF($E8="Q32026",COUNTIF($E$3:$E8,"Q32026"),"") | M8: =IF($E8="Q42026",COUNTIF($E$3:$E8,"Q42026"),"") | N8: =IF($E8="Backlog",COUNTIF($E$3:$E8,"Backlog"),"")
A9: 7 | B9: Andorid Anforderungen | E9: Q42026 | F9: Must | G9: WEB | H9: =IF(C9="XXL (>160h)",168,IF(C9="XL (>40h)",48,IF(C9="L (20-40h)",30,IF(C9="M (10-20h)",15,IF(C9="S (<10h)",5,""))))) | I9: -> relevant bis August 2026 | J9: =IF($E9="Q12026",COUNTIF($E$3:$E9,"Q12026"),"") | K9: =IF($E9="Q22026",COUNTIF($E$3:$E9,"Q22026"),"") | L9: =IF($E9="Q32026",COUNTIF($E$3:$E9,"Q32026"),"") | M9: =IF($E9="Q42026",COUNTIF($E$3:$E9,"Q42026"),"") -> 1 | N9: =IF($E9="Backlog",COUNTIF($E$3:$E9,"Backlog"),"")
A10: 8 | B10: Grundlasten berücksichtigen [ SIG / Incidents / Framework / etc. ] | F10: Must | G10: W->D | H10: =IF(C10="XXL (>160h)",168,IF(C10="XL (>40h)",48,IF(C10="L (20-40h)",30,IF(C10="M (10-20h)",15,IF(C10="S (<10h)",5,""))))) | J10: =IF($E10="Q12026",COUNTIF($E$3:$E10,"Q12026"),"") | K10: =IF($E10="Q22026",COUNTIF($E$3:$E10,"Q22026"),"") | L10: =IF($E10="Q32026",COUNTIF($E$3:$E10,"Q32026"),"") | M10: =IF($E10="Q42026",COUNTIF($E$3:$E10,"Q42026"),"") | N10: =IF($E10="Backlog",COUNTIF($E$3:$E10,"Backlog"),"")
A11: 9 | B11: Webshop - abweichende Lieferadresse + extra Namensfeld | F11: Should | G11: WEB | H11: =IF(C11="XXL (>160h)",168,IF(C11="XL (>40h)",48,IF(C11="L (20-40h)",30,IF(C11="M (10-20h)",15,IF(C11="S (<10h)",5,""))))) | J11: =IF($E11="Q12026",COUNTIF($E$3:$E11,"Q12026"),"") | K11: =IF($E11="Q22026",COUNTIF($E$3:$E11,"Q22026"),"") | L11: =IF($E11="Q32026",COUNTIF($E$3:$E11,"Q32026"),"") | M11: =IF($E11="Q42026",COUNTIF($E$3:$E11,"Q42026"),"") | N11: =IF($E11="Backlog",COUNTIF($E$3:$E11,"Backlog"),"")
A12: 10 | B12: Webshop - neues Feld Firmenname bei Gastfunktion | F12: Should | G12: WEB | H12: =IF(C12="XXL (>160h)",168,IF(C12="XL (>40h)",48,IF(C12="L (20-40h)",30,IF(C12="M (10-20h)",15,IF(C12="S (<10h)",5,""))))) | J12: =IF($E12="Q12026",COUNTIF($E$3:$E12,"Q12026"),"") | K12: =IF($E12="Q22026",COUNTIF($E$3:$E12,"Q22026"),"") | L12: =IF($E12="Q32026",COUNTIF($E$3:$E12,"Q32026"),"") | M12: =IF($E12="Q42026",COUNTIF($E$3:$E12,"Q42026"),"") | N12: =IF($E12="Backlog",COUNTIF($E$3:$E12,"Backlog"),"")
A13: 11 | B13: Paypal - integration muss zeitnah erneuert werden | F13: Must | G13: WEB | H13: =IF(C13="XXL (>160h)",168,IF(C13="XL (>40h)",48,IF(C13="L (20-40h)",30,IF(C13="M (10-20h)",15,IF(C13="S (<10h)",5,""))))) | J13: =IF($E13="Q12026",COUNTIF($E$3:$E13,"Q12026"),"") | K13: =IF($E13="Q22026",COUNTIF($E$3:$E13,"Q22026"),"") | L13: =IF($E13="Q32026",COUNTIF($E$3:$E13,"Q32026"),"") | M13: =IF($E13="Q42026",COUNTIF($E$3:$E13,"Q42026"),"") | N13: =IF($E13="Backlog",COUNTIF($E$3:$E13,"Backlog"),"")
A14: 12 | B14: DOKUMENTATION - Next Steps / V2? / | F14: Must | G14: W->D | H14: =IF(C14="XXL (>160h)",168,IF(C14="XL (>40h)",48,IF(C14="L (20-40h)",30,IF(C14="M (10-20h)",15,IF(C14="S (<10h)",5,""))))) | J14: =IF($E14="Q12026",COUNTIF($E$3:$E14,"Q12026"),"") | K14: =IF($E14="Q22026",COUNTIF($E$3:$E14,"Q22026"),"") | L14: =IF($E14="Q32026",COUNTIF($E$3:$E14,"Q32026"),"") | M14: =IF($E14="Q42026",COUNTIF($E$3:$E14,"Q42026"),"") | N14: =IF($E14="Backlog",COUNTIF($E$3:$E14,"Backlog"),"")
A15: 13 | B15: Reserv with Google / oder andere Anbindungen verbessern | H15: =IF(C15="XXL (>160h)",168,IF(C15="XL (>40h)",48,IF(C15="L (20-40h)",30,IF(C15="M (10-20h)",15,IF(C15="S (<10h)",5,""))))) | J15: =IF($E15="Q12026",COUNTIF($E$3:$E15,"Q12026"),"") | K15: =IF($E15="Q22026",COUNTIF($E$3:$E15,"Q22026"),"") | L15: =IF($E15="Q32026",COUNTIF($E$3:$E15,"Q32026"),"") | M15: =IF($E15="Q42026",COUNTIF($E$3:$E15,"Q42026"),"") | N15: =IF($E15="Backlog",COUNTIF($E$3:$E15,"Backlog"),"")
A16: 14 | B16: Jouney Gaps (2) | H16: =IF(C16="XXL (>160h)",168,IF(C16="XL (>40h)",48,IF(C16="L (20-40h)",30,IF(C16="M (10-20h)",15,IF(C16="S (<10h)",5,""))))) | J16: =IF($E16="Q12026",COUNTIF($E$3:$E16,"Q12026"),"") | K16: =IF($E16="Q22026",COUNTIF($E$3:$E16,"Q22026"),"") | L16: =IF($E16="Q32026",COUNTIF($E$3:$E16,"Q32026"),"") | M16: =IF($E16="Q42026",COUNTIF($E$3:$E16,"Q42026"),"") | N16: =IF($E16="Backlog",COUNTIF($E$3:$E16,"Backlog"),"")
A17: 15 | B17: Prosegur Cash Automat API | H17: =IF(C17="XXL (>160h)",168,IF(C17="XL (>40h)",48,IF(C17="L (20-40h)",30,IF(C17="M (10-20h)",15,IF(C17="S (<10h)",5,""))))) | J17: =IF($E17="Q12026",COUNTIF($E$3:$E17,"Q12026"),"") | K17: =IF($E17="Q22026",COUNTIF($E$3:$E17,"Q22026"),"") | L17: =IF($E17="Q32026",COUNTIF($E$3:$E17,"Q32026"),"") | M17: =IF($E17="Q42026",COUNTIF($E$3:$E17,"Q42026"),"") | N17: =IF($E17="Backlog",COUNTIF($E$3:$E17,"Backlog"),"")
A18: 16 | B18: Bei der Walletanbindung von Gutscheinen, sollten wir auch gleich die Tickets berücksichtigen. | H18: =IF(C18="XXL (>160h)",168,IF(C18="XL (>40h)",48,IF(C18="L (20-40h)",30,IF(C18="M (10-20h)",15,IF(C18="S (<10h)",5,""))))) | J18: =IF($E18="Q12026",COUNTIF($E$3:$E18,"Q12026"),"") | K18: =IF($E18="Q22026",COUNTIF($E$3:$E18,"Q22026"),"") | L18: =IF($E18="Q32026",COUNTIF($E$3:$E18,"Q32026"),"") | M18: =IF($E18="Q42026",COUNTIF($E$3:$E18,"Q42026"),"") | N18: =IF($E18="Backlog",COUNTIF($E$3:$E18,"Backlog"),"")
A19: 17 | B19: UHD | Jahresrechnung | H19: =IF(C19="XXL (>160h)",168,IF(C19="XL (>40h)",48,IF(C19="L (20-40h)",30,IF(C19="M (10-20h)",15,IF(C19="S (<10h)",5,""))))) | J19: =IF($E19="Q12026",COUNTIF($E$3:$E19,"Q12026"),"") | K19: =IF($E19="Q22026",COUNTIF($E$3:$E19,"Q22026"),"") | L19: =IF($E19="Q32026",COUNTIF($E$3:$E19,"Q32026"),"") | M19: =IF($E19="Q42026",COUNTIF($E$3:$E19,"Q42026"),"") | N19: =IF($E19="Backlog",COUNTIF($E$3:$E19,"Backlog"),"")
A20: 18 | B20: Neue DATEV-Schnittstelle | H20: =IF(C20="XXL (>160h)",168,IF(C20="XL (>40h)",48,IF(C20="L (20-40h)",30,IF(C20="M (10-20h)",15,IF(C20="S (<10h)",5,""))))) | J20: =IF($E20="Q12026",COUNTIF($E$3:$E20,"Q12026"),"") | K20: =IF($E20="Q22026",COUNTIF($E$3:$E20,"Q22026"),"") | L20: =IF($E20="Q32026",COUNTIF($E$3:$E20,"Q32026"),"") | M20: =IF($E20="Q42026",COUNTIF($E$3:$E20,"Q42026"),"") | N20: =IF($E20="Backlog",COUNTIF($E$3:$E20,"Backlog"),"")
A21: 19 | B21: Subventionierungsmodul im Webshop / Retail / Inhouse Ordering | Kundenstamm 1 vs. Kundenstamm 2.0 -> Mail von Dennis | H21: =IF(C21="XXL (>160h)",168,IF(C21="XL (>40h)",48,IF(C21="L (20-40h)",30,IF(C21="M (10-20h)",15,IF(C21="S (<10h)",5,""))))) | J21: =IF($E21="Q12026",COUNTIF($E$3:$E21,"Q12026"),"") | K21: =IF($E21="Q22026",COUNTIF($E$3:$E21,"Q22026"),"") | L21: =IF($E21="Q32026",COUNTIF($E$3:$E21,"Q32026"),"") | M21: =IF($E21="Q42026",COUNTIF($E$3:$E21,"Q42026"),"") | N21: =IF($E21="Backlog",COUNTIF($E$3:$E21,"Backlog"),"")
A22: 20 | B22: Eventfunktion auch für Gruppen aktiviert im IHO | H22: =IF(C22="XXL (>160h)",168,IF(C22="XL (>40h)",48,IF(C22="L (20-40h)",30,IF(C22="M (10-20h)",15,IF(C22="S (<10h)",5,""))))) | J22: =IF($E22="Q12026",COUNTIF($E$3:$E22,"Q12026"),"") | K22: =IF($E22="Q22026",COUNTIF($E$3:$E22,"Q22026"),"") | L22: =IF($E22="Q32026",COUNTIF($E$3:$E22,"Q32026"),"") | M22: =IF($E22="Q42026",COUNTIF($E$3:$E22,"Q42026"),"") | N22: =IF($E22="Backlog",COUNTIF($E$3:$E22,"Backlog"),"")
A23: 21 | B23: Adyen Tokenization und Network Tokenization -> Mail von Lars / 27.01.2026 | H23: =IF(C23="XXL (>160h)",168,IF(C23="XL (>40h)",48,IF(C23="L (20-40h)",30,IF(C23="M (10-20h)",15,IF(C23="S (<10h)",5,""))))) | I23: Wunsch noch in 2026 (Q3?) | Ausarbeitung fehlt | J23: =IF($E23="Q12026",COUNTIF($E$3:$E23,"Q12026"),"") | K23: =IF($E23="Q22026",COUNTIF($E$3:$E23,"Q22026"),"") | L23: =IF($E23="Q32026",COUNTIF($E$3:$E23,"Q32026"),"") | M23: =IF($E23="Q42026",COUNTIF($E$3:$E23,"Q42026"),"") | N23: =IF($E23="Backlog",COUNTIF($E$3:$E23,"Backlog"),"")
A24: 22 | B24: NoCoo auch in anderen Sprachen (primär englisch / gerne merhsprachig) | H24: =IF(C24="XXL (>160h)",168,IF(C24="XL (>40h)",48,IF(C24="L (20-40h)",30,IF(C24="M (10-20h)",15,IF(C24="S (<10h)",5,""))))) | J24: =IF($E24="Q12026",COUNTIF($E$3:$E24,"Q12026"),"") | K24: =IF($E24="Q22026",COUNTIF($E$3:$E24,"Q22026"),"") | L24: =IF($E24="Q32026",COUNTIF($E$3:$E24,"Q32026"),"") | M24: =IF($E24="Q42026",COUNTIF($E$3:$E24,"Q42026"),"") | N24: =IF($E24="Backlog",COUNTIF($E$3:$E24,"Backlog"),"")
A25: 23 | B25: Gekündigte Kunden dürfen nicht mehr auf das Portal zugreifen - Mail Sebastian 19.02.2026 | H25: =IF(C25="XXL (>160h)",168,IF(C25="XL (>40h)",48,IF(C25="L (20-40h)",30,IF(C25="M (10-20h)",15,IF(C25="S (<10h)",5,""))))) | J25: =IF($E25="Q12026",COUNTIF($E$3:$E25,"Q12026"),"") | K25: =IF($E25="Q22026",COUNTIF($E$3:$E25,"Q22026"),"") | L25: =IF($E25="Q32026",COUNTIF($E$3:$E25,"Q32026"),"") | M25: =IF($E25="Q42026",COUNTIF($E$3:$E25,"Q42026"),"") | N25: =IF($E25="Backlog",COUNTIF($E$3:$E25,"Backlog"),"")
A26: 24 | B26: Den MyHypersoft-Login vor die Doku schalten. - Mail Sebastian 19.02.2026 | H26: =IF(C26="XXL (>160h)",168,IF(C26="XL (>40h)",48,IF(C26="L (20-40h)",30,IF(C26="M (10-20h)",15,IF(C26="S (<10h)",5,""))))) | J26: =IF($E26="Q12026",COUNTIF($E$3:$E26,"Q12026"),"") | K26: =IF($E26="Q22026",COUNTIF($E$3:$E26,"Q22026"),"") | L26: =IF($E26="Q32026",COUNTIF($E$3:$E26,"Q32026"),"") | M26: =IF($E26="Q42026",COUNTIF($E$3:$E26,"Q42026"),"") | N26: =IF($E26="Backlog",COUNTIF($E$3:$E26,"Backlog"),"")
A27: 25 | B27: UHD - Pflichtfeld „Benutzer“ (Hinweis, wenn keine Mail -> Eingabe) | H27: =IF(C27="XXL (>160h)",168,IF(C27="XL (>40h)",48,IF(C27="L (20-40h)",30,IF(C27="M (10-20h)",15,IF(C27="S (<10h)",5,""))))) | J27: =IF($E27="Q12026",COUNTIF($E$3:$E27,"Q12026"),"") | K27: =IF($E27="Q22026",COUNTIF($E$3:$E27,"Q22026"),"") | L27: =IF($E27="Q32026",COUNTIF($E$3:$E27,"Q32026"),"") | M27: =IF($E27="Q42026",COUNTIF($E$3:$E27,"Q42026"),"") | N27: =IF($E27="Backlog",COUNTIF($E$3:$E27,"Backlog"),"")
A28: 26 | B28: UHD - Ticket-Owner hinterlegen | H28: =IF(C28="XXL (>160h)",168,IF(C28="XL (>40h)",48,IF(C28="L (20-40h)",30,IF(C28="M (10-20h)",15,IF(C28="S (<10h)",5,""))))) | J28: =IF($E28="Q12026",COUNTIF($E$3:$E28,"Q12026"),"") | K28: =IF($E28="Q22026",COUNTIF($E$3:$E28,"Q22026"),"") | L28: =IF($E28="Q32026",COUNTIF($E$3:$E28,"Q32026"),"") | M28: =IF($E28="Q42026",COUNTIF($E$3:$E28,"Q42026"),"") | N28: =IF($E28="Backlog",COUNTIF($E$3:$E28,"Backlog"),"")
A29: 27 | B29: UHD - Autoresponder bei eingehenden Mails. (SLA) | H29: =IF(C29="XXL (>160h)",168,IF(C29="XL (>40h)",48,IF(C29="L (20-40h)",30,IF(C29="M (10-20h)",15,IF(C29="S (<10h)",5,""))))) | J29: =IF($E29="Q12026",COUNTIF($E$3:$E29,"Q12026"),"") | K29: =IF($E29="Q22026",COUNTIF($E$3:$E29,"Q22026"),"") | L29: =IF($E29="Q32026",COUNTIF($E$3:$E29,"Q32026"),"") | M29: =IF($E29="Q42026",COUNTIF($E$3:$E29,"Q42026"),"") | N29: =IF($E29="Backlog",COUNTIF($E$3:$E29,"Backlog"),"")
A30: 28 | B30: UHD - Incident-Antworten mit Company-Mail in CC (SLA) – An welche Mail? | H30: =IF(C30="XXL (>160h)",168,IF(C30="XL (>40h)",48,IF(C30="L (20-40h)",30,IF(C30="M (10-20h)",15,IF(C30="S (<10h)",5,""))))) | J30: =IF($E30="Q12026",COUNTIF($E$3:$E30,"Q12026"),"") | K30: =IF($E30="Q22026",COUNTIF($E$3:$E30,"Q22026"),"") | L30: =IF($E30="Q32026",COUNTIF($E$3:$E30,"Q32026"),"") | M30: =IF($E30="Q42026",COUNTIF($E$3:$E30,"Q42026"),"") | N30: =IF($E30="Backlog",COUNTIF($E$3:$E30,"Backlog"),"")
A31: 29 | B31: UHD - Parsing | H31: =IF(C31="XXL (>160h)",168,IF(C31="XL (>40h)",48,IF(C31="L (20-40h)",30,IF(C31="M (10-20h)",15,IF(C31="S (<10h)",5,""))))) | J31: =IF($E31="Q12026",COUNTIF($E$3:$E31,"Q12026"),"") | K31: =IF($E31="Q22026",COUNTIF($E$3:$E31,"Q22026"),"") | L31: =IF($E31="Q32026",COUNTIF($E$3:$E31,"Q32026"),"") | M31: =IF($E31="Q42026",COUNTIF($E$3:$E31,"Q42026"),"") | N31: =IF($E31="Backlog",COUNTIF($E$3:$E31,"Backlog"),"")
A32: 30 | B32: Optimierung Gruppenwarenkorb / Tutorial-Modus / inhouse Ordering / Menüreihenfolge | H32: =IF(C32="XXL (>160h)",168,IF(C32="XL (>40h)",48,IF(C32="L (20-40h)",30,IF(C32="M (10-20h)",15,IF(C32="S (<10h)",5,""))))) | J32: =IF($E32="Q12026",COUNTIF($E$3:$E32,"Q12026"),"") | K32: =IF($E32="Q22026",COUNTIF($E$3:$E32,"Q22026"),"") | L32: =IF($E32="Q32026",COUNTIF($E$3:$E32,"Q32026"),"") | M32: =IF($E32="Q42026",COUNTIF($E$3:$E32,"Q42026"),"") | N32: =IF($E32="Backlog",COUNTIF($E$3:$E32,"Backlog"),"")
A33: 31 | B33: QR-Code auf der Zwischenrechnung zum Zahlprozess (Chamäleon Berlin) | H33: =IF(C33="XXL (>160h)",168,IF(C33="XL (>40h)",48,IF(C33="L (20-40h)",30,IF(C33="M (10-20h)",15,IF(C33="S (<10h)",5,""))))) | I33: NoCOO PAY | J33: =IF($E33="Q12026",COUNTIF($E$3:$E33,"Q12026"),"") | K33: =IF($E33="Q22026",COUNTIF($E$3:$E33,"Q22026"),"") | L33: =IF($E33="Q32026",COUNTIF($E$3:$E33,"Q32026"),"") | M33: =IF($E33="Q42026",COUNTIF($E$3:$E33,"Q42026"),"") | N33: =IF($E33="Backlog",COUNTIF($E$3:$E33,"Backlog"),"")
A34: 32 | B34: Widerruf im Onlineshop (Pflicht ab 19.06.2026) | E34: Q42026 | H34: =IF(C34="XXL (>160h)",168,IF(C34="XL (>40h)",48,IF(C34="L (20-40h)",30,IF(C34="M (10-20h)",15,IF(C34="S (<10h)",5,""))))) | I34: Erst einmal nicht bzw. nur oberflächlcih prüfen und validiern. | J34: =IF($E34="Q12026",COUNTIF($E$3:$E34,"Q12026"),"") | K34: =IF($E34="Q22026",COUNTIF($E$3:$E34,"Q22026"),"") | L34: =IF($E34="Q32026",COUNTIF($E$3:$E34,"Q32026"),"") | M34: =IF($E34="Q42026",COUNTIF($E$3:$E34,"Q42026"),"") -> 2 | N34: =IF($E34="Backlog",COUNTIF($E$3:$E34,"Backlog"),"")
A35: 33 | B35: KI-Prompt-Interface für den Desktop-UHD. Eventuell mittels "MCP" | E35: Q32026 | H35: =IF(C35="XXL (>160h)",168,IF(C35="XL (>40h)",48,IF(C35="L (20-40h)",30,IF(C35="M (10-20h)",15,IF(C35="S (<10h)",5,""))))) | J35: =IF($E35="Q12026",COUNTIF($E$3:$E35,"Q12026"),"") | K35: =IF($E35="Q22026",COUNTIF($E$3:$E35,"Q22026"),"") | L35: =IF($E35="Q32026",COUNTIF($E$3:$E35,"Q32026"),"") -> 1 | M35: =IF($E35="Q42026",COUNTIF($E$3:$E35,"Q42026"),"") | N35: =IF($E35="Backlog",COUNTIF($E$3:$E35,"Backlog"),"")
A36: 34 | B36: Touchpoint-Lizensierung | E36: Q32026 | H36: =IF(C36="XXL (>160h)",168,IF(C36="XL (>40h)",48,IF(C36="L (20-40h)",30,IF(C36="M (10-20h)",15,IF(C36="S (<10h)",5,""))))) | J36: =IF($E36="Q12026",COUNTIF($E$3:$E36,"Q12026"),"") | K36: =IF($E36="Q22026",COUNTIF($E$3:$E36,"Q22026"),"") | L36: =IF($E36="Q32026",COUNTIF($E$3:$E36,"Q32026"),"") -> 2 | M36: =IF($E36="Q42026",COUNTIF($E$3:$E36,"Q42026"),"") | N36: =IF($E36="Backlog",COUNTIF($E$3:$E36,"Backlog"),"")
A37: 35 | H37: =IF(C37="XXL (>160h)",168,IF(C37="XL (>40h)",48,IF(C37="L (20-40h)",30,IF(C37="M (10-20h)",15,IF(C37="S (<10h)",5,""))))) | J37: =IF($E37="Q12026",COUNTIF($E$3:$E37,"Q12026"),"") | K37: =IF($E37="Q22026",COUNTIF($E$3:$E37,"Q22026"),"") | L37: =IF($E37="Q32026",COUNTIF($E$3:$E37,"Q32026"),"") | M37: =IF($E37="Q42026",COUNTIF($E$3:$E37,"Q42026"),"") | N37: =IF($E37="Backlog",COUNTIF($E$3:$E37,"Backlog"),"")
A38: 36 | H38: =IF(C38="XXL (>160h)",168,IF(C38="XL (>40h)",48,IF(C38="L (20-40h)",30,IF(C38="M (10-20h)",15,IF(C38="S (<10h)",5,""))))) | J38: =IF($E38="Q12026",COUNTIF($E$3:$E38,"Q12026"),"") | K38: =IF($E38="Q22026",COUNTIF($E$3:$E38,"Q22026"),"") | L38: =IF($E38="Q32026",COUNTIF($E$3:$E38,"Q32026"),"") | M38: =IF($E38="Q42026",COUNTIF($E$3:$E38,"Q42026"),"") | N38: =IF($E38="Backlog",COUNTIF($E$3:$E38,"Backlog"),"")
A39: 37 | H39: =IF(C39="XXL (>160h)",168,IF(C39="XL (>40h)",48,IF(C39="L (20-40h)",30,IF(C39="M (10-20h)",15,IF(C39="S (<10h)",5,""))))) | J39: =IF($E39="Q12026",COUNTIF($E$3:$E39,"Q12026"),"") | K39: =IF($E39="Q22026",COUNTIF($E$3:$E39,"Q22026"),"") | L39: =IF($E39="Q32026",COUNTIF($E$3:$E39,"Q32026"),"") | M39: =IF($E39="Q42026",COUNTIF($E$3:$E39,"Q42026"),"") | N39: =IF($E39="Backlog",COUNTIF($E$3:$E39,"Backlog"),"")
A40: 38 | H40: =IF(C40="XXL (>160h)",168,IF(C40="XL (>40h)",48,IF(C40="L (20-40h)",30,IF(C40="M (10-20h)",15,IF(C40="S (<10h)",5,""))))) | J40: =IF($E40="Q12026",COUNTIF($E$3:$E40,"Q12026"),"") | K40: =IF($E40="Q22026",COUNTIF($E$3:$E40,"Q22026"),"") | L40: =IF($E40="Q32026",COUNTIF($E$3:$E40,"Q32026"),"") | M40: =IF($E40="Q42026",COUNTIF($E$3:$E40,"Q42026"),"") | N40: =IF($E40="Backlog",COUNTIF($E$3:$E40,"Backlog"),"")
A41: 39 | H41: =IF(C41="XXL (>160h)",168,IF(C41="XL (>40h)",48,IF(C41="L (20-40h)",30,IF(C41="M (10-20h)",15,IF(C41="S (<10h)",5,""))))) | J41: =IF($E41="Q12026",COUNTIF($E$3:$E41,"Q12026"),"") | K41: =IF($E41="Q22026",COUNTIF($E$3:$E41,"Q22026"),"") | L41: =IF($E41="Q32026",COUNTIF($E$3:$E41,"Q32026"),"") | M41: =IF($E41="Q42026",COUNTIF($E$3:$E41,"Q42026"),"") | N41: =IF($E41="Backlog",COUNTIF($E$3:$E41,"Backlog"),"")
A42: 40 | H42: =IF(C42="XXL (>160h)",168,IF(C42="XL (>40h)",48,IF(C42="L (20-40h)",30,IF(C42="M (10-20h)",15,IF(C42="S (<10h)",5,""))))) | J42: =IF($E42="Q12026",COUNTIF($E$3:$E42,"Q12026"),"") | K42: =IF($E42="Q22026",COUNTIF($E$3:$E42,"Q22026"),"") | L42: =IF($E42="Q32026",COUNTIF($E$3:$E42,"Q32026"),"") | M42: =IF($E42="Q42026",COUNTIF($E$3:$E42,"Q42026"),"") | N42: =IF($E42="Backlog",COUNTIF($E$3:$E42,"Backlog"),"")
A43: 41 | H43: =IF(C43="XXL (>160h)",168,IF(C43="XL (>40h)",48,IF(C43="L (20-40h)",30,IF(C43="M (10-20h)",15,IF(C43="S (<10h)",5,""))))) | J43: =IF($E43="Q12026",COUNTIF($E$3:$E43,"Q12026"),"") | K43: =IF($E43="Q22026",COUNTIF($E$3:$E43,"Q22026"),"") | L43: =IF($E43="Q32026",COUNTIF($E$3:$E43,"Q32026"),"") | M43: =IF($E43="Q42026",COUNTIF($E$3:$E43,"Q42026"),"") | N43: =IF($E43="Backlog",COUNTIF($E$3:$E43,"Backlog"),"")
A44: 42 | H44: =IF(C44="XXL (>160h)",168,IF(C44="XL (>40h)",48,IF(C44="L (20-40h)",30,IF(C44="M (10-20h)",15,IF(C44="S (<10h)",5,""))))) | J44: =IF($E44="Q12026",COUNTIF($E$3:$E44,"Q12026"),"") | K44: =IF($E44="Q22026",COUNTIF($E$3:$E44,"Q22026"),"") | L44: =IF($E44="Q32026",COUNTIF($E$3:$E44,"Q32026"),"") | M44: =IF($E44="Q42026",COUNTIF($E$3:$E44,"Q42026"),"") | N44: =IF($E44="Backlog",COUNTIF($E$3:$E44,"Backlog"),"")
A45: 43 | H45: =IF(C45="XXL (>160h)",168,IF(C45="XL (>40h)",48,IF(C45="L (20-40h)",30,IF(C45="M (10-20h)",15,IF(C45="S (<10h)",5,""))))) | J45: =IF($E45="Q12026",COUNTIF($E$3:$E45,"Q12026"),"") | K45: =IF($E45="Q22026",COUNTIF($E$3:$E45,"Q22026"),"") | L45: =IF($E45="Q32026",COUNTIF($E$3:$E45,"Q32026"),"") | M45: =IF($E45="Q42026",COUNTIF($E$3:$E45,"Q42026"),"") | N45: =IF($E45="Backlog",COUNTIF($E$3:$E45,"Backlog"),"")
A46: 44 | H46: =IF(C46="XXL (>160h)",168,IF(C46="XL (>40h)",48,IF(C46="L (20-40h)",30,IF(C46="M (10-20h)",15,IF(C46="S (<10h)",5,""))))) | J46: =IF($E46="Q12026",COUNTIF($E$3:$E46,"Q12026"),"") | K46: =IF($E46="Q22026",COUNTIF($E$3:$E46,"Q22026"),"") | L46: =IF($E46="Q32026",COUNTIF($E$3:$E46,"Q32026"),"") | M46: =IF($E46="Q42026",COUNTIF($E$3:$E46,"Q42026"),"") | N46: =IF($E46="Backlog",COUNTIF($E$3:$E46,"Backlog"),"")
A47: 45 | H47: =IF(C47="XXL (>160h)",168,IF(C47="XL (>40h)",48,IF(C47="L (20-40h)",30,IF(C47="M (10-20h)",15,IF(C47="S (<10h)",5,""))))) | J47: =IF($E47="Q12026",COUNTIF($E$3:$E47,"Q12026"),"") | K47: =IF($E47="Q22026",COUNTIF($E$3:$E47,"Q22026"),"") | L47: =IF($E47="Q32026",COUNTIF($E$3:$E47,"Q32026"),"") | M47: =IF($E47="Q42026",COUNTIF($E$3:$E47,"Q42026"),"") | N47: =IF($E47="Backlog",COUNTIF($E$3:$E47,"Backlog"),"")
A48: 46 | H48: =IF(C48="XXL (>160h)",168,IF(C48="XL (>40h)",48,IF(C48="L (20-40h)",30,IF(C48="M (10-20h)",15,IF(C48="S (<10h)",5,""))))) | J48: =IF($E48="Q12026",COUNTIF($E$3:$E48,"Q12026"),"") | K48: =IF($E48="Q22026",COUNTIF($E$3:$E48,"Q22026"),"") | L48: =IF($E48="Q32026",COUNTIF($E$3:$E48,"Q32026"),"") | M48: =IF($E48="Q42026",COUNTIF($E$3:$E48,"Q42026"),"") | N48: =IF($E48="Backlog",COUNTIF($E$3:$E48,"Backlog"),"")
... A82: 80 | H82: =IF(C82="XXL (>160h)",168,IF(C82="XL (>40h)",48,IF(C82="L (20-40h)",30,IF(C82="M (10-20h)",15,IF(C82="S (<10h)",5,""))))) | J82: =IF($E82="Q12026",COUNTIF($E$3:$E82,"Q12026"),"") | K82: =IF($E82="Q22026",COUNTIF($E$3:$E82,"Q22026"),"") | L82: =IF($E82="Q32026",COUNTIF($E$3:$E82,"Q32026"),"") | M82: =IF($E82="Q42026",COUNTIF($E$3:$E82,"Q42026"),"") | N82: =IF($E82="Backlog",COUNTIF($E$3:$E82,"Backlog"),"")
A83: ∑ Geschätzte Stunden gesamt | H83: =SUM(H3:H82) -> 0
A85: Value: 🟢 Strengthen = strategische Stärkung | 🔵 Innovation = neue Fähigkeiten | 🔴 Repair = Fehler/Schulden beheben
A86: MoSCoW: Must = Pflicht · Should = Soll · Could = Optional · Won't = Ausgeschlossen | Team: WEB · Desktop · W->D · D->W (anteilig je 50% auf beide Teams)
A87: Größen: S <10h · M 10–20h · L 20–40h · XL >40h · XXL >160h | Stunden = automatisch aus Größe | Kapazitäten (blaue Felder) = manuell

Sheet Roadmap2026
B1: ENTWICKLUNGS-ROADMAP 2026
B2: Q12026 | F2: Q22026 | J2: Q32026 | N2: Q42026
B3: Kapazität | C3: Stunden | D3: Tage | F3: Kapazität | G3: Stunden | H3: Tage | J3: Kapazität | K3: Stunden | L3: Tage | N3: Kapazität | O3: Stunden | P3: Tage
B4: Gesamt verfügbar | C4: =D4*8 -> 0 | F4: Gesamt verfügbar | G4: =H4*8 -> 0 | J4: Gesamt verfügbar | K4: =L4*8 -> 1192 | L4: 149 | N4: Gesamt verfügbar | O4: =P4*8 -> 0
B5: Team Desktop | C5: =D5*8 -> 0 | F5: Team Desktop | G5: =H5*8 -> 0 | J5: Team Desktop | K5: =L5*8 -> 608 | L5: 76 | N5: Team Desktop | O5: =P5*8 -> 0
B6: Team Web | C6: =D6*8 -> 0 | F6: Team Web | G6: =H6*8 -> 0 | J6: Team Web | K6: =L6*8 -> 688 | L6: 86 | N6: Team Web | O6: =P6*8 -> 0
B7: Grundlast-Verteilung (Ist) | F7: Grundlast-Verteilung (Ist) | J7: Grundlast-Verteilung (Ist) | N7: Grundlast-Verteilung (Ist)
B8: GL-Daily Meetings | D8: =IFERROR(C8/C4,"") | F8: GL-Daily Meetings | H8: =IFERROR(G8/G4,"") | J8: GL-Daily Meetings | L8: =IFERROR(K8/K4,"") -> 0 | N8: GL-Daily Meetings | P8: =IFERROR(O8/O4,"")
B9: GL-Support/Incident | D9: =IFERROR(C9/C4,"") | F9: GL-Support/Incident | H9: =IFERROR(G9/G4,"") | J9: GL-Support/Incident | L9: =IFERROR(K9/K4,"") -> 0 | N9: GL-Support/Incident | P9: =IFERROR(O9/O4,"")
B10: GL-Updates | D10: =IFERROR(C10/C4,"") | F10: GL-Updates | H10: =IFERROR(G10/G4,"") | J10: GL-Updates | L10: =IFERROR(K10/K4,"") -> 0 | N10: GL-Updates | P10: =IFERROR(O10/O4,"")
B11: GL-Verwaltung | D11: =IFERROR(C11/C4,"") | F11: GL-Verwaltung | H11: =IFERROR(G11/G4,"") | J11: GL-Verwaltung | L11: =IFERROR(K11/K4,"") -> 0 | N11: GL-Verwaltung | P11: =IFERROR(O11/O4,"")
B12: GL-Refinement | D12: =IFERROR(C12/C4,"") | F12: GL-Refinement | H12: =IFERROR(G12/G4,"") | J12: GL-Refinement | L12: =IFERROR(K12/K4,"") -> 0 | N12: GL-Refinement | P12: =IFERROR(O12/O4,"")
B13: GL-CodeReview | D13: =IFERROR(C13/C4,"") | F13: GL-CodeReview | H13: =IFERROR(G13/G4,"") | J13: GL-CodeReview | L13: =IFERROR(K13/K4,"") -> 0 | N13: GL-CodeReview | P13: =IFERROR(O13/O4,"")
B14: GL-Technical Debt | D14: =IFERROR(C14/C4,"") | F14: GL-Technical Debt | H14: =IFERROR(G14/G4,"") | J14: GL-Technical Debt | L14: =IFERROR(K14/K4,"") -> 0 | N14: GL-Technical Debt | P14: =IFERROR(O14/O4,"")
B15: GL-Interne Tools | D15: =IFERROR(C15/C4,"") | F15: GL-Interne Tools | H15: =IFERROR(G15/G4,"") | J15: GL-Interne Tools | L15: =IFERROR(K15/K4,"") -> 0 | N15: GL-Interne Tools | P15: =IFERROR(O15/O4,"")
B17: Projekttitel | C17: Größe | D17: Value | F17: Projekttitel | G17: Größe | H17: Value | J17: Projekttitel | K17: Größe | L17: Value | N17: Projekttitel | O17: Größe | P17: Value
F18: =IFERROR(INDEX(DATA2026!B$2:B$401,MATCH(1,DATA2026!J$2:J$401,0)),"") -> Apple iOS SDK Anforderungen | G18: =IFERROR(INDEX(DATA2026!C$2:C$401,MATCH(1,DATA2026!J$2:J$401,0)),"") -> XL (>40h) | H18: =IFERROR(INDEX(DATA2026!D$2:D$401,MATCH(1,DATA2026!J$2:J$401,0)),"") -> Repair | J18: =IFERROR(INDEX(DATA2026!B$2:B$401,MATCH(1,DATA2026!K$2:K$401,0)),"") -> GitHub - Umstellung | K18: =IFERROR(INDEX(DATA2026!C$2:C$401,MATCH(1,DATA2026!K$2:K$401,0)),"") -> L (20-40h) | L18: =IFERROR(INDEX(DATA2026!D$2:D$401,MATCH(1,DATA2026!K$2:K$401,0)),"") -> Strengthen | N18: =IFERROR(INDEX(DATA2026!B$2:B$401,MATCH(1,DATA2026!L$2:L$401,0)),"") -> ReFund Zahlung POS | Refund bei Adyen | Pfand-Gutschrift bei Kartenzahlung | O18: =IFERROR(INDEX(DATA2026!C$2:C$401,MATCH(1,DATA2026!L$2:L$401,0)),"") -> 0 | P18: =IFERROR(INDEX(DATA2026!D$2:D$401,MATCH(1,DATA2026!L$2:L$401,0)),"") -> 0
B19: =IFERROR(INDEX(DATA2026!B$2:B$401,MATCH(2,DATA2026!I$2:I$401,0)),"") | C19: =IFERROR(INDEX(DATA2026!C$2:C$401,MATCH(2,DATA2026!I$2:I$401,0)),"") | D19: =IFERROR(INDEX(DATA2026!D$2:D$401,MATCH(2,DATA2026!I$2:I$401,0)),"") | F19: =IFERROR(INDEX(DATA2026!B$2:B$401,MATCH(2,DATA2026!J$2:J$401,0)),"") -> mobilePeople.de - Vulnerabilitys Portal Live | G19: =IFERROR(INDEX(DATA2026!C$2:C$401,MATCH(2,DATA2026!J$2:J$401,0)),"") -> XL (>40h) | H19: =IFERROR(INDEX(DATA2026!D$2:D$401,MATCH(2,DATA2026!J$2:J$401,0)),"") -> Repair | J19: =IFERROR(INDEX(DATA2026!B$2:B$401,MATCH(2,DATA2026!K$2:K$401,0)),"") -> EFSTA - Anbindung (Spanien) | K19: =IFERROR(INDEX(DATA2026!C$2:C$401,MATCH(2,DATA2026!K$2:K$401,0)),"") -> L (20-40h) | L19: =IFERROR(INDEX(DATA2026!D$2:D$401,MATCH(2,DATA2026!K$2:K$401,0)),"") -> Strengthen | N19: =IFERROR(INDEX(DATA2026!B$2:B$401,MATCH(2,DATA2026!L$2:L$401,0)),"") -> Abholmonitor (ggf. extern) | API | O19: =IFERROR(INDEX(DATA2026!C$2:C$401,MATCH(2,DATA2026!L$2:L$401,0)),"") -> 0 | P19: =IFERROR(INDEX(DATA2026!D$2:D$401,MATCH(2,DATA2026!L$2:L$401,0)),"") -> 0
B20: =IFERROR(INDEX(DATA2026!B$2:B$401,MATCH(3,DATA2026!I$2:I$401,0)),"") | C20: =IFERROR(INDEX(DATA2026!C$2:C$401,MATCH(3,DATA2026!I$2:I$401,0)),"") | D20: =IFERROR(INDEX(DATA2026!D$2:D$401,MATCH(3,DATA2026!I$2:I$401,0)),"") | F20: =IFERROR(INDEX(DATA2026!B$2:B$401,MATCH(3,DATA2026!J$2:J$401,0)),"") -> Webshop mit Newsletter Zustimmung | G20: =IFERROR(INDEX(DATA2026!C$2:C$401,MATCH(3,DATA2026!J$2:J$401,0)),"") -> M (10-20h) | H20: =IFERROR(INDEX(DATA2026!D$2:D$401,MATCH(3,DATA2026!J$2:J$401,0)),"") -> Strengthen | J20: =IFERROR(INDEX(DATA2026!B$2:B$401,MATCH(3,DATA2026!K$2:K$401,0)),"") -> DSFinV-K | Startdatum der ersten Buchung | K20: =IFERROR(INDEX(DATA2026!C$2:C$401,MATCH(3,DATA2026!K$2:K$401,0)),"") -> M (10-20h) | L20: =IFERROR(INDEX(DATA2026!D$2:D$401,MATCH(3,DATA2026!K$2:K$401,0)),"") -> Repair | N20: =IFERROR(INDEX(DATA2026!B$2:B$401,MATCH(3,DATA2026!L$2:L$401,0)),"") -> Portal & POS - UX Update (1) | O20: =IFERROR(INDEX(DATA2026!C$2:C$401,MATCH(3,DATA2026!L$2:L$401,0)),"") -> 0 | P20: =IFERROR(INDEX(DATA2026!D$2:D$401,MATCH(3,DATA2026!L$2:L$401,0)),"") -> 0
B21: =IFERROR(INDEX(DATA2026!B$2:B$401,MATCH(4,DATA2026!I$2:I$401,0)),"") | C21: =IFERROR(INDEX(DATA2026!C$2:C$401,MATCH(4,DATA2026!I$2:I$401,0)),"") | D21: =IFERROR(INDEX(DATA2026!D$2:D$401,MATCH(4,DATA2026!I$2:I$401,0)),"") | F21: =IFERROR(INDEX(DATA2026!B$2:B$401,MATCH(4,DATA2026!J$2:J$401,0)),"") -> Ticketshop mit Kalender & Anzahl | G21: =IFERROR(INDEX(DATA2026!C$2:C$401,MATCH(4,DATA2026!J$2:J$401,0)),"") -> M (10-20h) | H21: =IFERROR(INDEX(DATA2026!D$2:D$401,MATCH(4,DATA2026!J$2:J$401,0)),"") -> Strengthen | J21: =IFERROR(INDEX(DATA2026!B$2:B$401,MATCH(4,DATA2026!K$2:K$401,0)),"") -> Webhook Deliverect | K21: =IFERROR(INDEX(DATA2026!C$2:C$401,MATCH(4,DATA2026!K$2:K$401,0)),"") -> L (20-40h) | L21: =IFERROR(INDEX(DATA2026!D$2:D$401,MATCH(4,DATA2026!K$2:K$401,0)),"") -> Strengthen | N21: =IFERROR(INDEX(DATA2026!B$2:B$401,MATCH(4,DATA2026!L$2:L$401,0)),"") -> Artikelbestandteile im eCom abwählen | O21: =IFERROR(INDEX(DATA2026!C$2:C$401,MATCH(4,DATA2026!L$2:L$401,0)),"") -> 0 | P21: =IFERROR(INDEX(DATA2026!D$2:D$401,MATCH(4,DATA2026!L$2:L$401,0)),"") -> 0
B22: =IFERROR(INDEX(DATA2026!B$2:B$401,MATCH(5,DATA2026!I$2:I$401,0)),"") | C22: =IFERROR(INDEX(DATA2026!C$2:C$401,MATCH(5,DATA2026!I$2:I$401,0)),"") | D22: =IFERROR(INDEX(DATA2026!D$2:D$401,MATCH(5,DATA2026!I$2:I$401,0)),"") | F22: =IFERROR(INDEX(DATA2026!B$2:B$401,MATCH(5,DATA2026!J$2:J$401,0)),"") -> Optimierung SOT Sync | G22: =IFERROR(INDEX(DATA2026!C$2:C$401,MATCH(5,DATA2026!J$2:J$401,0)),"") -> L (20-40h) | H22: =IFERROR(INDEX(DATA2026!D$2:D$401,MATCH(5,DATA2026!J$2:J$401,0)),"") -> Repair | J22: =IFERROR(INDEX(DATA2026!B$2:B$401,MATCH(5,DATA2026!K$2:K$401,0)),"") -> MwSt. Verteilung | K22: =IFERROR(INDEX(DATA2026!C$2:C$401,MATCH(5,DATA2026!K$2:K$401,0)),"") -> XXL (>160h) | L22: =IFERROR(INDEX(DATA2026!D$2:D$401,MATCH(5,DATA2026!K$2:K$401,0)),"") -> Strengthen | N22: =IFERROR(INDEX(DATA2026!B$2:B$401,MATCH(5,DATA2026!L$2:L$401,0)),"") -> KPI Dashboard mit KI | O22: =IFERROR(INDEX(DATA2026!C$2:C$401,MATCH(5,DATA2026!L$2:L$401,0)),"") -> 0 | P22: =IFERROR(INDEX(DATA2026!D$2:D$401,MATCH(5,DATA2026!L$2:L$401,0)),"") -> 0
B23: =IFERROR(INDEX(DATA2026!B$2:B$401,MATCH(6,DATA2026!I$2:I$401,0)),"") | C23: =IFERROR(INDEX(DATA2026!C$2:C$401,MATCH(6,DATA2026!I$2:I$401,0)),"") | D23: =IFERROR(INDEX(DATA2026!D$2:D$401,MATCH(6,DATA2026!I$2:I$401,0)),"") | F23: =IFERROR(INDEX(DATA2026!B$2:B$401,MATCH(6,DATA2026!J$2:J$401,0)),"") -> UHD | AI Agent - Support | G23: =IFERROR(INDEX(DATA2026!C$2:C$401,MATCH(6,DATA2026!J$2:J$401,0)),"") -> L (20-40h) | H23: =IFERROR(INDEX(DATA2026!D$2:D$401,MATCH(6,DATA2026!J$2:J$401,0)),"") -> Strengthen | J23: =IFERROR(INDEX(DATA2026!B$2:B$401,MATCH(6,DATA2026!K$2:K$401,0)),"") -> Protokollierung bei Lizenzzuweisungen. (Internal Audit) | K23: =IFERROR(INDEX(DATA2026!C$2:C$401,MATCH(6,DATA2026!K$2:K$401,0)),"") -> XL (>40h) | L23: =IFERROR(INDEX(DATA2026!D$2:D$401,MATCH(6,DATA2026!K$2:K$401,0)),"") -> Repair | N23: =IFERROR(INDEX(DATA2026!B$2:B$401,MATCH(6,DATA2026!L$2:L$401,0)),"") -> Loyalty (4) | DataWarehouse und KI NOCH NICHT GEPLANT | O23: =IFERROR(INDEX(DATA2026!C$2:C$401,MATCH(6,DATA2026!L$2:L$401,0)),"") -> 0 | P23: =IFERROR(INDEX(DATA2026!D$2:D$401,MATCH(6,DATA2026!L$2:L$401,0)),"") -> 0
B24: =IFERROR(INDEX(DATA2026!B$2:B$401,MATCH(7,DATA2026!I$2:I$401,0)),"") | C24: =IFERROR(INDEX(DATA2026!C$2:C$401,MATCH(7,DATA2026!I$2:I$401,0)),"") | D24: =IFERROR(INDEX(DATA2026!D$2:D$401,MATCH(7,DATA2026!I$2:I$401,0)),"") | F24: =IFERROR(INDEX(DATA2026!B$2:B$401,MATCH(7,DATA2026!J$2:J$401,0)),"") -> 3rd Party - Google Log In für APP | G24: =IFERROR(INDEX(DATA2026!C$2:C$401,MATCH(7,DATA2026!J$2:J$401,0)),"") -> M (10-20h) | H24: =IFERROR(INDEX(DATA2026!D$2:D$401,MATCH(7,DATA2026!J$2:J$401,0)),"") -> Repair | J24: =IFERROR(INDEX(DATA2026!B$2:B$401,MATCH(7,DATA2026!K$2:K$401,0)),"") -> Trinkgeldentnahme signieren (ALEX-GRUPPE) | K24: =IFERROR(INDEX(DATA2026!C$2:C$401,MATCH(7,DATA2026!K$2:K$401,0)),"") -> L (20-40h) | L24: =IFERROR(INDEX(DATA2026!D$2:D$401,MATCH(7,DATA2026!K$2:K$401,0)),"") -> Strengthen | N24: =IFERROR(INDEX(DATA2026!B$2:B$401,MATCH(7,DATA2026!L$2:L$401,0)),"") -> Jouney Gaps (3) | O24: =IFERROR(INDEX(DATA2026!C$2:C$401,MATCH(7,DATA2026!L$2:L$401,0)),"") -> 0 | P24: =IFERROR(INDEX(DATA2026!D$2:D$401,MATCH(7,DATA2026!L$2:L$401,0)),"") -> 0
B25: =IFERROR(INDEX(DATA2026!B$2:B$401,MATCH(8,DATA2026!I$2:I$401,0)),"") | C25: =IFERROR(INDEX(DATA2026!C$2:C$401,MATCH(8,DATA2026!I$2:I$401,0)),"") | D25: =IFERROR(INDEX(DATA2026!D$2:D$401,MATCH(8,DATA2026!I$2:I$401,0)),"") | F25: =IFERROR(INDEX(DATA2026!B$2:B$401,MATCH(8,DATA2026!J$2:J$401,0)),"") -> SIG#156 Landingpage -> Bonuspunkte anzeigen | G25: =IFERROR(INDEX(DATA2026!C$2:C$401,MATCH(8,DATA2026!J$2:J$401,0)),"") -> M (10-20h) | H25: =IFERROR(INDEX(DATA2026!D$2:D$401,MATCH(8,DATA2026!J$2:J$401,0)),"") -> Strengthen | J25: =IFERROR(INDEX(DATA2026!B$2:B$401,MATCH(8,DATA2026!K$2:K$401,0)),"") -> ePOS mobilePRO | K25: =IFERROR(INDEX(DATA2026!C$2:C$401,MATCH(8,DATA2026!K$2:K$401,0)),"") -> XXL (>160h) | L25: =IFERROR(INDEX(DATA2026!D$2:D$401,MATCH(8,DATA2026!K$2:K$401,0)),"") -> Strengthen | N25: =IFERROR(INDEX(DATA2026!B$2:B$401,MATCH(8,DATA2026!L$2:L$401,0)),"") -> Artikelgenaue Übergabe an PMS-Interface (MEWS) | O25: =IFERROR(INDEX(DATA2026!C$2:C$401,MATCH(8,DATA2026!L$2:L$401,0)),"") -> 0 | P25: =IFERROR(INDEX(DATA2026!D$2:D$401,MATCH(8,DATA2026!L$2:L$401,0)),"") -> Strengthen
B26: =IFERROR(INDEX(DATA2026!B$2:B$401,MATCH(9,DATA2026!I$2:I$401,0)),"") | C26: =IFERROR(INDEX(DATA2026!C$2:C$401,MATCH(9,DATA2026!I$2:I$401,0)),"") | D26: =IFERROR(INDEX(DATA2026!D$2:D$401,MATCH(9,DATA2026!I$2:I$401,0)),"") | F26: =IFERROR(INDEX(DATA2026!B$2:B$401,MATCH(9,DATA2026!J$2:J$401,0)),"") -> iCoupon | G26: =IFERROR(INDEX(DATA2026!C$2:C$401,MATCH(9,DATA2026!J$2:J$401,0)),"") -> M (10-20h) | H26: =IFERROR(INDEX(DATA2026!D$2:D$401,MATCH(9,DATA2026!J$2:J$401,0)),"") -> Strengthen | J26: =IFERROR(INDEX(DATA2026!B$2:B$401,MATCH(9,DATA2026!K$2:K$401,0)),"") -> SOT/Webshop & POS | Grundlage / Basis der Kundenkarte QR-Code zur Identifikation | K26: =IFERROR(INDEX(DATA2026!C$2:C$401,MATCH(9,DATA2026!K$2:K$401,0)),"") -> XL (>40h) | L26: =IFERROR(INDEX(DATA2026!D$2:D$401,MATCH(9,DATA2026!K$2:K$401,0)),"") -> Innovation | N26: =IFERROR(INDEX(DATA2026!B$2:B$401,MATCH(9,DATA2026!L$2:L$401,0)),"") -> ePOS Campaigns | O26: =IFERROR(INDEX(DATA2026!C$2:C$401,MATCH(9,DATA2026!L$2:L$401,0)),"") -> 0 | P26: =IFERROR(INDEX(DATA2026!D$2:D$401,MATCH(9,DATA2026!L$2:L$401,0)),"") -> Repair
B27: =IFERROR(INDEX(DATA2026!B$2:B$401,MATCH(10,DATA2026!I$2:I$401,0)),"") | C27: =IFERROR(INDEX(DATA2026!C$2:C$401,MATCH(10,DATA2026!I$2:I$401,0)),"") | D27: =IFERROR(INDEX(DATA2026!D$2:D$401,MATCH(10,DATA2026!I$2:I$401,0)),"") | F27: =IFERROR(INDEX(DATA2026!B$2:B$401,MATCH(10,DATA2026!J$2:J$401,0)),"") -> Supportreduzierung: / Kontingent definieren | G27: =IFERROR(INDEX(DATA2026!C$2:C$401,MATCH(10,DATA2026!J$2:J$401,0)),"") -> XXL (>160h) | H27: =IFERROR(INDEX(DATA2026!D$2:D$401,MATCH(10,DATA2026!J$2:J$401,0)),"") -> Repair | J27: =IFERROR(INDEX(DATA2026!B$2:B$401,MATCH(10,DATA2026!K$2:K$401,0)),"") -> Benefits am SOT einlösen | K27: =IFERROR(INDEX(DATA2026!C$2:C$401,MATCH(10,DATA2026!K$2:K$401,0)),"") -> L (20-40h) | L27: =IFERROR(INDEX(DATA2026!D$2:D$401,MATCH(10,DATA2026!K$2:K$401,0)),"") -> Strengthen | N27: =IFERROR(INDEX(DATA2026!B$2:B$401,MATCH(10,DATA2026!L$2:L$401,0)),"") -> Deaktivierung von Order Channel an POS | O27: =IFERROR(INDEX(DATA2026!C$2:C$401,MATCH(10,DATA2026!L$2:L$401,0)),"") -> 0 | P27: =IFERROR(INDEX(DATA2026!D$2:D$401,MATCH(10,DATA2026!L$2:L$401,0)),"") -> Innovation
B28: =IFERROR(INDEX(DATA2026!B$2:B$401,MATCH(11,DATA2026!I$2:I$401,0)),"") | C28: =IFERROR(INDEX(DATA2026!C$2:C$401,MATCH(11,DATA2026!I$2:I$401,0)),"") | D28: =IFERROR(INDEX(DATA2026!D$2:D$401,MATCH(11,DATA2026!I$2:I$401,0)),"") | F28: =IFERROR(INDEX(DATA2026!B$2:B$401,MATCH(11,DATA2026!J$2:J$401,0)),"") -> Actian Umstellung | G28: =IFERROR(INDEX(DATA2026!C$2:C$401,MATCH(11,DATA2026!J$2:J$401,0)),"") -> XXL (>160h) | H28: =IFERROR(INDEX(DATA2026!D$2:D$401,MATCH(11,DATA2026!J$2:J$401,0)),"") -> Repair | J28: =IFERROR(INDEX(DATA2026!B$2:B$401,MATCH(11,DATA2026!K$2:K$401,0)),"") -> UHD | Rechnungsstellung in CHF | K28: =IFERROR(INDEX(DATA2026!C$2:C$401,MATCH(11,DATA2026!K$2:K$401,0)),"") -> L (20-40h) | L28: =IFERROR(INDEX(DATA2026!D$2:D$401,MATCH(11,DATA2026!K$2:K$401,0)),"") -> Strengthen | N28: =IFERROR(INDEX(DATA2026!B$2:B$401,MATCH(11,DATA2026!L$2:L$401,0)),"") -> Accounting in YourAPP | O28: =IFERROR(INDEX(DATA2026!C$2:C$401,MATCH(11,DATA2026!L$2:L$401,0)),"") -> 0 | P28: =IFERROR(INDEX(DATA2026!D$2:D$401,MATCH(11,DATA2026!L$2:L$401,0)),"") -> Innovation
B29: =IFERROR(INDEX(DATA2026!B$2:B$401,MATCH(12,DATA2026!I$2:I$401,0)),"") | C29: =IFERROR(INDEX(DATA2026!C$2:C$401,MATCH(12,DATA2026!I$2:I$401,0)),"") | D29: =IFERROR(INDEX(DATA2026!D$2:D$401,MATCH(12,DATA2026!I$2:I$401,0)),"") | F29: =IFERROR(INDEX(DATA2026!B$2:B$401,MATCH(12,DATA2026!J$2:J$401,0)),"") -> ePOS mobile PRO V1 | G29: =IFERROR(INDEX(DATA2026!C$2:C$401,MATCH(12,DATA2026!J$2:J$401,0)),"") -> XL (>40h) | H29: =IFERROR(INDEX(DATA2026!D$2:D$401,MATCH(12,DATA2026!J$2:J$401,0)),"") -> Innovation | J29: =IFERROR(INDEX(DATA2026!B$2:B$401,MATCH(12,DATA2026!K$2:K$401,0)),"") -> UHD | Filtermöglichkeit für „Priorisierung“ | K29: =IFERROR(INDEX(DATA2026!C$2:C$401,MATCH(12,DATA2026!K$2:K$401,0)),"") -> L (20-40h) | L29: =IFERROR(INDEX(DATA2026!D$2:D$401,MATCH(12,DATA2026!K$2:K$401,0)),"") -> Strengthen | N29: =IFERROR(INDEX(DATA2026!B$2:B$401,MATCH(12,DATA2026!L$2:L$401,0)),"") -> Signum Orga-Soft API erweitern | O29: =IFERROR(INDEX(DATA2026!C$2:C$401,MATCH(12,DATA2026!L$2:L$401,0)),"") -> 0 | P29: =IFERROR(INDEX(DATA2026!D$2:D$401,MATCH(12,DATA2026!L$2:L$401,0)),"") -> Strengthen
B30: =IFERROR(INDEX(DATA2026!B$2:B$401,MATCH(13,DATA2026!I$2:I$401,0)),"") | C30: =IFERROR(INDEX(DATA2026!C$2:C$401,MATCH(13,DATA2026!I$2:I$401,0)),"") | D30: =IFERROR(INDEX(DATA2026!D$2:D$401,MATCH(13,DATA2026!I$2:I$401,0)),"") | F30: =IFERROR(INDEX(DATA2026!B$2:B$401,MATCH(13,DATA2026!J$2:J$401,0)),"") -> Artikel-Tabellenbearbeitung auch Bilder (Shop) hinzufügen | G30: =IFERROR(INDEX(DATA2026!C$2:C$401,MATCH(13,DATA2026!J$2:J$401,0)),"") -> M (10-20h) | H30: =IFERROR(INDEX(DATA2026!D$2:D$401,MATCH(13,DATA2026!J$2:J$401,0)),"") -> Strengthen | J30: =IFERROR(INDEX(DATA2026!B$2:B$401,MATCH(13,DATA2026!K$2:K$401,0)),"") -> UHD | Bearbeiter ergänzen / anzeigen | K30: =IFERROR(INDEX(DATA2026!C$2:C$401,MATCH(13,DATA2026!K$2:K$401,0)),"") -> L (20-40h) | L30: =IFERROR(INDEX(DATA2026!D$2:D$401,MATCH(13,DATA2026!K$2:K$401,0)),"") -> Strengthen | N30: =IFERROR(INDEX(DATA2026!B$2:B$401,MATCH(13,DATA2026!L$2:L$401,0)),"") -> Loyalty (3) | Couopons 2.0 NOCH NICHT GEPLANT | O30: =IFERROR(INDEX(DATA2026!C$2:C$401,MATCH(13,DATA2026!L$2:L$401,0)),"") -> 0 | P30: =IFERROR(INDEX(DATA2026!D$2:D$401,MATCH(13,DATA2026!L$2:L$401,0)),"") -> Innovation
B31: =IFERROR(INDEX(DATA2026!B$2:B$401,MATCH(14,DATA2026!I$2:I$401,0)),"") | C31: =IFERROR(INDEX(DATA2026!C$2:C$401,MATCH(14,DATA2026!I$2:I$401,0)),"") | D31: =IFERROR(INDEX(DATA2026!D$2:D$401,MATCH(14,DATA2026!I$2:I$401,0)),"") | F31: =IFERROR(INDEX(DATA2026!B$2:B$401,MATCH(14,DATA2026!J$2:J$401,0)),"") -> DSFinV-K: Verknüpfung von Bestellsignaturen | G31: =IFERROR(INDEX(DATA2026!C$2:C$401,MATCH(14,DATA2026!J$2:J$401,0)),"") -> L (20-40h) | H31: =IFERROR(INDEX(DATA2026!D$2:D$401,MATCH(14,DATA2026!J$2:J$401,0)),"") -> Strengthen | J31: =IFERROR(INDEX(DATA2026!B$2:B$401,MATCH(14,DATA2026!K$2:K$401,0)),"") -> UHD | S, M, L im UH sichtbar/Filterbar. (Kritisch, Wichtig und Normal -> sichtbar) | K31: =IFERROR(INDEX(DATA2026!C$2:C$401,MATCH(14,DATA2026!K$2:K$401,0)),"") -> L (20-40h) | L31: =IFERROR(INDEX(DATA2026!D$2:D$401,MATCH(14,DATA2026!K$2:K$401,0)),"") -> Strengthen | N31: =IFERROR(INDEX(DATA2026!B$2:B$401,MATCH(14,DATA2026!L$2:L$401,0)),"") -> Data Warehouse | O31: =IFERROR(INDEX(DATA2026!C$2:C$401,MATCH(14,DATA2026!L$2:L$401,0)),"") -> 0 | P31: =IFERROR(INDEX(DATA2026!D$2:D$401,MATCH(14,DATA2026!L$2:L$401,0)),"") -> Strengthen
B32: =IFERROR(INDEX(DATA2026!B$2:B$401,MATCH(15,DATA2026!I$2:I$401,0)),"") | C32: =IFERROR(INDEX(DATA2026!C$2:C$401,MATCH(15,DATA2026!I$2:I$401,0)),"") | D32: =IFERROR(INDEX(DATA2026!D$2:D$401,MATCH(15,DATA2026!I$2:I$401,0)),"") | F32: =IFERROR(INDEX(DATA2026!B$2:B$401,MATCH(15,DATA2026!J$2:J$401,0)),"") | G32: =IFERROR(INDEX(DATA2026!C$2:C$401,MATCH(15,DATA2026!J$2:J$401,0)),"") | H32: =IFERROR(INDEX(DATA2026!D$2:D$401,MATCH(15,DATA2026!J$2:J$401,0)),"") | J32: =IFERROR(INDEX(DATA2026!B$2:B$401,MATCH(15,DATA2026!K$2:K$401,0)),"") -> Loaylty | Bonussystem 2.0 | K32: =IFERROR(INDEX(DATA2026!C$2:C$401,MATCH(15,DATA2026!K$2:K$401,0)),"") -> XXL (>160h) | L32: =IFERROR(INDEX(DATA2026!D$2:D$401,MATCH(15,DATA2026!K$2:K$401,0)),"") -> Innovation | N32: =IFERROR(INDEX(DATA2026!B$2:B$401,MATCH(15,DATA2026!L$2:L$401,0)),"") -> Paypal V2 | O32: =IFERROR(INDEX(DATA2026!C$2:C$401,MATCH(15,DATA2026!L$2:L$401,0)),"") -> 0 | P32: =IFERROR(INDEX(DATA2026!D$2:D$401,MATCH(15,DATA2026!L$2:L$401,0)),"") -> Strengthen
B33: =IFERROR(INDEX(DATA2026!B$2:B$401,MATCH(16,DATA2026!I$2:I$401,0)),"") | C33: =IFERROR(INDEX(DATA2026!C$2:C$401,MATCH(16,DATA2026!I$2:I$401,0)),"") | D33: =IFERROR(INDEX(DATA2026!D$2:D$401,MATCH(16,DATA2026!I$2:I$401,0)),"") | F33: =IFERROR(INDEX(DATA2026!B$2:B$401,MATCH(16,DATA2026!J$2:J$401,0)),"") | G33: =IFERROR(INDEX(DATA2026!C$2:C$401,MATCH(16,DATA2026!J$2:J$401,0)),"") | H33: =IFERROR(INDEX(DATA2026!D$2:D$401,MATCH(16,DATA2026!J$2:J$401,0)),"") | J33: =IFERROR(INDEX(DATA2026!B$2:B$401,MATCH(16,DATA2026!K$2:K$401,0)),"") -> Wallet-Anbindung iOS & Android | Web Gutscheine und Tickets | K33: =IFERROR(INDEX(DATA2026!C$2:C$401,MATCH(16,DATA2026!K$2:K$401,0)),"") -> XL (>40h) | L33: =IFERROR(INDEX(DATA2026!D$2:D$401,MATCH(16,DATA2026!K$2:K$401,0)),"") -> Innovation | N33: =IFERROR(INDEX(DATA2026!B$2:B$401,MATCH(16,DATA2026!L$2:L$401,0)),"") -> App-Systemstart beschleunigen / Code aktualisieren | O33: =IFERROR(INDEX(DATA2026!C$2:C$401,MATCH(16,DATA2026!L$2:L$401,0)),"") -> 0 | P33: =IFERROR(INDEX(DATA2026!D$2:D$401,MATCH(16,DATA2026!L$2:L$401,0)),"") -> Strengthen
B34: =IFERROR(INDEX(DATA2026!B$2:B$401,MATCH(17,DATA2026!I$2:I$401,0)),"") | C34: =IFERROR(INDEX(DATA2026!C$2:C$401,MATCH(17,DATA2026!I$2:I$401,0)),"") | D34: =IFERROR(INDEX(DATA2026!D$2:D$401,MATCH(17,DATA2026!I$2:I$401,0)),"") | F34: =IFERROR(INDEX(DATA2026!B$2:B$401,MATCH(17,DATA2026!J$2:J$401,0)),"") | G34: =IFERROR(INDEX(DATA2026!C$2:C$401,MATCH(17,DATA2026!J$2:J$401,0)),"") | H34: =IFERROR(INDEX(DATA2026!D$2:D$401,MATCH(17,DATA2026!J$2:J$401,0)),"") | J34: =IFERROR(INDEX(DATA2026!B$2:B$401,MATCH(17,DATA2026!K$2:K$401,0)),"") -> API | Externer Kundenstamm | K34: =IFERROR(INDEX(DATA2026!C$2:C$401,MATCH(17,DATA2026!K$2:K$401,0)),"") -> L (20-40h) | L34: =IFERROR(INDEX(DATA2026!D$2:D$401,MATCH(17,DATA2026!K$2:K$401,0)),"") -> Strengthen | N34: =IFERROR(INDEX(DATA2026!B$2:B$401,MATCH(17,DATA2026!L$2:L$401,0)),"") -> SIG - WAWI - Schnittstelle (Foodnotify / Apicbase) -> CDS & Vapiano | O34: =IFERROR(INDEX(DATA2026!C$2:C$401,MATCH(17,DATA2026!L$2:L$401,0)),"") -> 0 | P34: =IFERROR(INDEX(DATA2026!D$2:D$401,MATCH(17,DATA2026!L$2:L$401,0)),"") -> Innovation
B35: =IFERROR(INDEX(DATA2026!B$2:B$401,MATCH(18,DATA2026!I$2:I$401,0)),"") | C35: =IFERROR(INDEX(DATA2026!C$2:C$401,MATCH(18,DATA2026!I$2:I$401,0)),"") | D35: =IFERROR(INDEX(DATA2026!D$2:D$401,MATCH(18,DATA2026!I$2:I$401,0)),"") | F35: =IFERROR(INDEX(DATA2026!B$2:B$401,MATCH(18,DATA2026!J$2:J$401,0)),"") | G35: =IFERROR(INDEX(DATA2026!C$2:C$401,MATCH(18,DATA2026!J$2:J$401,0)),"") | H35: =IFERROR(INDEX(DATA2026!D$2:D$401,MATCH(18,DATA2026!J$2:J$401,0)),"") | J35: =IFERROR(INDEX(DATA2026!B$2:B$401,MATCH(18,DATA2026!K$2:K$401,0)),"") -> TWINT / Konstantin / HILTL | K35: =IFERROR(INDEX(DATA2026!C$2:C$401,MATCH(18,DATA2026!K$2:K$401,0)),"") -> M (10-20h) | L35: =IFERROR(INDEX(DATA2026!D$2:D$401,MATCH(18,DATA2026!K$2:K$401,0)),"") -> Repair | N35: =IFERROR(INDEX(DATA2026!B$2:B$401,MATCH(18,DATA2026!L$2:L$401,0)),"") -> NoCOO Code am SOT mit optionalem Ausdruck / weitere Informationen müssen ergänzt werden (Superhelden, etc.) -> Bewerten Q3 | O35: =IFERROR(INDEX(DATA2026!C$2:C$401,MATCH(18,DATA2026!L$2:L$401,0)),"") -> 0 | P35: =IFERROR(INDEX(DATA2026!D$2:D$401,MATCH(18,DATA2026!L$2:L$401,0)),"") -> Strengthen
B36: =IFERROR(INDEX(DATA2026!B$2:B$401,MATCH(19,DATA2026!I$2:I$401,0)),"") | C36: =IFERROR(INDEX(DATA2026!C$2:C$401,MATCH(19,DATA2026!I$2:I$401,0)),"") | D36: =IFERROR(INDEX(DATA2026!D$2:D$401,MATCH(19,DATA2026!I$2:I$401,0)),"") | F36: =IFERROR(INDEX(DATA2026!B$2:B$401,MATCH(19,DATA2026!J$2:J$401,0)),"") | G36: =IFERROR(INDEX(DATA2026!C$2:C$401,MATCH(19,DATA2026!J$2:J$401,0)),"") | H36: =IFERROR(INDEX(DATA2026!D$2:D$401,MATCH(19,DATA2026!J$2:J$401,0)),"") | J36: =IFERROR(INDEX(DATA2026!B$2:B$401,MATCH(19,DATA2026!K$2:K$401,0)),"") -> OpenTable API | K36: =IFERROR(INDEX(DATA2026!C$2:C$401,MATCH(19,DATA2026!K$2:K$401,0)),"") -> M (10-20h) | L36: =IFERROR(INDEX(DATA2026!D$2:D$401,MATCH(19,DATA2026!K$2:K$401,0)),"") -> Innovation | N36: =IFERROR(INDEX(DATA2026!B$2:B$401,MATCH(19,DATA2026!L$2:L$401,0)),"") -> Borland Code Migrieren in Visual Studio - bis Q4 muss das umgesetzt werden | O36: =IFERROR(INDEX(DATA2026!C$2:C$401,MATCH(19,DATA2026!L$2:L$401,0)),"") -> 0 | P36: =IFERROR(INDEX(DATA2026!D$2:D$401,MATCH(19,DATA2026!L$2:L$401,0)),"") -> Strengthen
B37: =IFERROR(INDEX(DATA2026!B$2:B$401,MATCH(20,DATA2026!I$2:I$401,0)),"") | C37: =IFERROR(INDEX(DATA2026!C$2:C$401,MATCH(20,DATA2026!I$2:I$401,0)),"") | D37: =IFERROR(INDEX(DATA2026!D$2:D$401,MATCH(20,DATA2026!I$2:I$401,0)),"") | F37: =IFERROR(INDEX(DATA2026!B$2:B$401,MATCH(20,DATA2026!J$2:J$401,0)),"") | G37: =IFERROR(INDEX(DATA2026!C$2:C$401,MATCH(20,DATA2026!J$2:J$401,0)),"") | H37: =IFERROR(INDEX(DATA2026!D$2:D$401,MATCH(20,DATA2026!J$2:J$401,0)),"") | J37: =IFERROR(INDEX(DATA2026!B$2:B$401,MATCH(20,DATA2026!K$2:K$401,0)),"") -> UHD | Incident Feedback an Kunde | K37: =IFERROR(INDEX(DATA2026!C$2:C$401,MATCH(20,DATA2026!K$2:K$401,0)),"") -> L (20-40h) | L37: =IFERROR(INDEX(DATA2026!D$2:D$401,MATCH(20,DATA2026!K$2:K$401,0)),"") -> Strengthen | N37: =IFERROR(INDEX(DATA2026!B$2:B$401,MATCH(20,DATA2026!L$2:L$401,0)),"") -> 64 Bit Konvertierung | O37: =IFERROR(INDEX(DATA2026!C$2:C$401,MATCH(20,DATA2026!L$2:L$401,0)),"") -> 0 | P37: =IFERROR(INDEX(DATA2026!D$2:D$401,MATCH(20,DATA2026!L$2:L$401,0)),"") -> Strengthen
B38: =IFERROR(INDEX(DATA2026!B$2:B$401,MATCH(21,DATA2026!I$2:I$401,0)),"") | C38: =IFERROR(INDEX(DATA2026!C$2:C$401,MATCH(21,DATA2026!I$2:I$401,0)),"") | D38: =IFERROR(INDEX(DATA2026!D$2:D$401,MATCH(21,DATA2026!I$2:I$401,0)),"") | F38: =IFERROR(INDEX(DATA2026!B$2:B$401,MATCH(21,DATA2026!J$2:J$401,0)),"") | G38: =IFERROR(INDEX(DATA2026!C$2:C$401,MATCH(21,DATA2026!J$2:J$401,0)),"") | H38: =IFERROR(INDEX(DATA2026!D$2:D$401,MATCH(21,DATA2026!J$2:J$401,0)),"") | J38: =IFERROR(INDEX(DATA2026!B$2:B$401,MATCH(21,DATA2026!K$2:K$401,0)),"") -> HeyRosi -> API | K38: =IFERROR(INDEX(DATA2026!C$2:C$401,MATCH(21,DATA2026!K$2:K$401,0)),"") -> M (10-20h) | L38: =IFERROR(INDEX(DATA2026!D$2:D$401,MATCH(21,DATA2026!K$2:K$401,0)),"") -> Innovation | N38: =IFERROR(INDEX(DATA2026!B$2:B$401,MATCH(21,DATA2026!L$2:L$401,0)),"") -> Webshop und erweiterte Zeitsteuerung (Artikel nicht verfügbar, bei Bestellung morgens für Mittags) -> CDS | O38: =IFERROR(INDEX(DATA2026!C$2:C$401,MATCH(21,DATA2026!L$2:L$401,0)),"") -> 0 | P38: =IFERROR(INDEX(DATA2026!D$2:D$401,MATCH(21,DATA2026!L$2:L$401,0)),"") -> Strengthen
B39: =IFERROR(INDEX(DATA2026!B$2:B$401,MATCH(22,DATA2026!I$2:I$401,0)),"") | C39: =IFERROR(INDEX(DATA2026!C$2:C$401,MATCH(22,DATA2026!I$2:I$401,0)),"") | D39: =IFERROR(INDEX(DATA2026!D$2:D$401,MATCH(22,DATA2026!I$2:I$401,0)),"") | F39: =IFERROR(INDEX(DATA2026!B$2:B$401,MATCH(22,DATA2026!J$2:J$401,0)),"") | G39: =IFERROR(INDEX(DATA2026!C$2:C$401,MATCH(22,DATA2026!J$2:J$401,0)),"") | H39: =IFERROR(INDEX(DATA2026!D$2:D$401,MATCH(22,DATA2026!J$2:J$401,0)),"") | J39: =IFERROR(INDEX(DATA2026!B$2:B$401,MATCH(22,DATA2026!K$2:K$401,0)),"") -> Landingpage zur Registrierung | K39: =IFERROR(INDEX(DATA2026!C$2:C$401,MATCH(22,DATA2026!K$2:K$401,0)),"") -> M (10-20h) | L39: =IFERROR(INDEX(DATA2026!D$2:D$401,MATCH(22,DATA2026!K$2:K$401,0)),"") -> Strengthen | N39: =IFERROR(INDEX(DATA2026!B$2:B$401,MATCH(22,DATA2026!L$2:L$401,0)),"") -> Digital Signage (Api) | O39: =IFERROR(INDEX(DATA2026!C$2:C$401,MATCH(22,DATA2026!L$2:L$401,0)),"") -> 0 | P39: =IFERROR(INDEX(DATA2026!D$2:D$401,MATCH(22,DATA2026!L$2:L$401,0)),"") -> Innovation
B40: =IFERROR(INDEX(DATA2026!B$2:B$401,MATCH(23,DATA2026!I$2:I$401,0)),"") | C40: =IFERROR(INDEX(DATA2026!C$2:C$401,MATCH(23,DATA2026!I$2:I$401,0)),"") | D40: =IFERROR(INDEX(DATA2026!D$2:D$401,MATCH(23,DATA2026!I$2:I$401,0)),"") | F40: =IFERROR(INDEX(DATA2026!B$2:B$401,MATCH(23,DATA2026!J$2:J$401,0)),"") | G40: =IFERROR(INDEX(DATA2026!C$2:C$401,MATCH(23,DATA2026!J$2:J$401,0)),"") | H40: =IFERROR(INDEX(DATA2026!D$2:D$401,MATCH(23,DATA2026!J$2:J$401,0)),"") | J40: =IFERROR(INDEX(DATA2026!B$2:B$401,MATCH(23,DATA2026!K$2:K$401,0)),"") -> UI / Code - Portalmodernisierung | Benutzer | K40: =IFERROR(INDEX(DATA2026!C$2:C$401,MATCH(23,DATA2026!K$2:K$401,0)),"") -> XXL (>160h) | L40: =IFERROR(INDEX(DATA2026!D$2:D$401,MATCH(23,DATA2026!K$2:K$401,0)),"") -> Strengthen | N40: =IFERROR(INDEX(DATA2026!B$2:B$401,MATCH(23,DATA2026!L$2:L$401,0)),"") -> 2-Faktor-Authentifizierung / Portal | O40: =IFERROR(INDEX(DATA2026!C$2:C$401,MATCH(23,DATA2026!L$2:L$401,0)),"") -> 0 | P40: =IFERROR(INDEX(DATA2026!D$2:D$401,MATCH(23,DATA2026!L$2:L$401,0)),"") -> Strengthen
B41: =IFERROR(INDEX(DATA2026!B$2:B$401,MATCH(24,DATA2026!I$2:I$401,0)),"") | C41: =IFERROR(INDEX(DATA2026!C$2:C$401,MATCH(24,DATA2026!I$2:I$401,0)),"") | D41: =IFERROR(INDEX(DATA2026!D$2:D$401,MATCH(24,DATA2026!I$2:I$401,0)),"") | F41: =IFERROR(INDEX(DATA2026!B$2:B$401,MATCH(24,DATA2026!J$2:J$401,0)),"") | G41: =IFERROR(INDEX(DATA2026!C$2:C$401,MATCH(24,DATA2026!J$2:J$401,0)),"") | H41: =IFERROR(INDEX(DATA2026!D$2:D$401,MATCH(24,DATA2026!J$2:J$401,0)),"") | J41: =IFERROR(INDEX(DATA2026!B$2:B$401,MATCH(24,DATA2026!K$2:K$401,0)),"") -> Einmal einlösbare Coupons für die YourApp | K41: =IFERROR(INDEX(DATA2026!C$2:C$401,MATCH(24,DATA2026!K$2:K$401,0)),"") -> XL (>40h) | L41: =IFERROR(INDEX(DATA2026!D$2:D$401,MATCH(24,DATA2026!K$2:K$401,0)),"") -> Strengthen | N41: =IFERROR(INDEX(DATA2026!B$2:B$401,MATCH(24,DATA2026!L$2:L$401,0)),"") -> UHD - RMA Digitalisieren | O41: =IFERROR(INDEX(DATA2026!C$2:C$401,MATCH(24,DATA2026!L$2:L$401,0)),"") -> 0 | P41: =IFERROR(INDEX(DATA2026!D$2:D$401,MATCH(24,DATA2026!L$2:L$401,0)),"") -> Strengthen
B42: =IFERROR(INDEX(DATA2026!B$2:B$401,MATCH(25,DATA2026!I$2:I$401,0)),"") | C42: =IFERROR(INDEX(DATA2026!C$2:C$401,MATCH(25,DATA2026!I$2:I$401,0)),"") | D42: =IFERROR(INDEX(DATA2026!D$2:D$401,MATCH(25,DATA2026!I$2:I$401,0)),"") | F42: =IFERROR(INDEX(DATA2026!B$2:B$401,MATCH(25,DATA2026!J$2:J$401,0)),"") | G42: =IFERROR(INDEX(DATA2026!C$2:C$401,MATCH(25,DATA2026!J$2:J$401,0)),"") | H42: =IFERROR(INDEX(DATA2026!D$2:D$401,MATCH(25,DATA2026!J$2:J$401,0)),"") | J42: =IFERROR(INDEX(DATA2026!B$2:B$401,MATCH(25,DATA2026!K$2:K$401,0)),"") -> KI-Prompt-Interface für den Desktop-UHD. Eventuell mittels "MCP" | K42: =IFERROR(INDEX(DATA2026!C$2:C$401,MATCH(25,DATA2026!K$2:K$401,0)),"") -> 0 | L42: =IFERROR(INDEX(DATA2026!D$2:D$401,MATCH(25,DATA2026!K$2:K$401,0)),"") -> 0 | N42: =IFERROR(INDEX(DATA2026!B$2:B$401,MATCH(25,DATA2026!L$2:L$401,0)),"") -> MobileEntry in das ePOS mobilePRO integrieren | O42: =IFERROR(INDEX(DATA2026!C$2:C$401,MATCH(25,DATA2026!L$2:L$401,0)),"") -> 0 | P42: =IFERROR(INDEX(DATA2026!D$2:D$401,MATCH(25,DATA2026!L$2:L$401,0)),"") -> 0
B43: =IFERROR(INDEX(DATA2026!B$2:B$401,MATCH(26,DATA2026!I$2:I$401,0)),"") | C43: =IFERROR(INDEX(DATA2026!C$2:C$401,MATCH(26,DATA2026!I$2:I$401,0)),"") | D43: =IFERROR(INDEX(DATA2026!D$2:D$401,MATCH(26,DATA2026!I$2:I$401,0)),"") | F43: =IFERROR(INDEX(DATA2026!B$2:B$401,MATCH(26,DATA2026!J$2:J$401,0)),"") | G43: =IFERROR(INDEX(DATA2026!C$2:C$401,MATCH(26,DATA2026!J$2:J$401,0)),"") | H43: =IFERROR(INDEX(DATA2026!D$2:D$401,MATCH(26,DATA2026!J$2:J$401,0)),"") | J43: =IFERROR(INDEX(DATA2026!B$2:B$401,MATCH(26,DATA2026!K$2:K$401,0)),"") -> Touchpoint-Lizensierung | K43: =IFERROR(INDEX(DATA2026!C$2:C$401,MATCH(26,DATA2026!K$2:K$401,0)),"") -> 0 | L43: =IFERROR(INDEX(DATA2026!D$2:D$401,MATCH(26,DATA2026!K$2:K$401,0)),"") -> 0 | N43: =IFERROR(INDEX(DATA2026!B$2:B$401,MATCH(26,DATA2026!L$2:L$401,0)),"") -> Andorid Anforderungen | O43: =IFERROR(INDEX(DATA2026!C$2:C$401,MATCH(26,DATA2026!L$2:L$401,0)),"") -> 0 | P43: =IFERROR(INDEX(DATA2026!D$2:D$401,MATCH(26,DATA2026!L$2:L$401,0)),"") -> 0
B44: =IFERROR(INDEX(DATA2026!B$2:B$401,MATCH(27,DATA2026!I$2:I$401,0)),"") | C44: =IFERROR(INDEX(DATA2026!C$2:C$401,MATCH(27,DATA2026!I$2:I$401,0)),"") | D44: =IFERROR(INDEX(DATA2026!D$2:D$401,MATCH(27,DATA2026!I$2:I$401,0)),"") | F44: =IFERROR(INDEX(DATA2026!B$2:B$401,MATCH(27,DATA2026!J$2:J$401,0)),"") | G44: =IFERROR(INDEX(DATA2026!C$2:C$401,MATCH(27,DATA2026!J$2:J$401,0)),"") | H44: =IFERROR(INDEX(DATA2026!D$2:D$401,MATCH(27,DATA2026!J$2:J$401,0)),"") | J44: =IFERROR(INDEX(DATA2026!B$2:B$401,MATCH(27,DATA2026!K$2:K$401,0)),"") | K44: =IFERROR(INDEX(DATA2026!C$2:C$401,MATCH(27,DATA2026!K$2:K$401,0)),"") | L44: =IFERROR(INDEX(DATA2026!D$2:D$401,MATCH(27,DATA2026!K$2:K$401,0)),"") | N44: =IFERROR(INDEX(DATA2026!B$2:B$401,MATCH(27,DATA2026!L$2:L$401,0)),"") -> Widerruf im Onlineshop (Pflicht ab 19.06.2026) | O44: =IFERROR(INDEX(DATA2026!C$2:C$401,MATCH(27,DATA2026!L$2:L$401,0)),"") -> 0 | P44: =IFERROR(INDEX(DATA2026!D$2:D$401,MATCH(27,DATA2026!L$2:L$401,0)),"") -> 0
B45: =IFERROR(INDEX(DATA2026!B$2:B$401,MATCH(28,DATA2026!I$2:I$401,0)),"") | C45: =IFERROR(INDEX(DATA2026!C$2:C$401,MATCH(28,DATA2026!I$2:I$401,0)),"") | D45: =IFERROR(INDEX(DATA2026!D$2:D$401,MATCH(28,DATA2026!I$2:I$401,0)),"") | F45: =IFERROR(INDEX(DATA2026!B$2:B$401,MATCH(28,DATA2026!J$2:J$401,0)),"") | G45: =IFERROR(INDEX(DATA2026!C$2:C$401,MATCH(28,DATA2026!J$2:J$401,0)),"") | H45: =IFERROR(INDEX(DATA2026!D$2:D$401,MATCH(28,DATA2026!J$2:J$401,0)),"") | J45: =IFERROR(INDEX(DATA2026!B$2:B$401,MATCH(28,DATA2026!K$2:K$401,0)),"") | K45: =IFERROR(INDEX(DATA2026!C$2:C$401,MATCH(28,DATA2026!K$2:K$401,0)),"") | L45: =IFERROR(INDEX(DATA2026!D$2:D$401,MATCH(28,DATA2026!K$2:K$401,0)),"") | N45: =IFERROR(INDEX(DATA2026!B$2:B$401,MATCH(28,DATA2026!L$2:L$401,0)),"") | O45: =IFERROR(INDEX(DATA2026!C$2:C$401,MATCH(28,DATA2026!L$2:L$401,0)),"") | P45: =IFERROR(INDEX(DATA2026!D$2:D$401,MATCH(28,DATA2026!L$2:L$401,0)),"")
B46: =IFERROR(INDEX(DATA2026!B$2:B$401,MATCH(29,DATA2026!I$2:I$401,0)),"") | C46: =IFERROR(INDEX(DATA2026!C$2:C$401,MATCH(29,DATA2026!I$2:I$401,0)),"") | D46: =IFERROR(INDEX(DATA2026!D$2:D$401,MATCH(29,DATA2026!I$2:I$401,0)),"") | F46: =IFERROR(INDEX(DATA2026!B$2:B$401,MATCH(29,DATA2026!J$2:J$401,0)),"") | G46: =IFERROR(INDEX(DATA2026!C$2:C$401,MATCH(29,DATA2026!J$2:J$401,0)),"") | H46: =IFERROR(INDEX(DATA2026!D$2:D$401,MATCH(29,DATA2026!J$2:J$401,0)),"") | J46: =IFERROR(INDEX(DATA2026!B$2:B$401,MATCH(29,DATA2026!K$2:K$401,0)),"") | K46: =IFERROR(INDEX(DATA2026!C$2:C$401,MATCH(29,DATA2026!K$2:K$401,0)),"") | L46: =IFERROR(INDEX(DATA2026!D$2:D$401,MATCH(29,DATA2026!K$2:K$401,0)),"") | N46: =IFERROR(INDEX(DATA2026!B$2:B$401,MATCH(29,DATA2026!L$2:L$401,0)),"") | O46: =IFERROR(INDEX(DATA2026!C$2:C$401,MATCH(29,DATA2026!L$2:L$401,0)),"") | P46: =IFERROR(INDEX(DATA2026!D$2:D$401,MATCH(29,DATA2026!L$2:L$401,0)),"")
B47: =IFERROR(INDEX(DATA2026!B$2:B$401,MATCH(30,DATA2026!I$2:I$401,0)),"") | C47: =IFERROR(INDEX(DATA2026!C$2:C$401,MATCH(30,DATA2026!I$2:I$401,0)),"") | D47: =IFERROR(INDEX(DATA2026!D$2:D$401,MATCH(30,DATA2026!I$2:I$401,0)),"") | F47: =IFERROR(INDEX(DATA2026!B$2:B$401,MATCH(30,DATA2026!J$2:J$401,0)),"") | G47: =IFERROR(INDEX(DATA2026!C$2:C$401,MATCH(30,DATA2026!J$2:J$401,0)),"") | H47: =IFERROR(INDEX(DATA2026!D$2:D$401,MATCH(30,DATA2026!J$2:J$401,0)),"") | J47: =IFERROR(INDEX(DATA2026!B$2:B$401,MATCH(30,DATA2026!K$2:K$401,0)),"") | K47: =IFERROR(INDEX(DATA2026!C$2:C$401,MATCH(30,DATA2026!K$2:K$401,0)),"") | L47: =IFERROR(INDEX(DATA2026!D$2:D$401,MATCH(30,DATA2026!K$2:K$401,0)),"") | N47: =IFERROR(INDEX(DATA2026!B$2:B$401,MATCH(30,DATA2026!L$2:L$401,0)),"") | O47: =IFERROR(INDEX(DATA2026!C$2:C$401,MATCH(30,DATA2026!L$2:L$401,0)),"") | P47: =IFERROR(INDEX(DATA2026!D$2:D$401,MATCH(30,DATA2026!L$2:L$401,0)),"")
B48: =IFERROR(INDEX(DATA2026!B$2:B$401,MATCH(31,DATA2026!I$2:I$401,0)),"") | C48: =IFERROR(INDEX(DATA2026!C$2:C$401,MATCH(31,DATA2026!I$2:I$401,0)),"") | D48: =IFERROR(INDEX(DATA2026!D$2:D$401,MATCH(31,DATA2026!I$2:I$401,0)),"") | F48: =IFERROR(INDEX(DATA2026!B$2:B$401,MATCH(31,DATA2026!J$2:J$401,0)),"") | G48: =IFERROR(INDEX(DATA2026!C$2:C$401,MATCH(31,DATA2026!J$2:J$401,0)),"") | H48: =IFERROR(INDEX(DATA2026!D$2:D$401,MATCH(31,DATA2026!J$2:J$401,0)),"") | J48: =IFERROR(INDEX(DATA2026!B$2:B$401,MATCH(31,DATA2026!K$2:K$401,0)),"") | K48: =IFERROR(INDEX(DATA2026!C$2:C$401,MATCH(31,DATA2026!K$2:K$401,0)),"") | L48: =IFERROR(INDEX(DATA2026!D$2:D$401,MATCH(31,DATA2026!K$2:K$401,0)),"") | N48: =IFERROR(INDEX(DATA2026!B$2:B$401,MATCH(31,DATA2026!L$2:L$401,0)),"") | O48: =IFERROR(INDEX(DATA2026!C$2:C$401,MATCH(31,DATA2026!L$2:L$401,0)),"") | P48: =IFERROR(INDEX(DATA2026!D$2:D$401,MATCH(31,DATA2026!L$2:L$401,0)),"")
B49: =IFERROR(INDEX(DATA2026!B$2:B$401,MATCH(32,DATA2026!I$2:I$401,0)),"") | C49: =IFERROR(INDEX(DATA2026!C$2:C$401,MATCH(32,DATA2026!I$2:I$401,0)),"") | D49: =IFERROR(INDEX(DATA2026!D$2:D$401,MATCH(32,DATA2026!I$2:I$401,0)),"") | F49: =IFERROR(INDEX(DATA2026!B$2:B$401,MATCH(32,DATA2026!J$2:J$401,0)),"") | G49: =IFERROR(INDEX(DATA2026!C$2:C$401,MATCH(32,DATA2026!J$2:J$401,0)),"") | H49: =IFERROR(INDEX(DATA2026!D$2:D$401,MATCH(32,DATA2026!J$2:J$401,0)),"") | J49: =IFERROR(INDEX(DATA2026!B$2:B$401,MATCH(32,DATA2026!K$2:K$401,0)),"") | K49: =IFERROR(INDEX(DATA2026!C$2:C$401,MATCH(32,DATA2026!K$2:K$401,0)),"") | L49: =IFERROR(INDEX(DATA2026!D$2:D$401,MATCH(32,DATA2026!K$2:K$401,0)),"") | N49: =IFERROR(INDEX(DATA2026!B$2:B$401,MATCH(32,DATA2026!L$2:L$401,0)),"") | O49: =IFERROR(INDEX(DATA2026!C$2:C$401,MATCH(32,DATA2026!L$2:L$401,0)),"") | P49: =IFERROR(INDEX(DATA2026!D$2:D$401,MATCH(32,DATA2026!L$2:L$401,0)),"")
B50: =IFERROR(INDEX(DATA2026!B$2:B$401,MATCH(33,DATA2026!I$2:I$401,0)),"") | C50: =IFERROR(INDEX(DATA2026!C$2:C$401,MATCH(33,DATA2026!I$2:I$401,0)),"") | D50: =IFERROR(INDEX(DATA2026!D$2:D$401,MATCH(33,DATA2026!I$2:I$401,0)),"") | F50: =IFERROR(INDEX(DATA2026!B$2:B$401,MATCH(33,DATA2026!J$2:J$401,0)),"") | G50: =IFERROR(INDEX(DATA2026!C$2:C$401,MATCH(33,DATA2026!J$2:J$401,0)),"") | H50: =IFERROR(INDEX(DATA2026!D$2:D$401,MATCH(33,DATA2026!J$2:J$401,0)),"") | J50: =IFERROR(INDEX(DATA2026!B$2:B$401,MATCH(33,DATA2026!K$2:K$401,0)),"") | K50: =IFERROR(INDEX(DATA2026!C$2:C$401,MATCH(33,DATA2026!K$2:K$401,0)),"") | L50: =IFERROR(INDEX(DATA2026!D$2:D$401,MATCH(33,DATA2026!K$2:K$401,0)),"") | N50: =IFERROR(INDEX(DATA2026!B$2:B$401,MATCH(33,DATA2026!L$2:L$401,0)),"") | O50: =IFERROR(INDEX(DATA2026!C$2:C$401,MATCH(33,DATA2026!L$2:L$401,0)),"") | P50: =IFERROR(INDEX(DATA2026!D$2:D$401,MATCH(33,DATA2026!L$2:L$401,0)),"")
B51: =IFERROR(INDEX(DATA2026!B$2:B$401,MATCH(34,DATA2026!I$2:I$401,0)),"") | C51: =IFERROR(INDEX(DATA2026!C$2:C$401,MATCH(34,DATA2026!I$2:I$401,0)),"") | D51: =IFERROR(INDEX(DATA2026!D$2:D$401,MATCH(34,DATA2026!I$2:I$401,0)),"") | F51: =IFERROR(INDEX(DATA2026!B$2:B$401,MATCH(34,DATA2026!J$2:J$401,0)),"") | G51: =IFERROR(INDEX(DATA2026!C$2:C$401,MATCH(34,DATA2026!J$2:J$401,0)),"") | H51: =IFERROR(INDEX(DATA2026!D$2:D$401,MATCH(34,DATA2026!J$2:J$401,0)),"") | J51: =IFERROR(INDEX(DATA2026!B$2:B$401,MATCH(34,DATA2026!K$2:K$401,0)),"") | K51: =IFERROR(INDEX(DATA2026!C$2:C$401,MATCH(34,DATA2026!K$2:K$401,0)),"") | L51: =IFERROR(INDEX(DATA2026!D$2:D$401,MATCH(34,DATA2026!K$2:K$401,0)),"") | N51: =IFERROR(INDEX(DATA2026!B$2:B$401,MATCH(34,DATA2026!L$2:L$401,0)),"") | O51: =IFERROR(INDEX(DATA2026!C$2:C$401,MATCH(34,DATA2026!L$2:L$401,0)),"") | P51: =IFERROR(INDEX(DATA2026!D$2:D$401,MATCH(34,DATA2026!L$2:L$401,0)),"")
B52: =IFERROR(INDEX(DATA2026!B$2:B$401,MATCH(35,DATA2026!I$2:I$401,0)),"") | C52: =IFERROR(INDEX(DATA2026!C$2:C$401,MATCH(35,DATA2026!I$2:I$401,0)),"") | D52: =IFERROR(INDEX(DATA2026!D$2:D$401,MATCH(35,DATA2026!I$2:I$401,0)),"") | F52: =IFERROR(INDEX(DATA2026!B$2:B$401,MATCH(35,DATA2026!J$2:J$401,0)),"") | G52: =IFERROR(INDEX(DATA2026!C$2:C$401,MATCH(35,DATA2026!J$2:J$401,0)),"") | H52: =IFERROR(INDEX(DATA2026!D$2:D$401,MATCH(35,DATA2026!J$2:J$401,0)),"") | J52: =IFERROR(INDEX(DATA2026!B$2:B$401,MATCH(35,DATA2026!K$2:K$401,0)),"") | K52: =IFERROR(INDEX(DATA2026!C$2:C$401,MATCH(35,DATA2026!K$2:K$401,0)),"") | L52: =IFERROR(INDEX(DATA2026!D$2:D$401,MATCH(35,DATA2026!K$2:K$401,0)),"") | N52: =IFERROR(INDEX(DATA2026!B$2:B$401,MATCH(35,DATA2026!L$2:L$401,0)),"") | O52: =IFERROR(INDEX(DATA2026!C$2:C$401,MATCH(35,DATA2026!L$2:L$401,0)),"") | P52: =IFERROR(INDEX(DATA2026!D$2:D$401,MATCH(35,DATA2026!L$2:L$401,0)),"")
B53: =IFERROR(INDEX(DATA2026!B$2:B$401,MATCH(36,DATA2026!I$2:I$401,0)),"") | C53: =IFERROR(INDEX(DATA2026!C$2:C$401,MATCH(36,DATA2026!I$2:I$401,0)),"") | D53: =IFERROR(INDEX(DATA2026!D$2:D$401,MATCH(36,DATA2026!I$2:I$401,0)),"") | F53: =IFERROR(INDEX(DATA2026!B$2:B$401,MATCH(36,DATA2026!J$2:J$401,0)),"") | G53: =IFERROR(INDEX(DATA2026!C$2:C$401,MATCH(36,DATA2026!J$2:J$401,0)),"") | H53: =IFERROR(INDEX(DATA2026!D$2:D$401,MATCH(36,DATA2026!J$2:J$401,0)),"") | J53: =IFERROR(INDEX(DATA2026!B$2:B$401,MATCH(36,DATA2026!K$2:K$401,0)),"") | K53: =IFERROR(INDEX(DATA2026!C$2:C$401,MATCH(36,DATA2026!K$2:K$401,0)),"") | L53: =IFERROR(INDEX(DATA2026!D$2:D$401,MATCH(36,DATA2026!K$2:K$401,0)),"") | N53: =IFERROR(INDEX(DATA2026!B$2:B$401,MATCH(36,DATA2026!L$2:L$401,0)),"") | O53: =IFERROR(INDEX(DATA2026!C$2:C$401,MATCH(36,DATA2026!L$2:L$401,0)),"") | P53: =IFERROR(INDEX(DATA2026!D$2:D$401,MATCH(36,DATA2026!L$2:L$401,0)),"")
B54: =IFERROR(INDEX(DATA2026!B$2:B$401,MATCH(37,DATA2026!I$2:I$401,0)),"") | C54: =IFERROR(INDEX(DATA2026!C$2:C$401,MATCH(37,DATA2026!I$2:I$401,0)),"") | D54: =IFERROR(INDEX(DATA2026!D$2:D$401,MATCH(37,DATA2026!I$2:I$401,0)),"") | F54: =IFERROR(INDEX(DATA2026!B$2:B$401,MATCH(37,DATA2026!J$2:J$401,0)),"") | G54: =IFERROR(INDEX(DATA2026!C$2:C$401,MATCH(37,DATA2026!J$2:J$401,0)),"") | H54: =IFERROR(INDEX(DATA2026!D$2:D$401,MATCH(37,DATA2026!J$2:J$401,0)),"") | J54: =IFERROR(INDEX(DATA2026!B$2:B$401,MATCH(37,DATA2026!K$2:K$401,0)),"") | K54: =IFERROR(INDEX(DATA2026!C$2:C$401,MATCH(37,DATA2026!K$2:K$401,0)),"") | L54: =IFERROR(INDEX(DATA2026!D$2:D$401,MATCH(37,DATA2026!K$2:K$401,0)),"") | N54: =IFERROR(INDEX(DATA2026!B$2:B$401,MATCH(37,DATA2026!L$2:L$401,0)),"") | O54: =IFERROR(INDEX(DATA2026!C$2:C$401,MATCH(37,DATA2026!L$2:L$401,0)),"") | P54: =IFERROR(INDEX(DATA2026!D$2:D$401,MATCH(37,DATA2026!L$2:L$401,0)),"")
B55: =IFERROR(INDEX(DATA2026!B$2:B$401,MATCH(38,DATA2026!I$2:I$401,0)),"") | C55: =IFERROR(INDEX(DATA2026!C$2:C$401,MATCH(38,DATA2026!I$2:I$401,0)),"") | D55: =IFERROR(INDEX(DATA2026!D$2:D$401,MATCH(38,DATA2026!I$2:I$401,0)),"") | F55: =IFERROR(INDEX(DATA2026!B$2:B$401,MATCH(38,DATA2026!J$2:J$401,0)),"") | G55: =IFERROR(INDEX(DATA2026!C$2:C$401,MATCH(38,DATA2026!J$2:J$401,0)),"") | H55: =IFERROR(INDEX(DATA2026!D$2:D$401,MATCH(38,DATA2026!J$2:J$401,0)),"") | J55: =IFERROR(INDEX(DATA2026!B$2:B$401,MATCH(38,DATA2026!K$2:K$401,0)),"") | K55: =IFERROR(INDEX(DATA2026!C$2:C$401,MATCH(38,DATA2026!K$2:K$401,0)),"") | L55: =IFERROR(INDEX(DATA2026!D$2:D$401,MATCH(38,DATA2026!K$2:K$401,0)),"") | N55: =IFERROR(INDEX(DATA2026!B$2:B$401,MATCH(38,DATA2026!L$2:L$401,0)),"") | O55: =IFERROR(INDEX(DATA2026!C$2:C$401,MATCH(38,DATA2026!L$2:L$401,0)),"") | P55: =IFERROR(INDEX(DATA2026!D$2:D$401,MATCH(38,DATA2026!L$2:L$401,0)),"")
B56: =IFERROR(INDEX(DATA2026!B$2:B$401,MATCH(39,DATA2026!I$2:I$401,0)),"") | C56: =IFERROR(INDEX(DATA2026!C$2:C$401,MATCH(39,DATA2026!I$2:I$401,0)),"") | D56: =IFERROR(INDEX(DATA2026!D$2:D$401,MATCH(39,DATA2026!I$2:I$401,0)),"") | F56: =IFERROR(INDEX(DATA2026!B$2:B$401,MATCH(39,DATA2026!J$2:J$401,0)),"") | G56: =IFERROR(INDEX(DATA2026!C$2:C$401,MATCH(39,DATA2026!J$2:J$401,0)),"") | H56: =IFERROR(INDEX(DATA2026!D$2:D$401,MATCH(39,DATA2026!J$2:J$401,0)),"") | J56: =IFERROR(INDEX(DATA2026!B$2:B$401,MATCH(39,DATA2026!K$2:K$401,0)),"") | K56: =IFERROR(INDEX(DATA2026!C$2:C$401,MATCH(39,DATA2026!K$2:K$401,0)),"") | L56: =IFERROR(INDEX(DATA2026!D$2:D$401,MATCH(39,DATA2026!K$2:K$401,0)),"") | N56: =IFERROR(INDEX(DATA2026!B$2:B$401,MATCH(39,DATA2026!L$2:L$401,0)),"") | O56: =IFERROR(INDEX(DATA2026!C$2:C$401,MATCH(39,DATA2026!L$2:L$401,0)),"") | P56: =IFERROR(INDEX(DATA2026!D$2:D$401,MATCH(39,DATA2026!L$2:L$401,0)),"")
B57: =IFERROR(INDEX(DATA2026!B$2:B$401,MATCH(40,DATA2026!I$2:I$401,0)),"") | C57: =IFERROR(INDEX(DATA2026!C$2:C$401,MATCH(40,DATA2026!I$2:I$401,0)),"") | D57: =IFERROR(INDEX(DATA2026!D$2:D$401,MATCH(40,DATA2026!I$2:I$401,0)),"") | F57: =IFERROR(INDEX(DATA2026!B$2:B$401,MATCH(40,DATA2026!J$2:J$401,0)),"") | G57: =IFERROR(INDEX(DATA2026!C$2:C$401,MATCH(40,DATA2026!J$2:J$401,0)),"") | H57: =IFERROR(INDEX(DATA2026!D$2:D$401,MATCH(40,DATA2026!J$2:J$401,0)),"") | J57: =IFERROR(INDEX(DATA2026!B$2:B$401,MATCH(40,DATA2026!K$2:K$401,0)),"") | K57: =IFERROR(INDEX(DATA2026!C$2:C$401,MATCH(40,DATA2026!K$2:K$401,0)),"") | L57: =IFERROR(INDEX(DATA2026!D$2:D$401,MATCH(40,DATA2026!K$2:K$401,0)),"") | N57: =IFERROR(INDEX(DATA2026!B$2:B$401,MATCH(40,DATA2026!L$2:L$401,0)),"") | O57: =IFERROR(INDEX(DATA2026!C$2:C$401,MATCH(40,DATA2026!L$2:L$401,0)),"") | P57: =IFERROR(INDEX(DATA2026!D$2:D$401,MATCH(40,DATA2026!L$2:L$401,0)),"")
B58: =IFERROR(INDEX(DATA2026!B$2:B$401,MATCH(41,DATA2026!I$2:I$401,0)),"") | C58: =IFERROR(INDEX(DATA2026!C$2:C$401,MATCH(41,DATA2026!I$2:I$401,0)),"") | D58: =IFERROR(INDEX(DATA2026!D$2:D$401,MATCH(41,DATA2026!I$2:I$401,0)),"") | F58: =IFERROR(INDEX(DATA2026!B$2:B$401,MATCH(41,DATA2026!J$2:J$401,0)),"") | G58: =IFERROR(INDEX(DATA2026!C$2:C$401,MATCH(41,DATA2026!J$2:J$401,0)),"") | H58: =IFERROR(INDEX(DATA2026!D$2:D$401,MATCH(41,DATA2026!J$2:J$401,0)),"") | J58: =IFERROR(INDEX(DATA2026!B$2:B$401,MATCH(41,DATA2026!K$2:K$401,0)),"") | K58: =IFERROR(INDEX(DATA2026!C$2:C$401,MATCH(41,DATA2026!K$2:K$401,0)),"") | L58: =IFERROR(INDEX(DATA2026!D$2:D$401,MATCH(41,DATA2026!K$2:K$401,0)),"") | N58: =IFERROR(INDEX(DATA2026!B$2:B$401,MATCH(41,DATA2026!L$2:L$401,0)),"") | O58: =IFERROR(INDEX(DATA2026!C$2:C$401,MATCH(41,DATA2026!L$2:L$401,0)),"") | P58: =IFERROR(INDEX(DATA2026!D$2:D$401,MATCH(41,DATA2026!L$2:L$401,0)),"")
B59: =IFERROR(INDEX(DATA2026!B$2:B$401,MATCH(42,DATA2026!I$2:I$401,0)),"") | C59: =IFERROR(INDEX(DATA2026!C$2:C$401,MATCH(42,DATA2026!I$2:I$401,0)),"") | D59: =IFERROR(INDEX(DATA2026!D$2:D$401,MATCH(42,DATA2026!I$2:I$401,0)),"") | F59: =IFERROR(INDEX(DATA2026!B$2:B$401,MATCH(42,DATA2026!J$2:J$401,0)),"") | G59: =IFERROR(INDEX(DATA2026!C$2:C$401,MATCH(42,DATA2026!J$2:J$401,0)),"") | H59: =IFERROR(INDEX(DATA2026!D$2:D$401,MATCH(42,DATA2026!J$2:J$401,0)),"") | J59: =IFERROR(INDEX(DATA2026!B$2:B$401,MATCH(42,DATA2026!K$2:K$401,0)),"") | K59: =IFERROR(INDEX(DATA2026!C$2:C$401,MATCH(42,DATA2026!K$2:K$401,0)),"") | L59: =IFERROR(INDEX(DATA2026!D$2:D$401,MATCH(42,DATA2026!K$2:K$401,0)),"") | N59: =IFERROR(INDEX(DATA2026!B$2:B$401,MATCH(42,DATA2026!L$2:L$401,0)),"") | O59: =IFERROR(INDEX(DATA2026!C$2:C$401,MATCH(42,DATA2026!L$2:L$401,0)),"") | P59: =IFERROR(INDEX(DATA2026!D$2:D$401,MATCH(42,DATA2026!L$2:L$401,0)),"")
B60: =IFERROR(INDEX(DATA2026!B$2:B$401,MATCH(43,DATA2026!I$2:I$401,0)),"") | C60: =IFERROR(INDEX(DATA2026!C$2:C$401,MATCH(43,DATA2026!I$2:I$401,0)),"") | D60: =IFERROR(INDEX(DATA2026!D$2:D$401,MATCH(43,DATA2026!I$2:I$401,0)),"") | F60: =IFERROR(INDEX(DATA2026!B$2:B$401,MATCH(43,DATA2026!J$2:J$401,0)),"") | G60: =IFERROR(INDEX(DATA2026!C$2:C$401,MATCH(43,DATA2026!J$2:J$401,0)),"") | H60: =IFERROR(INDEX(DATA2026!D$2:D$401,MATCH(43,DATA2026!J$2:J$401,0)),"") | J60: =IFERROR(INDEX(DATA2026!B$2:B$401,MATCH(43,DATA2026!K$2:K$401,0)),"") | K60: =IFERROR(INDEX(DATA2026!C$2:C$401,MATCH(43,DATA2026!K$2:K$401,0)),"") | L60: =IFERROR(INDEX(DATA2026!D$2:D$401,MATCH(43,DATA2026!K$2:K$401,0)),"") | N60: =IFERROR(INDEX(DATA2026!B$2:B$401,MATCH(43,DATA2026!L$2:L$401,0)),"") | O60: =IFERROR(INDEX(DATA2026!C$2:C$401,MATCH(43,DATA2026!L$2:L$401,0)),"") | P60: =IFERROR(INDEX(DATA2026!D$2:D$401,MATCH(43,DATA2026!L$2:L$401,0)),"")
B61: =IFERROR(INDEX(DATA2026!B$2:B$401,MATCH(44,DATA2026!I$2:I$401,0)),"") | C61: =IFERROR(INDEX(DATA2026!C$2:C$401,MATCH(44,DATA2026!I$2:I$401,0)),"") | D61: =IFERROR(INDEX(DATA2026!D$2:D$401,MATCH(44,DATA2026!I$2:I$401,0)),"") | F61: =IFERROR(INDEX(DATA2026!B$2:B$401,MATCH(44,DATA2026!J$2:J$401,0)),"") | G61: =IFERROR(INDEX(DATA2026!C$2:C$401,MATCH(44,DATA2026!J$2:J$401,0)),"") | H61: =IFERROR(INDEX(DATA2026!D$2:D$401,MATCH(44,DATA2026!J$2:J$401,0)),"") | J61: =IFERROR(INDEX(DATA2026!B$2:B$401,MATCH(44,DATA2026!K$2:K$401,0)),"") | K61: =IFERROR(INDEX(DATA2026!C$2:C$401,MATCH(44,DATA2026!K$2:K$401,0)),"") | L61: =IFERROR(INDEX(DATA2026!D$2:D$401,MATCH(44,DATA2026!K$2:K$401,0)),"") | N61: =IFERROR(INDEX(DATA2026!B$2:B$401,MATCH(44,DATA2026!L$2:L$401,0)),"") | O61: =IFERROR(INDEX(DATA2026!C$2:C$401,MATCH(44,DATA2026!L$2:L$401,0)),"") | P61: =IFERROR(INDEX(DATA2026!D$2:D$401,MATCH(44,DATA2026!L$2:L$401,0)),"")
B62: =IFERROR(INDEX(DATA2026!B$2:B$401,MATCH(45,DATA2026!I$2:I$401,0)),"") | C62: =IFERROR(INDEX(DATA2026!C$2:C$401,MATCH(45,DATA2026!I$2:I$401,0)),"") | D62: =IFERROR(INDEX(DATA2026!D$2:D$401,MATCH(45,DATA2026!I$2:I$401,0)),"") | F62: =IFERROR(INDEX(DATA2026!B$2:B$401,MATCH(45,DATA2026!J$2:J$401,0)),"") | G62: =IFERROR(INDEX(DATA2026!C$2:C$401,MATCH(45,DATA2026!J$2:J$401,0)),"") | H62: =IFERROR(INDEX(DATA2026!D$2:D$401,MATCH(45,DATA2026!J$2:J$401,0)),"") | J62: =IFERROR(INDEX(DATA2026!B$2:B$401,MATCH(45,DATA2026!K$2:K$401,0)),"") | K62: =IFERROR(INDEX(DATA2026!C$2:C$401,MATCH(45,DATA2026!K$2:K$401,0)),"") | L62: =IFERROR(INDEX(DATA2026!D$2:D$401,MATCH(45,DATA2026!K$2:K$401,0)),"") | N62: =IFERROR(INDEX(DATA2026!B$2:B$401,MATCH(45,DATA2026!L$2:L$401,0)),"") | O62: =IFERROR(INDEX(DATA2026!C$2:C$401,MATCH(45,DATA2026!L$2:L$401,0)),"") | P62: =IFERROR(INDEX(DATA2026!D$2:D$401,MATCH(45,DATA2026!L$2:L$401,0)),"")
B63: =IFERROR(INDEX(DATA2026!B$2:B$401,MATCH(46,DATA2026!I$2:I$401,0)),"") | C63: =IFERROR(INDEX(DATA2026!C$2:C$401,MATCH(46,DATA2026!I$2:I$401,0)),"") | D63: =IFERROR(INDEX(DATA2026!D$2:D$401,MATCH(46,DATA2026!I$2:I$401,0)),"") | F63: =IFERROR(INDEX(DATA2026!B$2:B$401,MATCH(46,DATA2026!J$2:J$401,0)),"") | G63: =IFERROR(INDEX(DATA2026!C$2:C$401,MATCH(46,DATA2026!J$2:J$401,0)),"") | H63: =IFERROR(INDEX(DATA2026!D$2:D$401,MATCH(46,DATA2026!J$2:J$401,0)),"") | J63: =IFERROR(INDEX(DATA2026!B$2:B$401,MATCH(46,DATA2026!K$2:K$401,0)),"") | K63: =IFERROR(INDEX(DATA2026!C$2:C$401,MATCH(46,DATA2026!K$2:K$401,0)),"") | L63: =IFERROR(INDEX(DATA2026!D$2:D$401,MATCH(46,DATA2026!K$2:K$401,0)),"") | N63: =IFERROR(INDEX(DATA2026!B$2:B$401,MATCH(46,DATA2026!L$2:L$401,0)),"") | O63: =IFERROR(INDEX(DATA2026!C$2:C$401,MATCH(46,DATA2026!L$2:L$401,0)),"") | P63: =IFERROR(INDEX(DATA2026!D$2:D$401,MATCH(46,DATA2026!L$2:L$401,0)),"")
B64: =IFERROR(INDEX(DATA2026!B$2:B$401,MATCH(47,DATA2026!I$2:I$401,0)),"") | C64: =IFERROR(INDEX(DATA2026!C$2:C$401,MATCH(47,DATA2026!I$2:I$401,0)),"") | D64: =IFERROR(INDEX(DATA2026!D$2:D$401,MATCH(47,DATA2026!I$2:I$401,0)),"") | F64: =IFERROR(INDEX(DATA2026!B$2:B$401,MATCH(47,DATA2026!J$2:J$401,0)),"") | G64: =IFERROR(INDEX(DATA2026!C$2:C$401,MATCH(47,DATA2026!J$2:J$401,0)),"") | H64: =IFERROR(INDEX(DATA2026!D$2:D$401,MATCH(47,DATA2026!J$2:J$401,0)),"") | J64: =IFERROR(INDEX(DATA2026!B$2:B$401,MATCH(47,DATA2026!K$2:K$401,0)),"") | K64: =IFERROR(INDEX(DATA2026!C$2:C$401,MATCH(47,DATA2026!K$2:K$401,0)),"") | L64: =IFERROR(INDEX(DATA2026!D$2:D$401,MATCH(47,DATA2026!K$2:K$401,0)),"") | N64: =IFERROR(INDEX(DATA2026!B$2:B$401,MATCH(47,DATA2026!L$2:L$401,0)),"") | O64: =IFERROR(INDEX(DATA2026!C$2:C$401,MATCH(47,DATA2026!L$2:L$401,0)),"") | P64: =IFERROR(INDEX(DATA2026!D$2:D$401,MATCH(47,DATA2026!L$2:L$401,0)),"")
B65: =IFERROR(INDEX(DATA2026!B$2:B$401,MATCH(48,DATA2026!I$2:I$401,0)),"") | C65: =IFERROR(INDEX(DATA2026!C$2:C$401,MATCH(48,DATA2026!I$2:I$401,0)),"") | D65: =IFERROR(INDEX(DATA2026!D$2:D$401,MATCH(48,DATA2026!I$2:I$401,0)),"") | F65: =IFERROR(INDEX(DATA2026!B$2:B$401,MATCH(48,DATA2026!J$2:J$401,0)),"") | G65: =IFERROR(INDEX(DATA2026!C$2:C$401,MATCH(48,DATA2026!J$2:J$401,0)),"") | H65: =IFERROR(INDEX(DATA2026!D$2:D$401,MATCH(48,DATA2026!J$2:J$401,0)),"") | J65: =IFERROR(INDEX(DATA2026!B$2:B$401,MATCH(48,DATA2026!K$2:K$401,0)),"") | K65: =IFERROR(INDEX(DATA2026!C$2:C$401,MATCH(48,DATA2026!K$2:K$401,0)),"") | L65: =IFERROR(INDEX(DATA2026!D$2:D$401,MATCH(48,DATA2026!K$2:K$401,0)),"") | N65: =IFERROR(INDEX(DATA2026!B$2:B$401,MATCH(48,DATA2026!L$2:L$401,0)),"") | O65: =IFERROR(INDEX(DATA2026!C$2:C$401,MATCH(48,DATA2026!L$2:L$401,0)),"") | P65: =IFERROR(INDEX(DATA2026!D$2:D$401,MATCH(48,DATA2026!L$2:L$401,0)),"")
B66: =IFERROR(INDEX(DATA2026!B$2:B$401,MATCH(49,DATA2026!I$2:I$401,0)),"") | C66: =IFERROR(INDEX(DATA2026!C$2:C$401,MATCH(49,DATA2026!I$2:I$401,0)),"") | D66: =IFERROR(INDEX(DATA2026!D$2:D$401,MATCH(49,DATA2026!I$2:I$401,0)),"") | F66: =IFERROR(INDEX(DATA2026!B$2:B$401,MATCH(49,DATA2026!J$2:J$401,0)),"") | G66: =IFERROR(INDEX(DATA2026!C$2:C$401,MATCH(49,DATA2026!J$2:J$401,0)),"") | H66: =IFERROR(INDEX(DATA2026!D$2:D$401,MATCH(49,DATA2026!J$2:J$401,0)),"") | J66: =IFERROR(INDEX(DATA2026!B$2:B$401,MATCH(49,DATA2026!K$2:K$401,0)),"") | K66: =IFERROR(INDEX(DATA2026!C$2:C$401,MATCH(49,DATA2026!K$2:K$401,0)),"") | L66: =IFERROR(INDEX(DATA2026!D$2:D$401,MATCH(49,DATA2026!K$2:K$401,0)),"") | N66: =IFERROR(INDEX(DATA2026!B$2:B$401,MATCH(49,DATA2026!L$2:L$401,0)),"") | O66: =IFERROR(INDEX(DATA2026!C$2:C$401,MATCH(49,DATA2026!L$2:L$401,0)),"") | P66: =IFERROR(INDEX(DATA2026!D$2:D$401,MATCH(49,DATA2026!L$2:L$401,0)),"")
B67: =IFERROR(INDEX(DATA2026!B$2:B$401,MATCH(50,DATA2026!I$2:I$401,0)),"") | C67: =IFERROR(INDEX(DATA2026!C$2:C$401,MATCH(50,DATA2026!I$2:I$401,0)),"") | D67: =IFERROR(INDEX(DATA2026!D$2:D$401,MATCH(50,DATA2026!I$2:I$401,0)),"") | F67: =IFERROR(INDEX(DATA2026!B$2:B$401,MATCH(50,DATA2026!J$2:J$401,0)),"") | G67: =IFERROR(INDEX(DATA2026!C$2:C$401,MATCH(50,DATA2026!J$2:J$401,0)),"") | H67: =IFERROR(INDEX(DATA2026!D$2:D$401,MATCH(50,DATA2026!J$2:J$401,0)),"") | J67: =IFERROR(INDEX(DATA2026!B$2:B$401,MATCH(50,DATA2026!K$2:K$401,0)),"") | K67: =IFERROR(INDEX(DATA2026!C$2:C$401,MATCH(50,DATA2026!K$2:K$401,0)),"") | L67: =IFERROR(INDEX(DATA2026!D$2:D$401,MATCH(50,DATA2026!K$2:K$401,0)),"") | N67: =IFERROR(INDEX(DATA2026!B$2:B$401,MATCH(50,DATA2026!L$2:L$401,0)),"") | O67: =IFERROR(INDEX(DATA2026!C$2:C$401,MATCH(50,DATA2026!L$2:L$401,0)),"") | P67: =IFERROR(INDEX(DATA2026!D$2:D$401,MATCH(50,DATA2026!L$2:L$401,0)),"")
B68: =IFERROR(INDEX(DATA2026!B$2:B$401,MATCH(51,DATA2026!I$2:I$401,0)),"") | C68: =IFERROR(INDEX(DATA2026!C$2:C$401,MATCH(51,DATA2026!I$2:I$401,0)),"") | D68: =IFERROR(INDEX(DATA2026!D$2:D$401,MATCH(51,DATA2026!I$2:I$401,0)),"") | F68: =IFERROR(INDEX(DATA2026!B$2:B$401,MATCH(51,DATA2026!J$2:J$401,0)),"") | G68: =IFERROR(INDEX(DATA2026!C$2:C$401,MATCH(51,DATA2026!J$2:J$401,0)),"") | H68: =IFERROR(INDEX(DATA2026!D$2:D$401,MATCH(51,DATA2026!J$2:J$401,0)),"") | J68: =IFERROR(INDEX(DATA2026!B$2:B$401,MATCH(51,DATA2026!K$2:K$401,0)),"") | K68: =IFERROR(INDEX(DATA2026!C$2:C$401,MATCH(51,DATA2026!K$2:K$401,0)),"") | L68: =IFERROR(INDEX(DATA2026!D$2:D$401,MATCH(51,DATA2026!K$2:K$401,0)),"") | N68: =IFERROR(INDEX(DATA2026!B$2:B$401,MATCH(51,DATA2026!L$2:L$401,0)),"") | O68: =IFERROR(INDEX(DATA2026!C$2:C$401,MATCH(51,DATA2026!L$2:L$401,0)),"") | P68: =IFERROR(INDEX(DATA2026!D$2:D$401,MATCH(51,DATA2026!L$2:L$401,0)),"")
B69: =IFERROR(INDEX(DATA2026!B$2:B$401,MATCH(52,DATA2026!I$2:I$401,0)),"") | C69: =IFERROR(INDEX(DATA2026!C$2:C$401,MATCH(52,DATA2026!I$2:I$401,0)),"") | D69: =IFERROR(INDEX(DATA2026!D$2:D$401,MATCH(52,DATA2026!I$2:I$401,0)),"") | F69: =IFERROR(INDEX(DATA2026!B$2:B$401,MATCH(52,DATA2026!J$2:J$401,0)),"") | G69: =IFERROR(INDEX(DATA2026!C$2:C$401,MATCH(52,DATA2026!J$2:J$401,0)),"") | H69: =IFERROR(INDEX(DATA2026!D$2:D$401,MATCH(52,DATA2026!J$2:J$401,0)),"") | J69: =IFERROR(INDEX(DATA2026!B$2:B$401,MATCH(52,DATA2026!K$2:K$401,0)),"") | K69: =IFERROR(INDEX(DATA2026!C$2:C$401,MATCH(52,DATA2026!K$2:K$401,0)),"") | L69: =IFERROR(INDEX(DATA2026!D$2:D$401,MATCH(52,DATA2026!K$2:K$401,0)),"") | N69: =IFERROR(INDEX(DATA2026!B$2:B$401,MATCH(52,DATA2026!L$2:L$401,0)),"") | O69: =IFERROR(INDEX(DATA2026!C$2:C$401,MATCH(52,DATA2026!L$2:L$401,0)),"") | P69: =IFERROR(INDEX(DATA2026!D$2:D$401,MATCH(52,DATA2026!L$2:L$401,0)),"")
B70: =IFERROR(INDEX(DATA2026!B$2:B$401,MATCH(53,DATA2026!I$2:I$401,0)),"") | C70: =IFERROR(INDEX(DATA2026!C$2:C$401,MATCH(53,DATA2026!I$2:I$401,0)),"") | D70: =IFERROR(INDEX(DATA2026!D$2:D$401,MATCH(53,DATA2026!I$2:I$401,0)),"") | F70: =IFERROR(INDEX(DATA2026!B$2:B$401,MATCH(53,DATA2026!J$2:J$401,0)),"") | G70: =IFERROR(INDEX(DATA2026!C$2:C$401,MATCH(53,DATA2026!J$2:J$401,0)),"") | H70: =IFERROR(INDEX(DATA2026!D$2:D$401,MATCH(53,DATA2026!J$2:J$401,0)),"") | J70: =IFERROR(INDEX(DATA2026!B$2:B$401,MATCH(53,DATA2026!K$2:K$401,0)),"") | K70: =IFERROR(INDEX(DATA2026!C$2:C$401,MATCH(53,DATA2026!K$2:K$401,0)),"") | L70: =IFERROR(INDEX(DATA2026!D$2:D$401,MATCH(53,DATA2026!K$2:K$401,0)),"") | N70: =IFERROR(INDEX(DATA2026!B$2:B$401,MATCH(53,DATA2026!L$2:L$401,0)),"") | O70: =IFERROR(INDEX(DATA2026!C$2:C$401,MATCH(53,DATA2026!L$2:L$401,0)),"") | P70: =IFERROR(INDEX(DATA2026!D$2:D$401,MATCH(53,DATA2026!L$2:L$401,0)),"")
B71: =IFERROR(INDEX(DATA2026!B$2:B$401,MATCH(54,DATA2026!I$2:I$401,0)),"") | C71: =IFERROR(INDEX(DATA2026!C$2:C$401,MATCH(54,DATA2026!I$2:I$401,0)),"") | D71: =IFERROR(INDEX(DATA2026!D$2:D$401,MATCH(54,DATA2026!I$2:I$401,0)),"") | F71: =IFERROR(INDEX(DATA2026!B$2:B$401,MATCH(54,DATA2026!J$2:J$401,0)),"") | G71: =IFERROR(INDEX(DATA2026!C$2:C$401,MATCH(54,DATA2026!J$2:J$401,0)),"") | H71: =IFERROR(INDEX(DATA2026!D$2:D$401,MATCH(54,DATA2026!J$2:J$401,0)),"") | J71: =IFERROR(INDEX(DATA2026!B$2:B$401,MATCH(54,DATA2026!K$2:K$401,0)),"") | K71: =IFERROR(INDEX(DATA2026!C$2:C$401,MATCH(54,DATA2026!K$2:K$401,0)),"") | L71: =IFERROR(INDEX(DATA2026!D$2:D$401,MATCH(54,DATA2026!K$2:K$401,0)),"") | N71: =IFERROR(INDEX(DATA2026!B$2:B$401,MATCH(54,DATA2026!L$2:L$401,0)),"") | O71: =IFERROR(INDEX(DATA2026!C$2:C$401,MATCH(54,DATA2026!L$2:L$401,0)),"") | P71: =IFERROR(INDEX(DATA2026!D$2:D$401,MATCH(54,DATA2026!L$2:L$401,0)),"")
B72: =IFERROR(INDEX(DATA2026!B$2:B$401,MATCH(55,DATA2026!I$2:I$401,0)),"") | C72: =IFERROR(INDEX(DATA2026!C$2:C$401,MATCH(55,DATA2026!I$2:I$401,0)),"") | D72: =IFERROR(INDEX(DATA2026!D$2:D$401,MATCH(55,DATA2026!I$2:I$401,0)),"") | F72: =IFERROR(INDEX(DATA2026!B$2:B$401,MATCH(55,DATA2026!J$2:J$401,0)),"") | G72: =IFERROR(INDEX(DATA2026!C$2:C$401,MATCH(55,DATA2026!J$2:J$401,0)),"") | H72: =IFERROR(INDEX(DATA2026!D$2:D$401,MATCH(55,DATA2026!J$2:J$401,0)),"") | J72: =IFERROR(INDEX(DATA2026!B$2:B$401,MATCH(55,DATA2026!K$2:K$401,0)),"") | K72: =IFERROR(INDEX(DATA2026!C$2:C$401,MATCH(55,DATA2026!K$2:K$401,0)),"") | L72: =IFERROR(INDEX(DATA2026!D$2:D$401,MATCH(55,DATA2026!K$2:K$401,0)),"") | N72: =IFERROR(INDEX(DATA2026!B$2:B$401,MATCH(55,DATA2026!L$2:L$401,0)),"") | O72: =IFERROR(INDEX(DATA2026!C$2:C$401,MATCH(55,DATA2026!L$2:L$401,0)),"") | P72: =IFERROR(INDEX(DATA2026!D$2:D$401,MATCH(55,DATA2026!L$2:L$401,0)),"")
B73: =IFERROR(INDEX(DATA2026!B$2:B$401,MATCH(56,DATA2026!I$2:I$401,0)),"") | C73: =IFERROR(INDEX(DATA2026!C$2:C$401,MATCH(56,DATA2026!I$2:I$401,0)),"") | D73: =IFERROR(INDEX(DATA2026!D$2:D$401,MATCH(56,DATA2026!I$2:I$401,0)),"") | F73: =IFERROR(INDEX(DATA2026!B$2:B$401,MATCH(56,DATA2026!J$2:J$401,0)),"") | G73: =IFERROR(INDEX(DATA2026!C$2:C$401,MATCH(56,DATA2026!J$2:J$401,0)),"") | H73: =IFERROR(INDEX(DATA2026!D$2:D$401,MATCH(56,DATA2026!J$2:J$401,0)),"") | J73: =IFERROR(INDEX(DATA2026!B$2:B$401,MATCH(56,DATA2026!K$2:K$401,0)),"") | K73: =IFERROR(INDEX(DATA2026!C$2:C$401,MATCH(56,DATA2026!K$2:K$401,0)),"") | L73: =IFERROR(INDEX(DATA2026!D$2:D$401,MATCH(56,DATA2026!K$2:K$401,0)),"") | N73: =IFERROR(INDEX(DATA2026!B$2:B$401,MATCH(56,DATA2026!L$2:L$401,0)),"") | O73: =IFERROR(INDEX(DATA2026!C$2:C$401,MATCH(56,DATA2026!L$2:L$401,0)),"") | P73: =IFERROR(INDEX(DATA2026!D$2:D$401,MATCH(56,DATA2026!L$2:L$401,0)),"")
B74: =IFERROR(INDEX(DATA2026!B$2:B$401,MATCH(57,DATA2026!I$2:I$401,0)),"") | C74: =IFERROR(INDEX(DATA2026!C$2:C$401,MATCH(57,DATA2026!I$2:I$401,0)),"") | D74: =IFERROR(INDEX(DATA2026!D$2:D$401,MATCH(57,DATA2026!I$2:I$401,0)),"") | F74: =IFERROR(INDEX(DATA2026!B$2:B$401,MATCH(57,DATA2026!J$2:J$401,0)),"") | G74: =IFERROR(INDEX(DATA2026!C$2:C$401,MATCH(57,DATA2026!J$2:J$401,0)),"") | H74: =IFERROR(INDEX(DATA2026!D$2:D$401,MATCH(57,DATA2026!J$2:J$401,0)),"") | J74: =IFERROR(INDEX(DATA2026!B$2:B$401,MATCH(57,DATA2026!K$2:K$401,0)),"") | K74: =IFERROR(INDEX(DATA2026!C$2:C$401,MATCH(57,DATA2026!K$2:K$401,0)),"") | L74: =IFERROR(INDEX(DATA2026!D$2:D$401,MATCH(57,DATA2026!K$2:K$401,0)),"") | N74: =IFERROR(INDEX(DATA2026!B$2:B$401,MATCH(57,DATA2026!L$2:L$401,0)),"") | O74: =IFERROR(INDEX(DATA2026!C$2:C$401,MATCH(57,DATA2026!L$2:L$401,0)),"") | P74: =IFERROR(INDEX(DATA2026!D$2:D$401,MATCH(57,DATA2026!L$2:L$401,0)),"")
B75: =IFERROR(INDEX(DATA2026!B$2:B$401,MATCH(58,DATA2026!I$2:I$401,0)),"") | C75: =IFERROR(INDEX(DATA2026!C$2:C$401,MATCH(58,DATA2026!I$2:I$401,0)),"") | D75: =IFERROR(INDEX(DATA2026!D$2:D$401,MATCH(58,DATA2026!I$2:I$401,0)),"") | F75: =IFERROR(INDEX(DATA2026!B$2:B$401,MATCH(58,DATA2026!J$2:J$401,0)),"") | G75: =IFERROR(INDEX(DATA2026!C$2:C$401,MATCH(58,DATA2026!J$2:J$401,0)),"") | H75: =IFERROR(INDEX(DATA2026!D$2:D$401,MATCH(58,DATA2026!J$2:J$401,0)),"") | J75: =IFERROR(INDEX(DATA2026!B$2:B$401,MATCH(58,DATA2026!K$2:K$401,0)),"") | K75: =IFERROR(INDEX(DATA2026!C$2:C$401,MATCH(58,DATA2026!K$2:K$401,0)),"") | L75: =IFERROR(INDEX(DATA2026!D$2:D$401,MATCH(58,DATA2026!K$2:K$401,0)),"") | N75: =IFERROR(INDEX(DATA2026!B$2:B$401,MATCH(58,DATA2026!L$2:L$401,0)),"") | O75: =IFERROR(INDEX(DATA2026!C$2:C$401,MATCH(58,DATA2026!L$2:L$401,0)),"") | P75: =IFERROR(INDEX(DATA2026!D$2:D$401,MATCH(58,DATA2026!L$2:L$401,0)),"")
B76: =IFERROR(INDEX(DATA2026!B$2:B$401,MATCH(59,DATA2026!I$2:I$401,0)),"") | C76: =IFERROR(INDEX(DATA2026!C$2:C$401,MATCH(59,DATA2026!I$2:I$401,0)),"") | D76: =IFERROR(INDEX(DATA2026!D$2:D$401,MATCH(59,DATA2026!I$2:I$401,0)),"") | F76: =IFERROR(INDEX(DATA2026!B$2:B$401,MATCH(59,DATA2026!J$2:J$401,0)),"") | G76: =IFERROR(INDEX(DATA2026!C$2:C$401,MATCH(59,DATA2026!J$2:J$401,0)),"") | H76: =IFERROR(INDEX(DATA2026!D$2:D$401,MATCH(59,DATA2026!J$2:J$401,0)),"") | J76: =IFERROR(INDEX(DATA2026!B$2:B$401,MATCH(59,DATA2026!K$2:K$401,0)),"") | K76: =IFERROR(INDEX(DATA2026!C$2:C$401,MATCH(59,DATA2026!K$2:K$401,0)),"") | L76: =IFERROR(INDEX(DATA2026!D$2:D$401,MATCH(59,DATA2026!K$2:K$401,0)),"") | N76: =IFERROR(INDEX(DATA2026!B$2:B$401,MATCH(59,DATA2026!L$2:L$401,0)),"") | O76: =IFERROR(INDEX(DATA2026!C$2:C$401,MATCH(59,DATA2026!L$2:L$401,0)),"") | P76: =IFERROR(INDEX(DATA2026!D$2:D$401,MATCH(59,DATA2026!L$2:L$401,0)),"")
B77: =IFERROR(INDEX(DATA2026!B$2:B$401,MATCH(60,DATA2026!I$2:I$401,0)),"") | C77: =IFERROR(INDEX(DATA2026!C$2:C$401,MATCH(60,DATA2026!I$2:I$401,0)),"") | D77: =IFERROR(INDEX(DATA2026!D$2:D$401,MATCH(60,DATA2026!I$2:I$401,0)),"") | F77: =IFERROR(INDEX(DATA2026!B$2:B$401,MATCH(60,DATA2026!J$2:J$401,0)),"") | G77: =IFERROR(INDEX(DATA2026!C$2:C$401,MATCH(60,DATA2026!J$2:J$401,0)),"") | H77: =IFERROR(INDEX(DATA2026!D$2:D$401,MATCH(60,DATA2026!J$2:J$401,0)),"") | J77: =IFERROR(INDEX(DATA2026!B$2:B$401,MATCH(60,DATA2026!K$2:K$401,0)),"") | K77: =IFERROR(INDEX(DATA2026!C$2:C$401,MATCH(60,DATA2026!K$2:K$401,0)),"") | L77: =IFERROR(INDEX(DATA2026!D$2:D$401,MATCH(60,DATA2026!K$2:K$401,0)),"") | N77: =IFERROR(INDEX(DATA2026!B$2:B$401,MATCH(60,DATA2026!L$2:L$401,0)),"") | O77: =IFERROR(INDEX(DATA2026!C$2:C$401,MATCH(60,DATA2026!L$2:L$401,0)),"") | P77: =IFERROR(INDEX(DATA2026!D$2:D$401,MATCH(60,DATA2026!L$2:L$401,0)),"")
B78: =IFERROR(INDEX(DATA2026!B$2:B$401,MATCH(61,DATA2026!I$2:I$401,0)),"") | C78: =IFERROR(INDEX(DATA2026!C$2:C$401,MATCH(61,DATA2026!I$2:I$401,0)),"") | D78: =IFERROR(INDEX(DATA2026!D$2:D$401,MATCH(61,DATA2026!I$2:I$401,0)),"") | F78: =IFERROR(INDEX(DATA2026!B$2:B$401,MATCH(61,DATA2026!J$2:J$401,0)),"") | G78: =IFERROR(INDEX(DATA2026!C$2:C$401,MATCH(61,DATA2026!J$2:J$401,0)),"") | H78: =IFERROR(INDEX(DATA2026!D$2:D$401,MATCH(61,DATA2026!J$2:J$401,0)),"") | J78: =IFERROR(INDEX(DATA2026!B$2:B$401,MATCH(61,DATA2026!K$2:K$401,0)),"") | K78: =IFERROR(INDEX(DATA2026!C$2:C$401,MATCH(61,DATA2026!K$2:K$401,0)),"") | L78: =IFERROR(INDEX(DATA2026!D$2:D$401,MATCH(61,DATA2026!K$2:K$401,0)),"") | N78: =IFERROR(INDEX(DATA2026!B$2:B$401,MATCH(61,DATA2026!L$2:L$401,0)),"") | O78: =IFERROR(INDEX(DATA2026!C$2:C$401,MATCH(61,DATA2026!L$2:L$401,0)),"") | P78: =IFERROR(INDEX(DATA2026!D$2:D$401,MATCH(61,DATA2026!L$2:L$401,0)),"")
B79: =IFERROR(INDEX(DATA2026!B$2:B$401,MATCH(62,DATA2026!I$2:I$401,0)),"") | C79: =IFERROR(INDEX(DATA2026!C$2:C$401,MATCH(62,DATA2026!I$2:I$401,0)),"") | D79: =IFERROR(INDEX(DATA2026!D$2:D$401,MATCH(62,DATA2026!I$2:I$401,0)),"") | F79: =IFERROR(INDEX(DATA2026!B$2:B$401,MATCH(62,DATA2026!J$2:J$401,0)),"") | G79: =IFERROR(INDEX(DATA2026!C$2:C$401,MATCH(62,DATA2026!J$2:J$401,0)),"") | H79: =IFERROR(INDEX(DATA2026!D$2:D$401,MATCH(62,DATA2026!J$2:J$401,0)),"") | J79: =IFERROR(INDEX(DATA2026!B$2:B$401,MATCH(62,DATA2026!K$2:K$401,0)),"") | K79: =IFERROR(INDEX(DATA2026!C$2:C$401,MATCH(62,DATA2026!K$2:K$401,0)),"") | L79: =IFERROR(INDEX(DATA2026!D$2:D$401,MATCH(62,DATA2026!K$2:K$401,0)),"") | N79: =IFERROR(INDEX(DATA2026!B$2:B$401,MATCH(62,DATA2026!L$2:L$401,0)),"") | O79: =IFERROR(INDEX(DATA2026!C$2:C$401,MATCH(62,DATA2026!L$2:L$401,0)),"") | P79: =IFERROR(INDEX(DATA2026!D$2:D$401,MATCH(62,DATA2026!L$2:L$401,0)),"")
B80: =IFERROR(INDEX(DATA2026!B$2:B$401,MATCH(63,DATA2026!I$2:I$401,0)),"") | C80: =IFERROR(INDEX(DATA2026!C$2:C$401,MATCH(63,DATA2026!I$2:I$401,0)),"") | D80: =IFERROR(INDEX(DATA2026!D$2:D$401,MATCH(63,DATA2026!I$2:I$401,0)),"") | F80: =IFERROR(INDEX(DATA2026!B$2:B$401,MATCH(63,DATA2026!J$2:J$401,0)),"") | G80: =IFERROR(INDEX(DATA2026!C$2:C$401,MATCH(63,DATA2026!J$2:J$401,0)),"") | H80: =IFERROR(INDEX(DATA2026!D$2:D$401,MATCH(63,DATA2026!J$2:J$401,0)),"") | J80: =IFERROR(INDEX(DATA2026!B$2:B$401,MATCH(63,DATA2026!K$2:K$401,0)),"") | K80: =IFERROR(INDEX(DATA2026!C$2:C$401,MATCH(63,DATA2026!K$2:K$401,0)),"") | L80: =IFERROR(INDEX(DATA2026!D$2:D$401,MATCH(63,DATA2026!K$2:K$401,0)),"") | N80: =IFERROR(INDEX(DATA2026!B$2:B$401,MATCH(63,DATA2026!L$2:L$401,0)),"") | O80: =IFERROR(INDEX(DATA2026!C$2:C$401,MATCH(63,DATA2026!L$2:L$401,0)),"") | P80: =IFERROR(INDEX(DATA2026!D$2:D$401,MATCH(63,DATA2026!L$2:L$401,0)),"")
B81: =IFERROR(INDEX(DATA2026!B$2:B$401,MATCH(64,DATA2026!I$2:I$401,0)),"") | C81: =IFERROR(INDEX(DATA2026!C$2:C$401,MATCH(64,DATA2026!I$2:I$401,0)),"") | D81: =IFERROR(INDEX(DATA2026!D$2:D$401,MATCH(64,DATA2026!I$2:I$401,0)),"") | F81: =IFERROR(INDEX(DATA2026!B$2:B$401,MATCH(64,DATA2026!J$2:J$401,0)),"") | G81: =IFERROR(INDEX(DATA2026!C$2:C$401,MATCH(64,DATA2026!J$2:J$401,0)),"") | H81: =IFERROR(INDEX(DATA2026!D$2:D$401,MATCH(64,DATA2026!J$2:J$401,0)),"") | J81: =IFERROR(INDEX(DATA2026!B$2:B$401,MATCH(64,DATA2026!K$2:K$401,0)),"") | K81: =IFERROR(INDEX(DATA2026!C$2:C$401,MATCH(64,DATA2026!K$2:K$401,0)),"") | L81: =IFERROR(INDEX(DATA2026!D$2:D$401,MATCH(64,DATA2026!K$2:K$401,0)),"") | N81: =IFERROR(INDEX(DATA2026!B$2:B$401,MATCH(64,DATA2026!L$2:L$401,0)),"") | O81: =IFERROR(INDEX(DATA2026!C$2:C$401,MATCH(64,DATA2026!L$2:L$401,0)),"") | P81: =IFERROR(INDEX(DATA2026!D$2:D$401,MATCH(64,DATA2026!L$2:L$401,0)),"")
B82: =IFERROR(INDEX(DATA2026!B$2:B$401,MATCH(65,DATA2026!I$2:I$401,0)),"") | C82: =IFERROR(INDEX(DATA2026!C$2:C$401,MATCH(65,DATA2026!I$2:I$401,0)),"") | D82: =IFERROR(INDEX(DATA2026!D$2:D$401,MATCH(65,DATA2026!I$2:I$401,0)),"") | F82: =IFERROR(INDEX(DATA2026!B$2:B$401,MATCH(65,DATA2026!J$2:J$401,0)),"") | G82: =IFERROR(INDEX(DATA2026!C$2:C$401,MATCH(65,DATA2026!J$2:J$401,0)),"") | H82: =IFERROR(INDEX(DATA2026!D$2:D$401,MATCH(65,DATA2026!J$2:J$401,0)),"") | J82: =IFERROR(INDEX(DATA2026!B$2:B$401,MATCH(65,DATA2026!K$2:K$401,0)),"") | K82: =IFERROR(INDEX(DATA2026!C$2:C$401,MATCH(65,DATA2026!K$2:K$401,0)),"") | L82: =IFERROR(INDEX(DATA2026!D$2:D$401,MATCH(65,DATA2026!K$2:K$401,0)),"") | N82: =IFERROR(INDEX(DATA2026!B$2:B$401,MATCH(65,DATA2026!L$2:L$401,0)),"") | O82: =IFERROR(INDEX(DATA2026!C$2:C$401,MATCH(65,DATA2026!L$2:L$401,0)),"") | P82: =IFERROR(INDEX(DATA2026!D$2:D$401,MATCH(65,DATA2026!L$2:L$401,0)),"")
B83: =IFERROR(INDEX(DATA2026!B$2:B$401,MATCH(66,DATA2026!I$2:I$401,0)),"") | C83: =IFERROR(INDEX(DATA2026!C$2:C$401,MATCH(66,DATA2026!I$2:I$401,0)),"") | D83: =IFERROR(INDEX(DATA2026!D$2:D$401,MATCH(66,DATA2026!I$2:I$401,0)),"") | F83: =IFERROR(INDEX(DATA2026!B$2:B$401,MATCH(66,DATA2026!J$2:J$401,0)),"") | G83: =IFERROR(INDEX(DATA2026!C$2:C$401,MATCH(66,DATA2026!J$2:J$401,0)),"") | H83: =IFERROR(INDEX(DATA2026!D$2:D$401,MATCH(66,DATA2026!J$2:J$401,0)),"") | J83: =IFERROR(INDEX(DATA2026!B$2:B$401,MATCH(66,DATA2026!K$2:K$401,0)),"") | K83: =IFERROR(INDEX(DATA2026!C$2:C$401,MATCH(66,DATA2026!K$2:K$401,0)),"") | L83: =IFERROR(INDEX(DATA2026!D$2:D$401,MATCH(66,DATA2026!K$2:K$401,0)),"") | N83: =IFERROR(INDEX(DATA2026!B$2:B$401,MATCH(66,DATA2026!L$2:L$401,0)),"") | O83: =IFERROR(INDEX(DATA2026!C$2:C$401,MATCH(66,DATA2026!L$2:L$401,0)),"") | P83: =IFERROR(INDEX(DATA2026!D$2:D$401,MATCH(66,DATA2026!L$2:L$401,0)),"")
B84: =IFERROR(INDEX(DATA2026!B$2:B$401,MATCH(67,DATA2026!I$2:I$401,0)),"") | C84: =IFERROR(INDEX(DATA2026!C$2:C$401,MATCH(67,DATA2026!I$2:I$401,0)),"") | D84: =IFERROR(INDEX(DATA2026!D$2:D$401,MATCH(67,DATA2026!I$2:I$401,0)),"") | F84: =IFERROR(INDEX(DATA2026!B$2:B$401,MATCH(67,DATA2026!J$2:J$401,0)),"") | G84: =IFERROR(INDEX(DATA2026!C$2:C$401,MATCH(67,DATA2026!J$2:J$401,0)),"") | H84: =IFERROR(INDEX(DATA2026!D$2:D$401,MATCH(67,DATA2026!J$2:J$401,0)),"") | J84: =IFERROR(INDEX(DATA2026!B$2:B$401,MATCH(67,DATA2026!K$2:K$401,0)),"") | K84: =IFERROR(INDEX(DATA2026!C$2:C$401,MATCH(67,DATA2026!K$2:K$401,0)),"") | L84: =IFERROR(INDEX(DATA2026!D$2:D$401,MATCH(67,DATA2026!K$2:K$401,0)),"") | N84: =IFERROR(INDEX(DATA2026!B$2:B$401,MATCH(67,DATA2026!L$2:L$401,0)),"") | O84: =IFERROR(INDEX(DATA2026!C$2:C$401,MATCH(67,DATA2026!L$2:L$401,0)),"") | P84: =IFERROR(INDEX(DATA2026!D$2:D$401,MATCH(67,DATA2026!L$2:L$401,0)),"")
B85: =IFERROR(INDEX(DATA2026!B$2:B$401,MATCH(68,DATA2026!I$2:I$401,0)),"") | C85: =IFERROR(INDEX(DATA2026!C$2:C$401,MATCH(68,DATA2026!I$2:I$401,0)),"") | D85: =IFERROR(INDEX(DATA2026!D$2:D$401,MATCH(68,DATA2026!I$2:I$401,0)),"") | F85: =IFERROR(INDEX(DATA2026!B$2:B$401,MATCH(68,DATA2026!J$2:J$401,0)),"") | G85: =IFERROR(INDEX(DATA2026!C$2:C$401,MATCH(68,DATA2026!J$2:J$401,0)),"") | H85: =IFERROR(INDEX(DATA2026!D$2:D$401,MATCH(68,DATA2026!J$2:J$401,0)),"") | J85: =IFERROR(INDEX(DATA2026!B$2:B$401,MATCH(68,DATA2026!K$2:K$401,0)),"") | K85: =IFERROR(INDEX(DATA2026!C$2:C$401,MATCH(68,DATA2026!K$2:K$401,0)),"") | L85: =IFERROR(INDEX(DATA2026!D$2:D$401,MATCH(68,DATA2026!K$2:K$401,0)),"") | N85: =IFERROR(INDEX(DATA2026!B$2:B$401,MATCH(68,DATA2026!L$2:L$401,0)),"") | O85: =IFERROR(INDEX(DATA2026!C$2:C$401,MATCH(68,DATA2026!L$2:L$401,0)),"") | P85: =IFERROR(INDEX(DATA2026!D$2:D$401,MATCH(68,DATA2026!L$2:L$401,0)),"")
B86: =IFERROR(INDEX(DATA2026!B$2:B$401,MATCH(69,DATA2026!I$2:I$401,0)),"") | C86: =IFERROR(INDEX(DATA2026!C$2:C$401,MATCH(69,DATA2026!I$2:I$401,0)),"") | D86: =IFERROR(INDEX(DATA2026!D$2:D$401,MATCH(69,DATA2026!I$2:I$401,0)),"") | F86: =IFERROR(INDEX(DATA2026!B$2:B$401,MATCH(69,DATA2026!J$2:J$401,0)),"") | G86: =IFERROR(INDEX(DATA2026!C$2:C$401,MATCH(69,DATA2026!J$2:J$401,0)),"") | H86: =IFERROR(INDEX(DATA2026!D$2:D$401,MATCH(69,DATA2026!J$2:J$401,0)),"") | J86: =IFERROR(INDEX(DATA2026!B$2:B$401,MATCH(69,DATA2026!K$2:K$401,0)),"") | K86: =IFERROR(INDEX(DATA2026!C$2:C$401,MATCH(69,DATA2026!K$2:K$401,0)),"") | L86: =IFERROR(INDEX(DATA2026!D$2:D$401,MATCH(69,DATA2026!K$2:K$401,0)),"") | N86: =IFERROR(INDEX(DATA2026!B$2:B$401,MATCH(69,DATA2026!L$2:L$401,0)),"") | O86: =IFERROR(INDEX(DATA2026!C$2:C$401,MATCH(69,DATA2026!L$2:L$401,0)),"") | P86: =IFERROR(INDEX(DATA2026!D$2:D$401,MATCH(69,DATA2026!L$2:L$401,0)),"")
B87: =IFERROR(INDEX(DATA2026!B$2:B$401,MATCH(70,DATA2026!I$2:I$401,0)),"") | C87: =IFERROR(INDEX(DATA2026!C$2:C$401,MATCH(70,DATA2026!I$2:I$401,0)),"") | D87: =IFERROR(INDEX(DATA2026!D$2:D$401,MATCH(70,DATA2026!I$2:I$401,0)),"") | F87: =IFERROR(INDEX(DATA2026!B$2:B$401,MATCH(70,DATA2026!J$2:J$401,0)),"") | G87: =IFERROR(INDEX(DATA2026!C$2:C$401,MATCH(70,DATA2026!J$2:J$401,0)),"") | H87: =IFERROR(INDEX(DATA2026!D$2:D$401,MATCH(70,DATA2026!J$2:J$401,0)),"") | J87: =IFERROR(INDEX(DATA2026!B$2:B$401,MATCH(70,DATA2026!K$2:K$401,0)),"") | K87: =IFERROR(INDEX(DATA2026!C$2:C$401,MATCH(70,DATA2026!K$2:K$401,0)),"") | L87: =IFERROR(INDEX(DATA2026!D$2:D$401,MATCH(70,DATA2026!K$2:K$401,0)),"") | N87: =IFERROR(INDEX(DATA2026!B$2:B$401,MATCH(70,DATA2026!L$2:L$401,0)),"") | O87: =IFERROR(INDEX(DATA2026!C$2:C$401,MATCH(70,DATA2026!L$2:L$401,0)),"") | P87: =IFERROR(INDEX(DATA2026!D$2:D$401,MATCH(70,DATA2026!L$2:L$401,0)),"")
B88: =IFERROR(INDEX(DATA2026!B$2:B$401,MATCH(71,DATA2026!I$2:I$401,0)),"") | C88: =IFERROR(INDEX(DATA2026!C$2:C$401,MATCH(71,DATA2026!I$2:I$401,0)),"") | D88: =IFERROR(INDEX(DATA2026!D$2:D$401,MATCH(71,DATA2026!I$2:I$401,0)),"") | F88: =IFERROR(INDEX(DATA2026!B$2:B$401,MATCH(71,DATA2026!J$2:J$401,0)),"") | G88: =IFERROR(INDEX(DATA2026!C$2:C$401,MATCH(71,DATA2026!J$2:J$401,0)),"") | H88: =IFERROR(INDEX(DATA2026!D$2:D$401,MATCH(71,DATA2026!J$2:J$401,0)),"") | J88: =IFERROR(INDEX(DATA2026!B$2:B$401,MATCH(71,DATA2026!K$2:K$401,0)),"") | K88: =IFERROR(INDEX(DATA2026!C$2:C$401,MATCH(71,DATA2026!K$2:K$401,0)),"") | L88: =IFERROR(INDEX(DATA2026!D$2:D$401,MATCH(71,DATA2026!K$2:K$401,0)),"") | N88: =IFERROR(INDEX(DATA2026!B$2:B$401,MATCH(71,DATA2026!L$2:L$401,0)),"") | O88: =IFERROR(INDEX(DATA2026!C$2:C$401,MATCH(71,DATA2026!L$2:L$401,0)),"") | P88: =IFERROR(INDEX(DATA2026!D$2:D$401,MATCH(71,DATA2026!L$2:L$401,0)),"")
B89: =IFERROR(INDEX(DATA2026!B$2:B$401,MATCH(72,DATA2026!I$2:I$401,0)),"") | C89: =IFERROR(INDEX(DATA2026!C$2:C$401,MATCH(72,DATA2026!I$2:I$401,0)),"") | D89: =IFERROR(INDEX(DATA2026!D$2:D$401,MATCH(72,DATA2026!I$2:I$401,0)),"") | F89: =IFERROR(INDEX(DATA2026!B$2:B$401,MATCH(72,DATA2026!J$2:J$401,0)),"") | G89: =IFERROR(INDEX(DATA2026!C$2:C$401,MATCH(72,DATA2026!J$2:J$401,0)),"") | H89: =IFERROR(INDEX(DATA2026!D$2:D$401,MATCH(72,DATA2026!J$2:J$401,0)),"") | J89: =IFERROR(INDEX(DATA2026!B$2:B$401,MATCH(72,DATA2026!K$2:K$401,0)),"") | K89: =IFERROR(INDEX(DATA2026!C$2:C$401,MATCH(72,DATA2026!K$2:K$401,0)),"") | L89: =IFERROR(INDEX(DATA2026!D$2:D$401,MATCH(72,DATA2026!K$2:K$401,0)),"") | N89: =IFERROR(INDEX(DATA2026!B$2:B$401,MATCH(72,DATA2026!L$2:L$401,0)),"") | O89: =IFERROR(INDEX(DATA2026!C$2:C$401,MATCH(72,DATA2026!L$2:L$401,0)),"") | P89: =IFERROR(INDEX(DATA2026!D$2:D$401,MATCH(72,DATA2026!L$2:L$401,0)),"")
B90: =IFERROR(INDEX(DATA2026!B$2:B$401,MATCH(73,DATA2026!I$2:I$401,0)),"") | C90: =IFERROR(INDEX(DATA2026!C$2:C$401,MATCH(73,DATA2026!I$2:I$401,0)),"") | D90: =IFERROR(INDEX(DATA2026!D$2:D$401,MATCH(73,DATA2026!I$2:I$401,0)),"") | F90: =IFERROR(INDEX(DATA2026!B$2:B$401,MATCH(73,DATA2026!J$2:J$401,0)),"") | G90: =IFERROR(INDEX(DATA2026!C$2:C$401,MATCH(73,DATA2026!J$2:J$401,0)),"") | H90: =IFERROR(INDEX(DATA2026!D$2:D$401,MATCH(73,DATA2026!J$2:J$401,0)),"") | J90: =IFERROR(INDEX(DATA2026!B$2:B$401,MATCH(73,DATA2026!K$2:K$401,0)),"") | K90: =IFERROR(INDEX(DATA2026!C$2:C$401,MATCH(73,DATA2026!K$2:K$401,0)),"") | L90: =IFERROR(INDEX(DATA2026!D$2:D$401,MATCH(73,DATA2026!K$2:K$401,0)),"") | N90: =IFERROR(INDEX(DATA2026!B$2:B$401,MATCH(73,DATA2026!L$2:L$401,0)),"") | O90: =IFERROR(INDEX(DATA2026!C$2:C$401,MATCH(73,DATA2026!L$2:L$401,0)),"") | P90: =IFERROR(INDEX(DATA2026!D$2:D$401,MATCH(73,DATA2026!L$2:L$401,0)),"")
B91: =IFERROR(INDEX(DATA2026!B$2:B$401,MATCH(74,DATA2026!I$2:I$401,0)),"") | C91: =IFERROR(INDEX(DATA2026!C$2:C$401,MATCH(74,DATA2026!I$2:I$401,0)),"") | D91: =IFERROR(INDEX(DATA2026!D$2:D$401,MATCH(74,DATA2026!I$2:I$401,0)),"") | F91: =IFERROR(INDEX(DATA2026!B$2:B$401,MATCH(74,DATA2026!J$2:J$401,0)),"") | G91: =IFERROR(INDEX(DATA2026!C$2:C$401,MATCH(74,DATA2026!J$2:J$401,0)),"") | H91: =IFERROR(INDEX(DATA2026!D$2:D$401,MATCH(74,DATA2026!J$2:J$401,0)),"") | J91: =IFERROR(INDEX(DATA2026!B$2:B$401,MATCH(74,DATA2026!K$2:K$401,0)),"") | K91: =IFERROR(INDEX(DATA2026!C$2:C$401,MATCH(74,DATA2026!K$2:K$401,0)),"") | L91: =IFERROR(INDEX(DATA2026!D$2:D$401,MATCH(74,DATA2026!K$2:K$401,0)),"") | N91: =IFERROR(INDEX(DATA2026!B$2:B$401,MATCH(74,DATA2026!L$2:L$401,0)),"") | O91: =IFERROR(INDEX(DATA2026!C$2:C$401,MATCH(74,DATA2026!L$2:L$401,0)),"") | P91: =IFERROR(INDEX(DATA2026!D$2:D$401,MATCH(74,DATA2026!L$2:L$401,0)),"")
B92: =IFERROR(INDEX(DATA2026!B$2:B$401,MATCH(75,DATA2026!I$2:I$401,0)),"") | C92: =IFERROR(INDEX(DATA2026!C$2:C$401,MATCH(75,DATA2026!I$2:I$401,0)),"") | D92: =IFERROR(INDEX(DATA2026!D$2:D$401,MATCH(75,DATA2026!I$2:I$401,0)),"") | F92: =IFERROR(INDEX(DATA2026!B$2:B$401,MATCH(75,DATA2026!J$2:J$401,0)),"") | G92: =IFERROR(INDEX(DATA2026!C$2:C$401,MATCH(75,DATA2026!J$2:J$401,0)),"") | H92: =IFERROR(INDEX(DATA2026!D$2:D$401,MATCH(75,DATA2026!J$2:J$401,0)),"") | J92: =IFERROR(INDEX(DATA2026!B$2:B$401,MATCH(75,DATA2026!K$2:K$401,0)),"") | K92: =IFERROR(INDEX(DATA2026!C$2:C$401,MATCH(75,DATA2026!K$2:K$401,0)),"") | L92: =IFERROR(INDEX(DATA2026!D$2:D$401,MATCH(75,DATA2026!K$2:K$401,0)),"") | N92: =IFERROR(INDEX(DATA2026!B$2:B$401,MATCH(75,DATA2026!L$2:L$401,0)),"") | O92: =IFERROR(INDEX(DATA2026!C$2:C$401,MATCH(75,DATA2026!L$2:L$401,0)),"") | P92: =IFERROR(INDEX(DATA2026!D$2:D$401,MATCH(75,DATA2026!L$2:L$401,0)),"")
B93: =IFERROR(INDEX(DATA2026!B$2:B$401,MATCH(76,DATA2026!I$2:I$401,0)),"") | C93: =IFERROR(INDEX(DATA2026!C$2:C$401,MATCH(76,DATA2026!I$2:I$401,0)),"") | D93: =IFERROR(INDEX(DATA2026!D$2:D$401,MATCH(76,DATA2026!I$2:I$401,0)),"") | F93: =IFERROR(INDEX(DATA2026!B$2:B$401,MATCH(76,DATA2026!J$2:J$401,0)),"") | G93: =IFERROR(INDEX(DATA2026!C$2:C$401,MATCH(76,DATA2026!J$2:J$401,0)),"") | H93: =IFERROR(INDEX(DATA2026!D$2:D$401,MATCH(76,DATA2026!J$2:J$401,0)),"") | J93: =IFERROR(INDEX(DATA2026!B$2:B$401,MATCH(76,DATA2026!K$2:K$401,0)),"") | K93: =IFERROR(INDEX(DATA2026!C$2:C$401,MATCH(76,DATA2026!K$2:K$401,0)),"") | L93: =IFERROR(INDEX(DATA2026!D$2:D$401,MATCH(76,DATA2026!K$2:K$401,0)),"") | N93: =IFERROR(INDEX(DATA2026!B$2:B$401,MATCH(76,DATA2026!L$2:L$401,0)),"") | O93: =IFERROR(INDEX(DATA2026!C$2:C$401,MATCH(76,DATA2026!L$2:L$401,0)),"") | P93: =IFERROR(INDEX(DATA2026!D$2:D$401,MATCH(76,DATA2026!L$2:L$401,0)),"")
B94: =IFERROR(INDEX(DATA2026!B$2:B$401,MATCH(77,DATA2026!I$2:I$401,0)),"") | C94: =IFERROR(INDEX(DATA2026!C$2:C$401,MATCH(77,DATA2026!I$2:I$401,0)),"") | D94: =IFERROR(INDEX(DATA2026!D$2:D$401,MATCH(77,DATA2026!I$2:I$401,0)),"") | F94: =IFERROR(INDEX(DATA2026!B$2:B$401,MATCH(77,DATA2026!J$2:J$401,0)),"") | G94: =IFERROR(INDEX(DATA2026!C$2:C$401,MATCH(77,DATA2026!J$2:J$401,0)),"") | H94: =IFERROR(INDEX(DATA2026!D$2:D$401,MATCH(77,DATA2026!J$2:J$401,0)),"") | J94: =IFERROR(INDEX(DATA2026!B$2:B$401,MATCH(77,DATA2026!K$2:K$401,0)),"") | K94: =IFERROR(INDEX(DATA2026!C$2:C$401,MATCH(77,DATA2026!K$2:K$401,0)),"") | L94: =IFERROR(INDEX(DATA2026!D$2:D$401,MATCH(77,DATA2026!K$2:K$401,0)),"") | N94: =IFERROR(INDEX(DATA2026!B$2:B$401,MATCH(77,DATA2026!L$2:L$401,0)),"") | O94: =IFERROR(INDEX(DATA2026!C$2:C$401,MATCH(77,DATA2026!L$2:L$401,0)),"") | P94: =IFERROR(INDEX(DATA2026!D$2:D$401,MATCH(77,DATA2026!L$2:L$401,0)),"")
B95: =IFERROR(INDEX(DATA2026!B$2:B$401,MATCH(78,DATA2026!I$2:I$401,0)),"") | C95: =IFERROR(INDEX(DATA2026!C$2:C$401,MATCH(78,DATA2026!I$2:I$401,0)),"") | D95: =IFERROR(INDEX(DATA2026!D$2:D$401,MATCH(78,DATA2026!I$2:I$401,0)),"") | F95: =IFERROR(INDEX(DATA2026!B$2:B$401,MATCH(78,DATA2026!J$2:J$401,0)),"") | G95: =IFERROR(INDEX(DATA2026!C$2:C$401,MATCH(78,DATA2026!J$2:J$401,0)),"") | H95: =IFERROR(INDEX(DATA2026!D$2:D$401,MATCH(78,DATA2026!J$2:J$401,0)),"") | J95: =IFERROR(INDEX(DATA2026!B$2:B$401,MATCH(78,DATA2026!K$2:K$401,0)),"") | K95: =IFERROR(INDEX(DATA2026!C$2:C$401,MATCH(78,DATA2026!K$2:K$401,0)),"") | L95: =IFERROR(INDEX(DATA2026!D$2:D$401,MATCH(78,DATA2026!K$2:K$401,0)),"") | N95: =IFERROR(INDEX(DATA2026!B$2:B$401,MATCH(78,DATA2026!L$2:L$401,0)),"") | O95: =IFERROR(INDEX(DATA2026!C$2:C$401,MATCH(78,DATA2026!L$2:L$401,0)),"") | P95: =IFERROR(INDEX(DATA2026!D$2:D$401,MATCH(78,DATA2026!L$2:L$401,0)),"")
B96: =IFERROR(INDEX(DATA2026!B$2:B$401,MATCH(79,DATA2026!I$2:I$401,0)),"") | C96: =IFERROR(INDEX(DATA2026!C$2:C$401,MATCH(79,DATA2026!I$2:I$401,0)),"") | D96: =IFERROR(INDEX(DATA2026!D$2:D$401,MATCH(79,DATA2026!I$2:I$401,0)),"") | F96: =IFERROR(INDEX(DATA2026!B$2:B$401,MATCH(79,DATA2026!J$2:J$401,0)),"") | G96: =IFERROR(INDEX(DATA2026!C$2:C$401,MATCH(79,DATA2026!J$2:J$401,0)),"") | H96: =IFERROR(INDEX(DATA2026!D$2:D$401,MATCH(79,DATA2026!J$2:J$401,0)),"") | J96: =IFERROR(INDEX(DATA2026!B$2:B$401,MATCH(79,DATA2026!K$2:K$401,0)),"") | K96: =IFERROR(INDEX(DATA2026!C$2:C$401,MATCH(79,DATA2026!K$2:K$401,0)),"") | L96: =IFERROR(INDEX(DATA2026!D$2:D$401,MATCH(79,DATA2026!K$2:K$401,0)),"") | N96: =IFERROR(INDEX(DATA2026!B$2:B$401,MATCH(79,DATA2026!L$2:L$401,0)),"") | O96: =IFERROR(INDEX(DATA2026!C$2:C$401,MATCH(79,DATA2026!L$2:L$401,0)),"") | P96: =IFERROR(INDEX(DATA2026!D$2:D$401,MATCH(79,DATA2026!L$2:L$401,0)),"")
B97: =IFERROR(INDEX(DATA2026!B$2:B$401,MATCH(80,DATA2026!I$2:I$401,0)),"") | C97: =IFERROR(INDEX(DATA2026!C$2:C$401,MATCH(80,DATA2026!I$2:I$401,0)),"") | D97: =IFERROR(INDEX(DATA2026!D$2:D$401,MATCH(80,DATA2026!I$2:I$401,0)),"") | F97: =IFERROR(INDEX(DATA2026!B$2:B$401,MATCH(80,DATA2026!J$2:J$401,0)),"") | G97: =IFERROR(INDEX(DATA2026!C$2:C$401,MATCH(80,DATA2026!J$2:J$401,0)),"") | H97: =IFERROR(INDEX(DATA2026!D$2:D$401,MATCH(80,DATA2026!J$2:J$401,0)),"") | J97: =IFERROR(INDEX(DATA2026!B$2:B$401,MATCH(80,DATA2026!K$2:K$401,0)),"") | K97: =IFERROR(INDEX(DATA2026!C$2:C$401,MATCH(80,DATA2026!K$2:K$401,0)),"") | L97: =IFERROR(INDEX(DATA2026!D$2:D$401,MATCH(80,DATA2026!K$2:K$401,0)),"") | N97: =IFERROR(INDEX(DATA2026!B$2:B$401,MATCH(80,DATA2026!L$2:L$401,0)),"") | O97: =IFERROR(INDEX(DATA2026!C$2:C$401,MATCH(80,DATA2026!L$2:L$401,0)),"") | P97: =IFERROR(INDEX(DATA2026!D$2:D$401,MATCH(80,DATA2026!L$2:L$401,0)),"")
B98: ∑ Geplante Stunden (Q12026) | D98: =SUMIF(DATA2026!A$2:A$401,"Q12026",DATA2026!E$2:E$401) -> 0 | F98: ∑ Geplante Stunden (Q22026) | H98: =SUMIF(DATA2026!A$2:A$401,"Q22026",DATA2026!E$2:E$401) -> 660 | J98: ∑ Geplante Stunden (Q32026) | L98: =SUMIF(DATA2026!A$2:A$401,"Q32026",DATA2026!E$2:E$401) -> 1269 | N98: ∑ Geplante Stunden (Q42026) | P98: =SUMIF(DATA2026!A$2:A$401,"Q42026",DATA2026!E$2:E$401) -> 0
B100: ℹ️ Tage = manuelle Eingabe (blau) · Stunden = automatisch (Tage × 8) | Projekte: Zuweisung per Dropdown in Quartal-Blättern | 🟡 Gelb = aus PO-Backlog
B101: 🟢 Strengthen · 🔵 Innovation · 🔴 Repair | S <10h · M 10–20h · L 20–40h · XL >40h · XXL >160h

Sheet Dashboard2026
A1: DASHBOARD — Roadmap 2026
A3: VALUE-BUCKET VERTEILUNG — Anzahl & Prozent
B4: Q1 | C4: Q2 | D4: Q3 | E4: Q4 | F4: Gesamt Jahr
A5: Strengthen (Anzahl) | B5: =COUNTIFS(DATA2026!A$2:A$401,"Q12026",DATA2026!D$2:D$401,"Strengthen") -> 0 | C5: =COUNTIFS(DATA2026!A$2:A$401,"Q22026",DATA2026!D$2:D$401,"Strengthen") -> 7 | D5: =COUNTIFS(DATA2026!A$2:A$401,"Q32026",DATA2026!D$2:D$401,"Strengthen") -> 16 | E5: =COUNTIFS(DATA2026!A$2:A$401,"Q42026",DATA2026!D$2:D$401,"Strengthen") -> 11 | F5: =COUNTIF(DATA2026!D$2:D$401,"Strengthen") -> 34
A6: Strengthen (%) | B6: =IFERROR(B5/B11,"") | C6: =IFERROR(C5/C11,"") -> 0.5 | D6: =IFERROR(D5/D11,"") -> 0.66666667 | E6: =IFERROR(E5/E11,"") -> 0.64705882 | F6: =IFERROR(F5/F11,"") -> 0.61818182
A7: Innovation (Anzahl) | B7: =COUNTIFS(DATA2026!A$2:A$401,"Q12026",DATA2026!D$2:D$401,"Innovation") -> 0 | C7: =COUNTIFS(DATA2026!A$2:A$401,"Q22026",DATA2026!D$2:D$401,"Innovation") -> 1 | D7: =COUNTIFS(DATA2026!A$2:A$401,"Q32026",DATA2026!D$2:D$401,"Innovation") -> 5 | E7: =COUNTIFS(DATA2026!A$2:A$401,"Q42026",DATA2026!D$2:D$401,"Innovation") -> 5 | F7: =COUNTIF(DATA2026!D$2:D$401,"Innovation") -> 11
A8: Innovation (%) | B8: =IFERROR(B7/B11,"") | C8: =IFERROR(C7/C11,"") -> 0.071428571 | D8: =IFERROR(D7/D11,"") -> 0.20833333 | E8: =IFERROR(E7/E11,"") -> 0.29411765 | F8: =IFERROR(F7/F11,"") -> 0.2
A9: Repair (Anzahl) | B9: =COUNTIFS(DATA2026!A$2:A$401,"Q12026",DATA2026!D$2:D$401,"Repair") -> 0 | C9: =COUNTIFS(DATA2026!A$2:A$401,"Q22026",DATA2026!D$2:D$401,"Repair") -> 6 | D9: =COUNTIFS(DATA2026!A$2:A$401,"Q32026",DATA2026!D$2:D$401,"Repair") -> 3 | E9: =COUNTIFS(DATA2026!A$2:A$401,"Q42026",DATA2026!D$2:D$401,"Repair") -> 1 | F9: =COUNTIF(DATA2026!D$2:D$401,"Repair") -> 10
A10: Repair (%) | B10: =IFERROR(B9/B11,"") | C10: =IFERROR(C9/C11,"") -> 0.42857143 | D10: =IFERROR(D9/D11,"") -> 0.125 | E10: =IFERROR(E9/E11,"") -> 0.058823529 | F10: =IFERROR(F9/F11,"") -> 0.18181818
A11: Gesamt Projekte | B11: =B5+B7+B9 -> 0 | C11: =C5+C7+C9 -> 14 | D11: =D5+D7+D9 -> 24 | E11: =E5+E7+E9 -> 17 | F11: =F5+F7+F9 -> 55
A14: KAPAZITÄT vs. GEPLANTE STUNDEN — pro Quartal & Team
B15: Q1 | C15: Q2 | D15: Q3 | E15: Q4
A16: Kapazität Gesamt (h) | B16: =Roadmap2026!C4 -> 0 | C16: =Roadmap2026!G4 -> 0 | D16: =Roadmap2026!K4 -> 1192 | E16: =Roadmap2026!O4 -> 0
A17: → Team Desktop (h) | B17: =Roadmap2026!C5 -> 0 | C17: =Roadmap2026!G5 -> 0 | D17: =Roadmap2026!K5 -> 608 | E17: =Roadmap2026!O5 -> 0
A18: → Team Web (h) | B18: =Roadmap2026!C6 -> 0 | C18: =Roadmap2026!G6 -> 0 | D18: =Roadmap2026!K6 -> 688 | E18: =Roadmap2026!O6 -> 0
A19: Geplant Gesamt (h) | B19: =SUMIF(DATA2026!A$2:A$401,"Q12026",DATA2026!E$2:E$401) -> 0 | C19: =SUMIF(DATA2026!A$2:A$401,"Q22026",DATA2026!E$2:E$401) -> 660 | D19: =SUMIF(DATA2026!A$2:A$401,"Q32026",DATA2026!E$2:E$401) -> 1269 | E19: =SUMIF(DATA2026!A$2:A$401,"Q42026",DATA2026!E$2:E$401) -> 0
A20: → Desktop geplant (h) | B20: =SUMIFS(DATA2026!E$2:E$401,DATA2026!A$2:A$401,"Q12026",DATA2026!G$2:G$401,"Desktop") -> 0 | C20: =SUMIFS(DATA2026!E$2:E$401,DATA2026!A$2:A$401,"Q22026",DATA2026!G$2:G$401,"Desktop") -> 444 | D20: =SUMIFS(DATA2026!E$2:E$401,DATA2026!A$2:A$401,"Q32026",DATA2026!G$2:G$401,"Desktop") -> 489 | E20: =SUMIFS(DATA2026!E$2:E$401,DATA2026!A$2:A$401,"Q42026",DATA2026!G$2:G$401,"Desktop") -> 0
A21: → Web geplant (h) | B21: =SUMIFS(DATA2026!E$2:E$401,DATA2026!A$2:A$401,"Q12026",DATA2026!G$2:G$401,"WEB") -> 0 | C21: =SUMIFS(DATA2026!E$2:E$401,DATA2026!A$2:A$401,"Q22026",DATA2026!G$2:G$401,"WEB") -> 216 | D21: =SUMIFS(DATA2026!E$2:E$401,DATA2026!A$2:A$401,"Q32026",DATA2026!G$2:G$401,"WEB") -> 672 | E21: =SUMIFS(DATA2026!E$2:E$401,DATA2026!A$2:A$401,"Q42026",DATA2026!G$2:G$401,"WEB") -> 0
A22: → W->D anteilig (h) | B22: =SUMIFS(DATA2026!E$2:E$401,DATA2026!A$2:A$401,"Q12026",DATA2026!G$2:G$401,"W->D")*0.5 -> 0 | C22: =SUMIFS(DATA2026!E$2:E$401,DATA2026!A$2:A$401,"Q22026",DATA2026!G$2:G$401,"W->D")*0.5 -> 0 | D22: =SUMIFS(DATA2026!E$2:E$401,DATA2026!A$2:A$401,"Q32026",DATA2026!G$2:G$401,"W->D")*0.5 -> 39 | E22: =SUMIFS(DATA2026!E$2:E$401,DATA2026!A$2:A$401,"Q42026",DATA2026!G$2:G$401,"W->D")*0.5 -> 0
A23: → D->W anteilig (h) | B23: =SUMIFS(DATA2026!E$2:E$401,DATA2026!A$2:A$401,"Q12026",DATA2026!G$2:G$401,"D->W")*0.5 -> 0 | C23: =SUMIFS(DATA2026!E$2:E$401,DATA2026!A$2:A$401,"Q22026",DATA2026!G$2:G$401,"D->W")*0.5 -> 0 | D23: =SUMIFS(DATA2026!E$2:E$401,DATA2026!A$2:A$401,"Q32026",DATA2026!G$2:G$401,"D->W")*0.5 -> 15 | E23: =SUMIFS(DATA2026!E$2:E$401,DATA2026!A$2:A$401,"Q42026",DATA2026!G$2:G$401,"D->W")*0.5 -> 0
A24: Effektiv Desktop (h) | B24: =B20+B22+B23 -> 0 | C24: =C20+C22+C23 -> 444 | D24: =D20+D22+D23 -> 543 | E24: =E20+E22+E23 -> 0
A25: Effektiv Web (h) | B25: =B21+B22+B23 -> 0 | C25: =C21+C22+C23 -> 216 | D25: =D21+D22+D23 -> 726 | E25: =E21+E22+E23 -> 0
A26: Auslastung Desktop % | B26: =IFERROR(B24/B17,"") | C26: =IFERROR(C24/C17,"") | D26: =IFERROR(D24/D17,"") -> 0.89309211 | E26: =IFERROR(E24/E17,"")
A27: Auslastung Web % | B27: =IFERROR(B26/B18,"") | C27: =IFERROR(C26/C18,"") | D27: =IFERROR(D25/D18,"") -> 1.0552326 | E27: =IFERROR(E26/E18,"")
A30: MoSCoW VERTEILUNG — pro Quartal
B31: Q1 | C31: Q2 | D31: Q3 | E31: Q4 | F31: Gesamt
A32: Must | B32: =COUNTIFS(DATA2026!A$2:A$401,"Q12026",DATA2026!F$2:F$401,"Must") -> 0 | C32: =COUNTIFS(DATA2026!A$2:A$401,"Q22026",DATA2026!F$2:F$401,"Must") -> 11 | D32: =COUNTIFS(DATA2026!A$2:A$401,"Q32026",DATA2026!F$2:F$401,"Must") -> 12 | E32: =COUNTIFS(DATA2026!A$2:A$401,"Q42026",DATA2026!F$2:F$401,"Must") -> 1 | F32: =COUNTIF(DATA2026!F$2:F$401,"Must") -> 24
A33: Should | B33: =COUNTIFS(DATA2026!A$2:A$401,"Q12026",DATA2026!F$2:F$401,"Should") -> 0 | C33: =COUNTIFS(DATA2026!A$2:A$401,"Q22026",DATA2026!F$2:F$401,"Should") -> 2 | D33: =COUNTIFS(DATA2026!A$2:A$401,"Q32026",DATA2026!F$2:F$401,"Should") -> 10 | E33: =COUNTIFS(DATA2026!A$2:A$401,"Q42026",DATA2026!F$2:F$401,"Should") -> 3 | F33: =COUNTIF(DATA2026!F$2:F$401,"Should") -> 15
A34: Could | B34: =COUNTIFS(DATA2026!A$2:A$401,"Q12026",DATA2026!F$2:F$401,"Could") -> 0 | C34: =COUNTIFS(DATA2026!A$2:A$401,"Q22026",DATA2026!F$2:F$401,"Could") -> 1 | D34: =COUNTIFS(DATA2026!A$2:A$401,"Q32026",DATA2026!F$2:F$401,"Could") -> 2 | E34: =COUNTIFS(DATA2026!A$2:A$401,"Q42026",DATA2026!F$2:F$401,"Could") -> 1 | F34: =COUNTIF(DATA2026!F$2:F$401,"Could") -> 4
A35: Won't | B35: =COUNTIFS(DATA2026!A$2:A$401,"Q12026",DATA2026!F$2:F$401,"Won't") -> 0 | C35: =COUNTIFS(DATA2026!A$2:A$401,"Q22026",DATA2026!F$2:F$401,"Won't") -> 0 | D35: =COUNTIFS(DATA2026!A$2:A$401,"Q32026",DATA2026!F$2:F$401,"Won't") -> 0 | E35: =COUNTIFS(DATA2026!A$2:A$401,"Q42026",DATA2026!F$2:F$401,"Won't") -> 0 | F35: =COUNTIF(DATA2026!F$2:F$401,"Won't") -> 0
A37: TEAM-ZUWEISUNG — Stunden pro Quartal
A38: Team | B38: Q1 | C38: Q2 | D38: Q3 | E38: Q4 | F38: Gesamt
A39: WEB | B39: =SUMIFS(DATA2026!E$2:E$401,DATA2026!A$2:A$401,"Q12026",DATA2026!G$2:G$401,"WEB") -> 0 | C39: =SUMIFS(DATA2026!E$2:E$401,DATA2026!A$2:A$401,"Q22026",DATA2026!G$2:G$401,"WEB") -> 216 | D39: =SUMIFS(DATA2026!E$2:E$401,DATA2026!A$2:A$401,"Q32026",DATA2026!G$2:G$401,"WEB") -> 672 | E39: =SUMIFS(DATA2026!E$2:E$401,DATA2026!A$2:A$401,"Q42026",DATA2026!G$2:G$401,"WEB") -> 0 | F39: =SUMIF(DATA2026!G$2:G$401,"WEB",DATA2026!E$2:E$401) -> 888
A40: Desktop | B40: =SUMIFS(DATA2026!E$2:E$401,DATA2026!A$2:A$401,"Q12026",DATA2026!G$2:G$401,"Desktop") -> 0 | C40: =SUMIFS(DATA2026!E$2:E$401,DATA2026!A$2:A$401,"Q22026",DATA2026!G$2:G$401,"Desktop") -> 444 | D40: =SUMIFS(DATA2026!E$2:E$401,DATA2026!A$2:A$401,"Q32026",DATA2026!G$2:G$401,"Desktop") -> 489 | E40: =SUMIFS(DATA2026!E$2:E$401,DATA2026!A$2:A$401,"Q42026",DATA2026!G$2:G$401,"Desktop") -> 0 | F40: =SUMIF(DATA2026!G$2:G$401,"Desktop",DATA2026!E$2:E$401) -> 933
A41: W->D | B41: =SUMIFS(DATA2026!E$2:E$401,DATA2026!A$2:A$401,"Q12026",DATA2026!G$2:G$401,"W->D") -> 0 | C41: =SUMIFS(DATA2026!E$2:E$401,DATA2026!A$2:A$401,"Q22026",DATA2026!G$2:G$401,"W->D") -> 0 | D41: =SUMIFS(DATA2026!E$2:E$401,DATA2026!A$2:A$401,"Q32026",DATA2026!G$2:G$401,"W->D") -> 78 | E41: =SUMIFS(DATA2026!E$2:E$401,DATA2026!A$2:A$401,"Q42026",DATA2026!G$2:G$401,"W->D") -> 0 | F41: =SUMIF(DATA2026!G$2:G$401,"W->D",DATA2026!E$2:E$401) -> 78
A42: D->W | B42: =SUMIFS(DATA2026!E$2:E$401,DATA2026!A$2:A$401,"Q12026",DATA2026!G$2:G$401,"D->W") -> 0 | C42: =SUMIFS(DATA2026!E$2:E$401,DATA2026!A$2:A$401,"Q22026",DATA2026!G$2:G$401,"D->W") -> 0 | D42: =SUMIFS(DATA2026!E$2:E$401,DATA2026!A$2:A$401,"Q32026",DATA2026!G$2:G$401,"D->W") -> 30 | E42: =SUMIFS(DATA2026!E$2:E$401,DATA2026!A$2:A$401,"Q42026",DATA2026!G$2:G$401,"D->W") -> 0 | F42: =SUMIF(DATA2026!G$2:G$401,"D->W",DATA2026!E$2:E$401) -> 30
A44: PO-BACKLOG — Einträge pro Quartal zugewiesen
B45: Q1 | C45: Q2 | D45: Q3 | E45: Q4 | F45: Gesamt
A46: Aus PO-Backlog | B46: =COUNTIFS(DATA2026!A$2:A$401,"Q12026",DATA2026!H$2:H$401,"PO-Backlog") -> 0 | C46: =COUNTIFS(DATA2026!A$2:A$401,"Q22026",DATA2026!H$2:H$401,"PO-Backlog") -> 0 | D46: =COUNTIFS(DATA2026!A$2:A$401,"Q32026",DATA2026!H$2:H$401,"PO-Backlog") -> 2 | E46: =COUNTIFS(DATA2026!A$2:A$401,"Q42026",DATA2026!H$2:H$401,"PO-Backlog") -> 2 | F46: =COUNTIF(DATA2026!H$2:H$401,"PO-Backlog") -> 4
A48: ℹ️ W->D und D->W werden je 50% auf Team Web und Team Desktop angerechnet | 🟡 Gelbe Einträge auf der Roadmap = aus PO-Backlog | Kapazitäten aus Roadmap-Blatt

Sheet Q12026
A1: Q12026
A2: # | B2: Projekttitel | C2: Größe | D2: Value-Bucket | E2: Quartal | F2: MoSCoW | G2: Team | H2: Std. | I2: Bemerkungen
A3: 1 | H3: =IF(C3="XXL (>160h)",168,IF(C3="XL (>40h)",48,IF(C3="L (20-40h)",30,IF(C3="M (10-20h)",15,IF(C3="S (<10h)",5,""))))) | J3: =IF($E3="Q12026",COUNTIF($E$3:$E3,"Q12026"),"") | K3: =IF($E3="Q22026",COUNTIF($E$3:$E3,"Q22026"),"") | L3: =IF($E3="Q32026",COUNTIF($E$3:$E3,"Q32026"),"") | M3: =IF($E3="Q42026",COUNTIF($E$3:$E3,"Q42026"),"") | N3: =IF($E3="Backlog",COUNTIF($E$3:$E3,"Backlog"),"")
A4: 2 | H4: =IF(C4="XXL (>160h)",168,IF(C4="XL (>40h)",48,IF(C4="L (20-40h)",30,IF(C4="M (10-20h)",15,IF(C4="S (<10h)",5,""))))) | J4: =IF($E4="Q12026",COUNTIF($E$3:$E4,"Q12026"),"") | K4: =IF($E4="Q22026",COUNTIF($E$3:$E4,"Q22026"),"") | L4: =IF($E4="Q32026",COUNTIF($E$3:$E4,"Q32026"),"") | M4: =IF($E4="Q42026",COUNTIF($E$3:$E4,"Q42026"),"") | N4: =IF($E4="Backlog",COUNTIF($E$3:$E4,"Backlog"),"")
A5: 3 | H5: =IF(C5="XXL (>160h)",168,IF(C5="XL (>40h)",48,IF(C5="L (20-40h)",30,IF(C5="M (10-20h)",15,IF(C5="S (<10h)",5,""))))) | J5: =IF($E5="Q12026",COUNTIF($E$3:$E5,"Q12026"),"") | K5: =IF($E5="Q22026",COUNTIF($E$3:$E5,"Q22026"),"") | L5: =IF($E5="Q32026",COUNTIF($E$3:$E5,"Q32026"),"") | M5: =IF($E5="Q42026",COUNTIF($E$3:$E5,"Q42026"),"") | N5: =IF($E5="Backlog",COUNTIF($E$3:$E5,"Backlog"),"")
A6: 4 | H6: =IF(C6="XXL (>160h)",168,IF(C6="XL (>40h)",48,IF(C6="L (20-40h)",30,IF(C6="M (10-20h)",15,IF(C6="S (<10h)",5,""))))) | J6: =IF($E6="Q12026",COUNTIF($E$3:$E6,"Q12026"),"") | K6: =IF($E6="Q22026",COUNTIF($E$3:$E6,"Q22026"),"") | L6: =IF($E6="Q32026",COUNTIF($E$3:$E6,"Q32026"),"") | M6: =IF($E6="Q42026",COUNTIF($E$3:$E6,"Q42026"),"") | N6: =IF($E6="Backlog",COUNTIF($E$3:$E6,"Backlog"),"")
A7: 5 | H7: =IF(C7="XXL (>160h)",168,IF(C7="XL (>40h)",48,IF(C7="L (20-40h)",30,IF(C7="M (10-20h)",15,IF(C7="S (<10h)",5,""))))) | J7: =IF($E7="Q12026",COUNTIF($E$3:$E7,"Q12026"),"") | K7: =IF($E7="Q22026",COUNTIF($E$3:$E7,"Q22026"),"") | L7: =IF($E7="Q32026",COUNTIF($E$3:$E7,"Q32026"),"") | M7: =IF($E7="Q42026",COUNTIF($E$3:$E7,"Q42026"),"") | N7: =IF($E7="Backlog",COUNTIF($E$3:$E7,"Backlog"),"")
A8: 6 | H8: =IF(C8="XXL (>160h)",168,IF(C8="XL (>40h)",48,IF(C8="L (20-40h)",30,IF(C8="M (10-20h)",15,IF(C8="S (<10h)",5,""))))) | J8: =IF($E8="Q12026",COUNTIF($E$3:$E8,"Q12026"),"") | K8: =IF($E8="Q22026",COUNTIF($E$3:$E8,"Q22026"),"") | L8: =IF($E8="Q32026",COUNTIF($E$3:$E8,"Q32026"),"") | M8: =IF($E8="Q42026",COUNTIF($E$3:$E8,"Q42026"),"") | N8: =IF($E8="Backlog",COUNTIF($E$3:$E8,"Backlog"),"")
A9: 7 | H9: =IF(C9="XXL (>160h)",168,IF(C9="XL (>40h)",48,IF(C9="L (20-40h)",30,IF(C9="M (10-20h)",15,IF(C9="S (<10h)",5,""))))) | J9: =IF($E9="Q12026",COUNTIF($E$3:$E9,"Q12026"),"") | K9: =IF($E9="Q22026",COUNTIF($E$3:$E9,"Q22026"),"") | L9: =IF($E9="Q32026",COUNTIF($E$3:$E9,"Q32026"),"") | M9: =IF($E9="Q42026",COUNTIF($E$3:$E9,"Q42026"),"") | N9: =IF($E9="Backlog",COUNTIF($E$3:$E9,"Backlog"),"")
A10: 8 | H10: =IF(C10="XXL (>160h)",168,IF(C10="XL (>40h)",48,IF(C10="L (20-40h)",30,IF(C10="M (10-20h)",15,IF(C10="S (<10h)",5,""))))) | J10: =IF($E10="Q12026",COUNTIF($E$3:$E10,"Q12026"),"") | K10: =IF($E10="Q22026",COUNTIF($E$3:$E10,"Q22026"),"") | L10: =IF($E10="Q32026",COUNTIF($E$3:$E10,"Q32026"),"") | M10: =IF($E10="Q42026",COUNTIF($E$3:$E10,"Q42026"),"") | N10: =IF($E10="Backlog",COUNTIF($E$3:$E10,"Backlog"),"")
A11: 9 | H11: =IF(C11="XXL (>160h)",168,IF(C11="XL (>40h)",48,IF(C11="L (20-40h)",30,IF(C11="M (10-20h)",15,IF(C11="S (<10h)",5,""))))) | J11: =IF($E11="Q12026",COUNTIF($E$3:$E11,"Q12026"),"") | K11: =IF($E11="Q22026",COUNTIF($E$3:$E11,"Q22026"),"") | L11: =IF($E11="Q32026",COUNTIF($E$3:$E11,"Q32026"),"") | M11: =IF($E11="Q42026",COUNTIF($E$3:$E11,"Q42026"),"") | N11: =IF($E11="Backlog",COUNTIF($E$3:$E11,"Backlog"),"")
A12: 10 | H12: =IF(C12="XXL (>160h)",168,IF(C12="XL (>40h)",48,IF(C12="L (20-40h)",30,IF(C12="M (10-20h)",15,IF(C12="S (<10h)",5,""))))) | J12: =IF($E12="Q12026",COUNTIF($E$3:$E12,"Q12026"),"") | K12: =IF($E12="Q22026",COUNTIF($E$3:$E12,"Q22026"),"") | L12: =IF($E12="Q32026",COUNTIF($E$3:$E12,"Q32026"),"") | M12: =IF($E12="Q42026",COUNTIF($E$3:$E12,"Q42026"),"") | N12: =IF($E12="Backlog",COUNTIF($E$3:$E12,"Backlog"),"")
A13: 11 | H13: =IF(C13="XXL (>160h)",168,IF(C13="XL (>40h)",48,IF(C13="L (20-40h)",30,IF(C13="M (10-20h)",15,IF(C13="S (<10h)",5,""))))) | J13: =IF($E13="Q12026",COUNTIF($E$3:$E13,"Q12026"),"") | K13: =IF($E13="Q22026",COUNTIF($E$3:$E13,"Q22026"),"") | L13: =IF($E13="Q32026",COUNTIF($E$3:$E13,"Q32026"),"") | M13: =IF($E13="Q42026",COUNTIF($E$3:$E13,"Q42026"),"") | N13: =IF($E13="Backlog",COUNTIF($E$3:$E13,"Backlog"),"")
A14: 12 | H14: =IF(C14="XXL (>160h)",168,IF(C14="XL (>40h)",48,IF(C14="L (20-40h)",30,IF(C14="M (10-20h)",15,IF(C14="S (<10h)",5,""))))) | J14: =IF($E14="Q12026",COUNTIF($E$3:$E14,"Q12026"),"") | K14: =IF($E14="Q22026",COUNTIF($E$3:$E14,"Q22026"),"") | L14: =IF($E14="Q32026",COUNTIF($E$3:$E14,"Q32026"),"") | M14: =IF($E14="Q42026",COUNTIF($E$3:$E14,"Q42026"),"") | N14: =IF($E14="Backlog",COUNTIF($E$3:$E14,"Backlog"),"")
... A82: 80 | H82: =IF(C82="XXL (>160h)",168,IF(C82="XL (>40h)",48,IF(C82="L (20-40h)",30,IF(C82="M (10-20h)",15,IF(C82="S (<10h)",5,""))))) | J82: =IF($E82="Q12026",COUNTIF($E$3:$E82,"Q12026"),"") | K82: =IF($E82="Q22026",COUNTIF($E$3:$E82,"Q22026"),"") | L82: =IF($E82="Q32026",COUNTIF($E$3:$E82,"Q32026"),"") | M82: =IF($E82="Q42026",COUNTIF($E$3:$E82,"Q42026"),"") | N82: =IF($E82="Backlog",COUNTIF($E$3:$E82,"Backlog"),"")
A83: ∑ Geschätzte Stunden gesamt | H83: =SUM(H3:H82) -> 0
A85: Value: 🟢 Strengthen = strategische Stärkung | 🔵 Innovation = neue Fähigkeiten | 🔴 Repair = Fehler/Schulden beheben
A86: MoSCoW: Must = Pflicht · Should = Soll · Could = Optional · Won't = Ausgeschlossen | Team: WEB · Desktop · W->D · D->W (anteilig je 50% auf beide Teams)
A87: Größen: S <10h · M 10–20h · L 20–40h · XL >40h · XXL >160h | Stunden = automatisch aus Größe | Kapazitäten (blaue Felder) = manuell

Sheet Q22026
A1: Q22026
A2: # | B2: Projekttitel | C2: Größe | D2: Value-Bucket | E2: Quartal | F2: MoSCoW | G2: Team | H2: Std. | I2: Bemerkungen
A3: 1 | B3: Apple iOS SDK Anforderungen | C3: XL (>40h) | D3: Repair | E3: Q22026 | F3: Must | G3: WEB | H3: =IF(C3="XXL (>160h)",168,IF(C3="XL (>40h)",48,IF(C3="L (20-40h)",30,IF(C3="M (10-20h)",15,IF(C3="S (<10h)",5,""))))) -> 48 | J3: =IF($E3="Q12026",COUNTIF($E$3:$E3,"Q12026"),"") | K3: =IF($E3="Q22026",COUNTIF($E$3:$E3,"Q22026"),"") -> 1 | L3: =IF($E3="Q32026",COUNTIF($E$3:$E3,"Q32026"),"") | M3: =IF($E3="Q42026",COUNTIF($E$3:$E3,"Q42026"),"") | N3: =IF($E3="Backlog",COUNTIF($E$3:$E3,"Backlog"),"")
A4: 2 | B4: mobilePeople.de - Vulnerabilitys Portal Live | C4: XL (>40h) | D4: Repair | E4: Q22026 | F4: Must | G4: WEB | H4: =IF(C4="XXL (>160h)",168,IF(C4="XL (>40h)",48,IF(C4="L (20-40h)",30,IF(C4="M (10-20h)",15,IF(C4="S (<10h)",5,""))))) -> 48 | J4: =IF($E4="Q12026",COUNTIF($E$3:$E4,"Q12026"),"") | K4: =IF($E4="Q22026",COUNTIF($E$3:$E4,"Q22026"),"") -> 2 | L4: =IF($E4="Q32026",COUNTIF($E$3:$E4,"Q32026"),"") | M4: =IF($E4="Q42026",COUNTIF($E$3:$E4,"Q42026"),"") | N4: =IF($E4="Backlog",COUNTIF($E$3:$E4,"Backlog"),"")
A5: 4 | B5: Webshop mit Newsletter Zustimmung | C5: M (10-20h) | D5: Strengthen | E5: Q22026 | F5: Should | G5: WEB | H5: =IF(C5="XXL (>160h)",168,IF(C5="XL (>40h)",48,IF(C5="L (20-40h)",30,IF(C5="M (10-20h)",15,IF(C5="S (<10h)",5,""))))) -> 15 | J5: =IF($E5="Q12026",COUNTIF($E$3:$E5,"Q12026"),"") | K5: =IF($E5="Q22026",COUNTIF($E$3:$E5,"Q22026"),"") -> 3 | L5: =IF($E5="Q32026",COUNTIF($E$3:$E5,"Q32026"),"") | M5: =IF($E5="Q42026",COUNTIF($E$3:$E5,"Q42026"),"") | N5: =IF($E5="Backlog",COUNTIF($E$3:$E5,"Backlog"),"")
A6: 5 | B6: Ticketshop mit Kalender & Anzahl | C6: M (10-20h) | D6: Strengthen | E6: Q22026 | F6: Must | G6: WEB | H6: =IF(C6="XXL (>160h)",168,IF(C6="XL (>40h)",48,IF(C6="L (20-40h)",30,IF(C6="M (10-20h)",15,IF(C6="S (<10h)",5,""))))) -> 15 | I6: Fertig bis Ende März -> Kunde hat schon Demo | J6: =IF($E6="Q12026",COUNTIF($E$3:$E6,"Q12026"),"") | K6: =IF($E6="Q22026",COUNTIF($E$3:$E6,"Q22026"),"") -> 4 | L6: =IF($E6="Q32026",COUNTIF($E$3:$E6,"Q32026"),"") | M6: =IF($E6="Q42026",COUNTIF($E$3:$E6,"Q42026"),"") | N6: =IF($E6="Backlog",COUNTIF($E$3:$E6,"Backlog"),"")
A7: 7 | B7: Optimierung SOT Sync | C7: L (20-40h) | D7: Repair | E7: Q22026 | F7: Must | G7: WEB | H7: =IF(C7="XXL (>160h)",168,IF(C7="XL (>40h)",48,IF(C7="L (20-40h)",30,IF(C7="M (10-20h)",15,IF(C7="S (<10h)",5,""))))) -> 30 | J7: =IF($E7="Q12026",COUNTIF($E$3:$E7,"Q12026"),"") | K7: =IF($E7="Q22026",COUNTIF($E$3:$E7,"Q22026"),"") -> 5 | L7: =IF($E7="Q32026",COUNTIF($E$3:$E7,"Q32026"),"") | M7: =IF($E7="Q42026",COUNTIF($E$3:$E7,"Q42026"),"") | N7: =IF($E7="Backlog",COUNTIF($E$3:$E7,"Backlog"),"")
A8: 8 | B8: TWINT / Konstantin / HILTL | C8: M (10-20h) | D8: Repair | F8: Must | G8: WEB | H8: =IF(C8="XXL (>160h)",168,IF(C8="XL (>40h)",48,IF(C8="L (20-40h)",30,IF(C8="M (10-20h)",15,IF(C8="S (<10h)",5,""))))) -> 15 | J8: =IF($E8="Q12026",COUNTIF($E$3:$E8,"Q12026"),"") | K8: =IF($E8="Q22026",COUNTIF($E$3:$E8,"Q22026"),"") | L8: =IF($E8="Q32026",COUNTIF($E$3:$E8,"Q32026"),"") | M8: =IF($E8="Q42026",COUNTIF($E$3:$E8,"Q42026"),"") | N8: =IF($E8="Backlog",COUNTIF($E$3:$E8,"Backlog"),"")
A9: 10 | B9: OpenTable API | C9: M (10-20h) | D9: Innovation | F9: Could | G9: WEB | H9: =IF(C9="XXL (>160h)",168,IF(C9="XL (>40h)",48,IF(C9="L (20-40h)",30,IF(C9="M (10-20h)",15,IF(C9="S (<10h)",5,""))))) -> 15 | I9: Fertig von HS! Abstimmung auf der Internorga -> liegt bei Erich & Co. | J9: =IF($E9="Q12026",COUNTIF($E$3:$E9,"Q12026"),"") | K9: =IF($E9="Q22026",COUNTIF($E$3:$E9,"Q22026"),"") | L9: =IF($E9="Q32026",COUNTIF($E$3:$E9,"Q32026"),"") | M9: =IF($E9="Q42026",COUNTIF($E$3:$E9,"Q42026"),"") | N9: =IF($E9="Backlog",COUNTIF($E$3:$E9,"Backlog"),"")
A10: 11 | B10: UHD | Incident Feedback an Kunde | C10: L (20-40h) | D10: Strengthen | F10: Must | G10: WEB | H10: =IF(C10="XXL (>160h)",168,IF(C10="XL (>40h)",48,IF(C10="L (20-40h)",30,IF(C10="M (10-20h)",15,IF(C10="S (<10h)",5,""))))) -> 30 | I10: Start der Ausarbeitung in Q2 -> Marco | J10: =IF($E10="Q12026",COUNTIF($E$3:$E10,"Q12026"),"") | K10: =IF($E10="Q22026",COUNTIF($E$3:$E10,"Q22026"),"") | L10: =IF($E10="Q32026",COUNTIF($E$3:$E10,"Q32026"),"") | M10: =IF($E10="Q42026",COUNTIF($E$3:$E10,"Q42026"),"") | N10: =IF($E10="Backlog",COUNTIF($E$3:$E10,"Backlog"),"")
A11: 12 | B11: UHD | AI Agent - Support | C11: L (20-40h) | D11: Strengthen | E11: Q22026 | F11: Must | G11: WEB | H11: =IF(C11="XXL (>160h)",168,IF(C11="XL (>40h)",48,IF(C11="L (20-40h)",30,IF(C11="M (10-20h)",15,IF(C11="S (<10h)",5,""))))) -> 30 | J11: =IF($E11="Q12026",COUNTIF($E$3:$E11,"Q12026"),"") | K11: =IF($E11="Q22026",COUNTIF($E$3:$E11,"Q22026"),"") -> 6 | L11: =IF($E11="Q32026",COUNTIF($E$3:$E11,"Q32026"),"") | M11: =IF($E11="Q42026",COUNTIF($E$3:$E11,"Q42026"),"") | N11: =IF($E11="Backlog",COUNTIF($E$3:$E11,"Backlog"),"")
A12: 14 | B12: HeyRosi -> API | C12: M (10-20h) | D12: Innovation | F12: Should | G12: WEB | H12: =IF(C12="XXL (>160h)",168,IF(C12="XL (>40h)",48,IF(C12="L (20-40h)",30,IF(C12="M (10-20h)",15,IF(C12="S (<10h)",5,""))))) -> 15 | I12: Reservierung fertig! Internorga | erst danach Planung für Bestellung -> Q3 | J12: =IF($E12="Q12026",COUNTIF($E$3:$E12,"Q12026"),"") | K12: =IF($E12="Q22026",COUNTIF($E$3:$E12,"Q22026"),"") | L12: =IF($E12="Q32026",COUNTIF($E$3:$E12,"Q32026"),"") | M12: =IF($E12="Q42026",COUNTIF($E$3:$E12,"Q42026"),"") | N12: =IF($E12="Backlog",COUNTIF($E$3:$E12,"Backlog"),"")
A13: 15 | B13: Landingpage zur Registrierung | C13: M (10-20h) | D13: Strengthen | F13: Must | G13: WEB | H13: =IF(C13="XXL (>160h)",168,IF(C13="XL (>40h)",48,IF(C13="L (20-40h)",30,IF(C13="M (10-20h)",15,IF(C13="S (<10h)",5,""))))) -> 15 | J13: =IF($E13="Q12026",COUNTIF($E$3:$E13,"Q12026"),"") | K13: =IF($E13="Q22026",COUNTIF($E$3:$E13,"Q22026"),"") | L13: =IF($E13="Q32026",COUNTIF($E$3:$E13,"Q32026"),"") | M13: =IF($E13="Q42026",COUNTIF($E$3:$E13,"Q42026"),"") | N13: =IF($E13="Backlog",COUNTIF($E$3:$E13,"Backlog"),"")
A14: 16 | B14: 3rd Party - Google Log In für APP | C14: M (10-20h) | D14: Repair | E14: Q22026 | F14: Must | G14: WEB | H14: =IF(C14="XXL (>160h)",168,IF(C14="XL (>40h)",48,IF(C14="L (20-40h)",30,IF(C14="M (10-20h)",15,IF(C14="S (<10h)",5,""))))) -> 15 | J14: =IF($E14="Q12026",COUNTIF($E$3:$E14,"Q12026"),"") | K14: =IF($E14="Q22026",COUNTIF($E$3:$E14,"Q22026"),"") -> 7 | L14: =IF($E14="Q32026",COUNTIF($E$3:$E14,"Q32026"),"") | M14: =IF($E14="Q42026",COUNTIF($E$3:$E14,"Q42026"),"") | N14: =IF($E14="Backlog",COUNTIF($E$3:$E14,"Backlog"),"")
A15: 17 | B15: SIG#156 Landingpage -> Bonuspunkte anzeigen | C15: M (10-20h) | D15: Strengthen | E15: Q22026 | F15: Must | G15: WEB | H15: =IF(C15="XXL (>160h)",168,IF(C15="XL (>40h)",48,IF(C15="L (20-40h)",30,IF(C15="M (10-20h)",15,IF(C15="S (<10h)",5,""))))) -> 15 | J15: =IF($E15="Q12026",COUNTIF($E$3:$E15,"Q12026"),"") | K15: =IF($E15="Q22026",COUNTIF($E$3:$E15,"Q22026"),"") -> 8 | L15: =IF($E15="Q32026",COUNTIF($E$3:$E15,"Q32026"),"") | M15: =IF($E15="Q42026",COUNTIF($E$3:$E15,"Q42026"),"") | N15: =IF($E15="Backlog",COUNTIF($E$3:$E15,"Backlog"),"")
A16: 19 | B16: UI / Code - Portalmodernisierung | Benutzer | C16: XXL (>160h) | D16: Strengthen | F16: Should | G16: WEB | H16: =IF(C16="XXL (>160h)",168,IF(C16="XL (>40h)",48,IF(C16="L (20-40h)",30,IF(C16="M (10-20h)",15,IF(C16="S (<10h)",5,""))))) -> 168 | J16: =IF($E16="Q12026",COUNTIF($E$3:$E16,"Q12026"),"") | K16: =IF($E16="Q22026",COUNTIF($E$3:$E16,"Q22026"),"") | L16: =IF($E16="Q32026",COUNTIF($E$3:$E16,"Q32026"),"") | M16: =IF($E16="Q42026",COUNTIF($E$3:$E16,"Q42026"),"") | N16: =IF($E16="Backlog",COUNTIF($E$3:$E16,"Backlog"),"")
A17: 3 | B17: iCoupon | C17: M (10-20h) | D17: Strengthen | E17: Q22026 | F17: Should | G17: Desktop | H17: =IF(C17="XXL (>160h)",168,IF(C17="XL (>40h)",48,IF(C17="L (20-40h)",30,IF(C17="M (10-20h)",15,IF(C17="S (<10h)",5,""))))) -> 15 | I17: Alex muss finalisieren (2-3 Stunden) dann zu Peter und/oder Farhad - mehrere Tage! Rabatte noch "unklar" und muss gff. nachgeliefert werden. | J17: =IF($E17="Q12026",COUNTIF($E$3:$E17,"Q12026"),"") | K17: =IF($E17="Q22026",COUNTIF($E$3:$E17,"Q22026"),"") -> 9 | L17: =IF($E17="Q32026",COUNTIF($E$3:$E17,"Q32026"),"") | M17: =IF($E17="Q42026",COUNTIF($E$3:$E17,"Q42026"),"") | N17: =IF($E17="Backlog",COUNTIF($E$3:$E17,"Backlog"),"")
A18: 6 | B18: Supportreduzierung: / Kontingent definieren | C18: XXL (>160h) | D18: Repair | E18: Q22026 | F18: Must | G18: Desktop | H18: =IF(C18="XXL (>160h)",168,IF(C18="XL (>40h)",48,IF(C18="L (20-40h)",30,IF(C18="M (10-20h)",15,IF(C18="S (<10h)",5,""))))) -> 168 | J18: =IF($E18="Q12026",COUNTIF($E$3:$E18,"Q12026"),"") | K18: =IF($E18="Q22026",COUNTIF($E$3:$E18,"Q22026"),"") -> 10 | L18: =IF($E18="Q32026",COUNTIF($E$3:$E18,"Q32026"),"") | M18: =IF($E18="Q42026",COUNTIF($E$3:$E18,"Q42026"),"") | N18: =IF($E18="Backlog",COUNTIF($E$3:$E18,"Backlog"),"")
A19: 9 | B19: Actian Umstellung | C19: XXL (>160h) | D19: Repair | E19: Q22026 | F19: Must | G19: Desktop | H19: =IF(C19="XXL (>160h)",168,IF(C19="XL (>40h)",48,IF(C19="L (20-40h)",30,IF(C19="M (10-20h)",15,IF(C19="S (<10h)",5,""))))) -> 168 | J19: =IF($E19="Q12026",COUNTIF($E$3:$E19,"Q12026"),"") | K19: =IF($E19="Q22026",COUNTIF($E$3:$E19,"Q22026"),"") -> 11 | L19: =IF($E19="Q32026",COUNTIF($E$3:$E19,"Q32026"),"") | M19: =IF($E19="Q42026",COUNTIF($E$3:$E19,"Q42026"),"") | N19: =IF($E19="Backlog",COUNTIF($E$3:$E19,"Backlog"),"")
A20: 13 | B20: ePOS mobile PRO V1 | C20: XL (>40h) | D20: Innovation | E20: Q22026 | F20: Must | G20: Desktop | H20: =IF(C20="XXL (>160h)",168,IF(C20="XL (>40h)",48,IF(C20="L (20-40h)",30,IF(C20="M (10-20h)",15,IF(C20="S (<10h)",5,""))))) -> 48 | J20: =IF($E20="Q12026",COUNTIF($E$3:$E20,"Q12026"),"") | K20: =IF($E20="Q22026",COUNTIF($E$3:$E20,"Q22026"),"") -> 12 | L20: =IF($E20="Q32026",COUNTIF($E$3:$E20,"Q32026"),"") | M20: =IF($E20="Q42026",COUNTIF($E$3:$E20,"Q42026"),"") | N20: =IF($E20="Backlog",COUNTIF($E$3:$E20,"Backlog"),"")
A21: 18 | B21: Artikel-Tabellenbearbeitung auch Bilder (Shop) hinzufügen | C21: M (10-20h) | D21: Strengthen | E21: Q22026 | F21: Could | G21: Desktop | H21: =IF(C21="XXL (>160h)",168,IF(C21="XL (>40h)",48,IF(C21="L (20-40h)",30,IF(C21="M (10-20h)",15,IF(C21="S (<10h)",5,""))))) -> 15 | I21: FRED? | J21: =IF($E21="Q12026",COUNTIF($E$3:$E21,"Q12026"),"") | K21: =IF($E21="Q22026",COUNTIF($E$3:$E21,"Q22026"),"") -> 13 | L21: =IF($E21="Q32026",COUNTIF($E$3:$E21,"Q32026"),"") | M21: =IF($E21="Q42026",COUNTIF($E$3:$E21,"Q42026"),"") | N21: =IF($E21="Backlog",COUNTIF($E$3:$E21,"Backlog"),"")
A22: 20 | B22: DSFinV-K: Verknüpfung von Bestellsignaturen | C22: L (20-40h) | D22: Strengthen | E22: Q22026 | F22: Must | G22: Desktop | H22: =IF(C22="XXL (>160h)",168,IF(C22="XL (>40h)",48,IF(C22="L (20-40h)",30,IF(C22="M (10-20h)",15,IF(C22="S (<10h)",5,""))))) -> 30 | I22: FRED Die Bestellsignaturen werden beim Export noch nicht über die zwischenzeitlich eingefügte TraceID pro Buchung miteinander verknüpft, da dieses System noch nicht komplett ist. Die Signaturen werden wie bisher über Datum/Uhrzeit/Artikelname verknüpft. | J22: =IF($E22="Q12026",COUNTIF($E$3:$E22,"Q12026"),"") | K22: =IF($E22="Q22026",COUNTIF($E$3:$E22,"Q22026"),"") -> 14 | L22: =IF($E22="Q32026",COUNTIF($E$3:$E22,"Q32026"),"") | M22: =IF($E22="Q42026",COUNTIF($E$3:$E22,"Q42026"),"") | N22: =IF($E22="Backlog",COUNTIF($E$3:$E22,"Backlog"),"")
A23: 21 | H23: =IF(C23="XXL (>160h)",168,IF(C23="XL (>40h)",48,IF(C23="L (20-40h)",30,IF(C23="M (10-20h)",15,IF(C23="S (<10h)",5,""))))) | J23: =IF($E23="Q12026",COUNTIF($E$3:$E23,"Q12026"),"") | K23: =IF($E23="Q22026",COUNTIF($E$3:$E23,"Q22026"),"") | L23: =IF($E23="Q32026",COUNTIF($E$3:$E23,"Q32026"),"") | M23: =IF($E23="Q42026",COUNTIF($E$3:$E23,"Q42026"),"") | N23: =IF($E23="Backlog",COUNTIF($E$3:$E23,"Backlog"),"")
A24: 22 | H24: =IF(C24="XXL (>160h)",168,IF(C24="XL (>40h)",48,IF(C24="L (20-40h)",30,IF(C24="M (10-20h)",15,IF(C24="S (<10h)",5,""))))) | J24: =IF($E24="Q12026",COUNTIF($E$3:$E24,"Q12026"),"") | K24: =IF($E24="Q22026",COUNTIF($E$3:$E24,"Q22026"),"") | L24: =IF($E24="Q32026",COUNTIF($E$3:$E24,"Q32026"),"") | M24: =IF($E24="Q42026",COUNTIF($E$3:$E24,"Q42026"),"") | N24: =IF($E24="Backlog",COUNTIF($E$3:$E24,"Backlog"),"")
A25: 23 | H25: =IF(C25="XXL (>160h)",168,IF(C25="XL (>40h)",48,IF(C25="L (20-40h)",30,IF(C25="M (10-20h)",15,IF(C25="S (<10h)",5,""))))) | J25: =IF($E25="Q12026",COUNTIF($E$3:$E25,"Q12026"),"") | K25: =IF($E25="Q22026",COUNTIF($E$3:$E25,"Q22026"),"") | L25: =IF($E25="Q32026",COUNTIF($E$3:$E25,"Q32026"),"") | M25: =IF($E25="Q42026",COUNTIF($E$3:$E25,"Q42026"),"") | N25: =IF($E25="Backlog",COUNTIF($E$3:$E25,"Backlog"),"")
A26: 24 | H26: =IF(C26="XXL (>160h)",168,IF(C26="XL (>40h)",48,IF(C26="L (20-40h)",30,IF(C26="M (10-20h)",15,IF(C26="S (<10h)",5,""))))) | J26: =IF($E26="Q12026",COUNTIF($E$3:$E26,"Q12026"),"") | K26: =IF($E26="Q22026",COUNTIF($E$3:$E26,"Q22026"),"") | L26: =IF($E26="Q32026",COUNTIF($E$3:$E26,"Q32026"),"") | M26: =IF($E26="Q42026",COUNTIF($E$3:$E26,"Q42026"),"") | N26: =IF($E26="Backlog",COUNTIF($E$3:$E26,"Backlog"),"")
A27: 25 | H27: =IF(C27="XXL (>160h)",168,IF(C27="XL (>40h)",48,IF(C27="L (20-40h)",30,IF(C27="M (10-20h)",15,IF(C27="S (<10h)",5,""))))) | J27: =IF($E27="Q12026",COUNTIF($E$3:$E27,"Q12026"),"") | K27: =IF($E27="Q22026",COUNTIF($E$3:$E27,"Q22026"),"") | L27: =IF($E27="Q32026",COUNTIF($E$3:$E27,"Q32026"),"") | M27: =IF($E27="Q42026",COUNTIF($E$3:$E27,"Q42026"),"") | N27: =IF($E27="Backlog",COUNTIF($E$3:$E27,"Backlog"),"")
A28: 26 | H28: =IF(C28="XXL (>160h)",168,IF(C28="XL (>40h)",48,IF(C28="L (20-40h)",30,IF(C28="M (10-20h)",15,IF(C28="S (<10h)",5,""))))) | J28: =IF($E28="Q12026",COUNTIF($E$3:$E28,"Q12026"),"") | K28: =IF($E28="Q22026",COUNTIF($E$3:$E28,"Q22026"),"") | L28: =IF($E28="Q32026",COUNTIF($E$3:$E28,"Q32026"),"") | M28: =IF($E28="Q42026",COUNTIF($E$3:$E28,"Q42026"),"") | N28: =IF($E28="Backlog",COUNTIF($E$3:$E28,"Backlog"),"")
A29: 27 | H29: =IF(C29="XXL (>160h)",168,IF(C29="XL (>40h)",48,IF(C29="L (20-40h)",30,IF(C29="M (10-20h)",15,IF(C29="S (<10h)",5,""))))) | J29: =IF($E29="Q12026",COUNTIF($E$3:$E29,"Q12026"),"") | K29: =IF($E29="Q22026",COUNTIF($E$3:$E29,"Q22026"),"") | L29: =IF($E29="Q32026",COUNTIF($E$3:$E29,"Q32026"),"") | M29: =IF($E29="Q42026",COUNTIF($E$3:$E29,"Q42026"),"") | N29: =IF($E29="Backlog",COUNTIF($E$3:$E29,"Backlog"),"")
A30: 28 | H30: =IF(C30="XXL (>160h)",168,IF(C30="XL (>40h)",48,IF(C30="L (20-40h)",30,IF(C30="M (10-20h)",15,IF(C30="S (<10h)",5,""))))) | J30: =IF($E30="Q12026",COUNTIF($E$3:$E30,"Q12026"),"") | K30: =IF($E30="Q22026",COUNTIF($E$3:$E30,"Q22026"),"") | L30: =IF($E30="Q32026",COUNTIF($E$3:$E30,"Q32026"),"") | M30: =IF($E30="Q42026",COUNTIF($E$3:$E30,"Q42026"),"") | N30: =IF($E30="Backlog",COUNTIF($E$3:$E30,"Backlog"),"")
A31: 29 | H31: =IF(C31="XXL (>160h)",168,IF(C31="XL (>40h)",48,IF(C31="L (20-40h)",30,IF(C31="M (10-20h)",15,IF(C31="S (<10h)",5,""))))) | J31: =IF($E31="Q12026",COUNTIF($E$3:$E31,"Q12026"),"") | K31: =IF($E31="Q22026",COUNTIF($E$3:$E31,"Q22026"),"") | L31: =IF($E31="Q32026",COUNTIF($E$3:$E31,"Q32026"),"") | M31: =IF($E31="Q42026",COUNTIF($E$3:$E31,"Q42026"),"") | N31: =IF($E31="Backlog",COUNTIF($E$3:$E31,"Backlog"),"")
A32: 30 | H32: =IF(C32="XXL (>160h)",168,IF(C32="XL (>40h)",48,IF(C32="L (20-40h)",30,IF(C32="M (10-20h)",15,IF(C32="S (<10h)",5,""))))) | J32: =IF($E32="Q12026",COUNTIF($E$3:$E32,"Q12026"),"") | K32: =IF($E32="Q22026",COUNTIF($E$3:$E32,"Q22026"),"") | L32: =IF($E32="Q32026",COUNTIF($E$3:$E32,"Q32026"),"") | M32: =IF($E32="Q42026",COUNTIF($E$3:$E32,"Q42026"),"") | N32: =IF($E32="Backlog",COUNTIF($E$3:$E32,"Backlog"),"")
A33: 31 | H33: =IF(C33="XXL (>160h)",168,IF(C33="XL (>40h)",48,IF(C33="L (20-40h)",30,IF(C33="M (10-20h)",15,IF(C33="S (<10h)",5,""))))) | J33: =IF($E33="Q12026",COUNTIF($E$3:$E33,"Q12026"),"") | K33: =IF($E33="Q22026",COUNTIF($E$3:$E33,"Q22026"),"") | L33: =IF($E33="Q32026",COUNTIF($E$3:$E33,"Q32026"),"") | M33: =IF($E33="Q42026",COUNTIF($E$3:$E33,"Q42026"),"") | N33: =IF($E33="Backlog",COUNTIF($E$3:$E33,"Backlog"),"")
A34: 32 | H34: =IF(C34="XXL (>160h)",168,IF(C34="XL (>40h)",48,IF(C34="L (20-40h)",30,IF(C34="M (10-20h)",15,IF(C34="S (<10h)",5,""))))) | J34: =IF($E34="Q12026",COUNTIF($E$3:$E34,"Q12026"),"") | K34: =IF($E34="Q22026",COUNTIF($E$3:$E34,"Q22026"),"") | L34: =IF($E34="Q32026",COUNTIF($E$3:$E34,"Q32026"),"") | M34: =IF($E34="Q42026",COUNTIF($E$3:$E34,"Q42026"),"") | N34: =IF($E34="Backlog",COUNTIF($E$3:$E34,"Backlog"),"")
... A82: 80 | H82: =IF(C82="XXL (>160h)",168,IF(C82="XL (>40h)",48,IF(C82="L (20-40h)",30,IF(C82="M (10-20h)",15,IF(C82="S (<10h)",5,""))))) | J82: =IF($E82="Q12026",COUNTIF($E$3:$E82,"Q12026"),"") | K82: =IF($E82="Q22026",COUNTIF($E$3:$E82,"Q22026"),"") | L82: =IF($E82="Q32026",COUNTIF($E$3:$E82,"Q32026"),"") | M82: =IF($E82="Q42026",COUNTIF($E$3:$E82,"Q42026"),"") | N82: =IF($E82="Backlog",COUNTIF($E$3:$E82,"Backlog"),"")
A83: ∑ Geschätzte Stunden gesamt | H83: =SUM(H3:H82) -> 918
A85: Value: 🟢 Strengthen = strategische Stärkung | 🔵 Innovation = neue Fähigkeiten | 🔴 Repair = Fehler/Schulden beheben
A86: MoSCoW: Must = Pflicht · Should = Soll · Could = Optional · Won't = Ausgeschlossen | Team: WEB · Desktop · W->D · D->W (anteilig je 50% auf beide Teams)
A87: Größen: S <10h · M 10–20h · L 20–40h · XL >40h · XXL >160h | Stunden = automatisch aus Größe | Kapazitäten (blaue Felder) = manuell

Sheet Q32026
A1: Q32026
A2: # | B2: Projekttitel | C2: Größe | D2: Value-Bucket | E2: Quartal | F2: MoSCoW | G2: Team | H2: Std. | I2: Bemerkungen
A3: 7 | B3: GitHub - Umstellung | C3: L (20-40h) | D3: Strengthen | E3: Q32026 | F3: Must | G3: D->W | H3: =IF(C3="XXL (>160h)",168,IF(C3="XL (>40h)",48,IF(C3="L (20-40h)",30,IF(C3="M (10-20h)",15,IF(C3="S (<10h)",5,""))))) -> 30 | I3: Start nach Campaigns in Q2 ? Hypertron -> Maik S. | J3: =IF($E3="Q12026",COUNTIF($E$3:$E3,"Q12026"),"") | K3: =IF($E3="Q22026",COUNTIF($E$3:$E3,"Q22026"),"") | L3: =IF($E3="Q32026",COUNTIF($E$3:$E3,"Q32026"),"") -> 1 | M3: =IF($E3="Q42026",COUNTIF($E$3:$E3,"Q42026"),"") | N3: =IF($E3="Backlog",COUNTIF($E$3:$E3,"Backlog"),"")
A4: 11 | B4: EFSTA - Anbindung (Spanien) | C4: L (20-40h) | D4: Strengthen | E4: Q32026 | F4: Should | G4: Desktop | H4: =IF(C4="XXL (>160h)",168,IF(C4="XL (>40h)",48,IF(C4="L (20-40h)",30,IF(C4="M (10-20h)",15,IF(C4="S (<10h)",5,""))))) -> 30 | J4: =IF($E4="Q12026",COUNTIF($E$3:$E4,"Q12026"),"") | K4: =IF($E4="Q22026",COUNTIF($E$3:$E4,"Q22026"),"") | L4: =IF($E4="Q32026",COUNTIF($E$3:$E4,"Q32026"),"") -> 2 | M4: =IF($E4="Q42026",COUNTIF($E$3:$E4,"Q42026"),"") | N4: =IF($E4="Backlog",COUNTIF($E$3:$E4,"Backlog"),"")
A5: 12 | B5: DSFinV-K | Startdatum der ersten Buchung | C5: M (10-20h) | D5: Repair | E5: Q32026 | F5: Must | G5: Desktop | H5: =IF(C5="XXL (>160h)",168,IF(C5="XL (>40h)",48,IF(C5="L (20-40h)",30,IF(C5="M (10-20h)",15,IF(C5="S (<10h)",5,""))))) -> 15 | I5: Erst Peter -> Fred | J5: =IF($E5="Q12026",COUNTIF($E$3:$E5,"Q12026"),"") | K5: =IF($E5="Q22026",COUNTIF($E$3:$E5,"Q22026"),"") | L5: =IF($E5="Q32026",COUNTIF($E$3:$E5,"Q32026"),"") -> 3 | M5: =IF($E5="Q42026",COUNTIF($E$3:$E5,"Q42026"),"") | N5: =IF($E5="Backlog",COUNTIF($E$3:$E5,"Backlog"),"")
A6: 13 | B6: Webhook Deliverect | C6: L (20-40h) | D6: Strengthen | E6: Q32026 | F6: Should | G6: Desktop | H6: =IF(C6="XXL (>160h)",168,IF(C6="XL (>40h)",48,IF(C6="L (20-40h)",30,IF(C6="M (10-20h)",15,IF(C6="S (<10h)",5,""))))) -> 30 | I6: ist bereits zu 90% fertig -> abschließen | J6: =IF($E6="Q12026",COUNTIF($E$3:$E6,"Q12026"),"") | K6: =IF($E6="Q22026",COUNTIF($E$3:$E6,"Q22026"),"") | L6: =IF($E6="Q32026",COUNTIF($E$3:$E6,"Q32026"),"") -> 4 | M6: =IF($E6="Q42026",COUNTIF($E$3:$E6,"Q42026"),"") | N6: =IF($E6="Backlog",COUNTIF($E$3:$E6,"Backlog"),"")
A7: 14 | B7: MwSt. Verteilung | C7: XXL (>160h) | D7: Strengthen | E7: Q32026 | F7: Must | G7: Desktop | H7: =IF(C7="XXL (>160h)",168,IF(C7="XL (>40h)",48,IF(C7="L (20-40h)",30,IF(C7="M (10-20h)",15,IF(C7="S (<10h)",5,""))))) -> 168 | J7: =IF($E7="Q12026",COUNTIF($E$3:$E7,"Q12026"),"") | K7: =IF($E7="Q22026",COUNTIF($E$3:$E7,"Q22026"),"") | L7: =IF($E7="Q32026",COUNTIF($E$3:$E7,"Q32026"),"") -> 5 | M7: =IF($E7="Q42026",COUNTIF($E$3:$E7,"Q42026"),"") | N7: =IF($E7="Backlog",COUNTIF($E$3:$E7,"Backlog"),"")
A8: 15 | B8: ePOS mobilePRO | C8: XXL (>160h) | D8: Strengthen | E8: Q32026 | F8: Must | G8: Desktop | H8: =IF(C8="XXL (>160h)",168,IF(C8="XL (>40h)",48,IF(C8="L (20-40h)",30,IF(C8="M (10-20h)",15,IF(C8="S (<10h)",5,""))))) -> 168 | J8: =IF($E8="Q12026",COUNTIF($E$3:$E11,"Q12026"),"") | K8: =IF($E8="Q22026",COUNTIF($E$3:$E11,"Q22026"),"") | L8: =IF($E8="Q32026",COUNTIF($E$3:$E11,"Q32026"),"") -> 8 | M8: =IF($E8="Q42026",COUNTIF($E$3:$E11,"Q42026"),"") | N8: =IF($E8="Backlog",COUNTIF($E$3:$E11,"Backlog"),"")
A9: 16 | B9: Protokollierung bei Lizenzzuweisungen. (Internal Audit) | C9: XL (>40h) | D9: Repair | E9: Q32026 | F9: Must | G9: Desktop | H9: =IF(C9="XXL (>160h)",168,IF(C9="XL (>40h)",48,IF(C9="L (20-40h)",30,IF(C9="M (10-20h)",15,IF(C9="S (<10h)",5,""))))) -> 48 | J9: =IF($E9="Q12026",COUNTIF($E$3:$E9,"Q12026"),"") | K9: =IF($E9="Q22026",COUNTIF($E$3:$E9,"Q22026"),"") | L9: =IF($E9="Q32026",COUNTIF($E$3:$E9,"Q32026"),"") -> 7 | M9: =IF($E9="Q42026",COUNTIF($E$3:$E9,"Q42026"),"") | N9: =IF($E9="Backlog",COUNTIF($E$3:$E9,"Backlog"),"")
A10: 17 | B10: Trinkgeldentnahme signieren (ALEX-GRUPPE) | C10: L (20-40h) | D10: Strengthen | E10: Q32026 | F10: Must | G10: Desktop | H10: =IF(C10="XXL (>160h)",168,IF(C10="XL (>40h)",48,IF(C10="L (20-40h)",30,IF(C10="M (10-20h)",15,IF(C10="S (<10h)",5,""))))) -> 30 | I10: Erst Fred und dann an Peter | J10: =IF($E10="Q12026",COUNTIF($E$3:$E10,"Q12026"),"") | K10: =IF($E10="Q22026",COUNTIF($E$3:$E10,"Q22026"),"") | L10: =IF($E10="Q32026",COUNTIF($E$3:$E10,"Q32026"),"") -> 8 | M10: =IF($E10="Q42026",COUNTIF($E$3:$E10,"Q42026"),"") | N10: =IF($E10="Backlog",COUNTIF($E$3:$E10,"Backlog"),"")
A11: 18 | B11: PLANUNG & UMSETZUNG | ZOTT - neue Chipkarten | C11: XL (>40h) | D11: Strengthen | F11: Must | G11: Desktop | H11: =IF(C11="XXL (>160h)",168,IF(C11="XL (>40h)",48,IF(C11="L (20-40h)",30,IF(C11="M (10-20h)",15,IF(C11="S (<10h)",5,""))))) -> 48 | J11: =IF($E11="Q12026",COUNTIF($E$3:$E11,"Q12026"),"") | K11: =IF($E11="Q22026",COUNTIF($E$3:$E11,"Q22026"),"") | L11: =IF($E11="Q32026",COUNTIF($E$3:$E11,"Q32026"),"") | M11: =IF($E11="Q42026",COUNTIF($E$3:$E11,"Q42026"),"") | N11: =IF($E11="Backlog",COUNTIF($E$3:$E11,"Backlog"),"")
A12: 19 | B12: DATEV | Lodas - Cloud MIgration ??? | D12: Strengthen | F12: Should | G12: Desktop | H12: =IF(C12="XXL (>160h)",168,IF(C12="XL (>40h)",48,IF(C12="L (20-40h)",30,IF(C12="M (10-20h)",15,IF(C12="S (<10h)",5,""))))) | I12: ALEX & AI | Report Manager <> Peter | J12: =IF($E12="Q12026",COUNTIF($E$3:$E12,"Q12026"),"") | K12: =IF($E12="Q22026",COUNTIF($E$3:$E12,"Q22026"),"") | L12: =IF($E12="Q32026",COUNTIF($E$3:$E12,"Q32026"),"") | M12: =IF($E12="Q42026",COUNTIF($E$3:$E12,"Q42026"),"") | N12: =IF($E12="Backlog",COUNTIF($E$3:$E12,"Backlog"),"")
A13: 9 | B13: SOT/Webshop & POS | Grundlage / Basis der Kundenkarte QR-Code zur Identifikation | C13: XL (>40h) | D13: Innovation | E13: Q32026 | F13: Must | G13: W->D | H13: =IF(C13="XXL (>160h)",168,IF(C13="XL (>40h)",48,IF(C13="L (20-40h)",30,IF(C13="M (10-20h)",15,IF(C13="S (<10h)",5,""))))) -> 48 | I13: Fahrplan von Sebastian (kurz) fehlt / Alternativ mit Niklas (oder anderem Domainenexperten) -> Ausarbeitung via MO | J13: =IF($E13="Q12026",COUNTIF($E$3:$E13,"Q12026"),"") | K13: =IF($E13="Q22026",COUNTIF($E$3:$E13,"Q22026"),"") | L13: =IF($E13="Q32026",COUNTIF($E$3:$E13,"Q32026"),"") -> 9 | M13: =IF($E13="Q42026",COUNTIF($E$3:$E13,"Q42026"),"") | N13: =IF($E13="Backlog",COUNTIF($E$3:$E13,"Backlog"),"")
A14: 8 | B14: Benefits am SOT einlösen | C14: L (20-40h) | D14: Strengthen | E14: Q32026 | F14: Should | G14: W->D | H14: =IF(C14="XXL (>160h)",168,IF(C14="XL (>40h)",48,IF(C14="L (20-40h)",30,IF(C14="M (10-20h)",15,IF(C14="S (<10h)",5,""))))) -> 30 | J14: =IF($E14="Q12026",COUNTIF($E$3:$E14,"Q12026"),"") | K14: =IF($E14="Q22026",COUNTIF($E$3:$E14,"Q22026"),"") | L14: =IF($E14="Q32026",COUNTIF($E$3:$E14,"Q32026"),"") -> 10 | M14: =IF($E14="Q42026",COUNTIF($E$3:$E14,"Q42026"),"") | N14: =IF($E14="Backlog",COUNTIF($E$3:$E14,"Backlog"),"")
A15: 1 | B15: UHD | Rechnungsstellung in CHF | C15: L (20-40h) | D15: Strengthen | E15: Q32026 | F15: Should | G15: WEB | H15: =IF(C15="XXL (>160h)",168,IF(C15="XL (>40h)",48,IF(C15="L (20-40h)",30,IF(C15="M (10-20h)",15,IF(C15="S (<10h)",5,""))))) -> 30 | I15: 3 Tage Frank 3 Tage Konstantin | J15: =IF($E15="Q12026",COUNTIF($E$3:$E15,"Q12026"),"") | K15: =IF($E15="Q22026",COUNTIF($E$3:$E15,"Q22026"),"") | L15: =IF($E15="Q32026",COUNTIF($E$3:$E15,"Q32026"),"") -> 11 | M15: =IF($E15="Q42026",COUNTIF($E$3:$E15,"Q42026"),"") | N15: =IF($E15="Backlog",COUNTIF($E$3:$E15,"Backlog"),"")
A16: 2 | B16: UHD | Filtermöglichkeit für „Priorisierung“ | C16: L (20-40h) | D16: Strengthen | E16: Q32026 | F16: Should | G16: WEB | H16: =IF(C16="XXL (>160h)",168,IF(C16="XL (>40h)",48,IF(C16="L (20-40h)",30,IF(C16="M (10-20h)",15,IF(C16="S (<10h)",5,""))))) -> 30 | J16: =IF($E16="Q12026",COUNTIF($E$3:$E16,"Q12026"),"") | K16: =IF($E16="Q22026",COUNTIF($E$3:$E16,"Q22026"),"") | L16: =IF($E16="Q32026",COUNTIF($E$3:$E16,"Q32026"),"") -> 12 | M16: =IF($E16="Q42026",COUNTIF($E$3:$E16,"Q42026"),"") | N16: =IF($E16="Backlog",COUNTIF($E$3:$E16,"Backlog"),"")
A17: 3 | B17: UHD | Bearbeiter ergänzen / anzeigen | C17: L (20-40h) | D17: Strengthen | E17: Q32026 | F17: Should | G17: WEB | H17: =IF(C17="XXL (>160h)",168,IF(C17="XL (>40h)",48,IF(C17="L (20-40h)",30,IF(C17="M (10-20h)",15,IF(C17="S (<10h)",5,""))))) -> 30 | J17: =IF($E17="Q12026",COUNTIF($E$3:$E17,"Q12026"),"") | K17: =IF($E17="Q22026",COUNTIF($E$3:$E17,"Q22026"),"") | L17: =IF($E17="Q32026",COUNTIF($E$3:$E17,"Q32026"),"") -> 13 | M17: =IF($E17="Q42026",COUNTIF($E$3:$E17,"Q42026"),"") | N17: =IF($E17="Backlog",COUNTIF($E$3:$E17,"Backlog"),"")
A18: 4 | B18: UHD | S, M, L im UH sichtbar/Filterbar. (Kritisch, Wichtig und Normal -> sichtbar) | C18: L (20-40h) | D18: Strengthen | E18: Q32026 | F18: Should | G18: WEB | H18: =IF(C18="XXL (>160h)",168,IF(C18="XL (>40h)",48,IF(C18="L (20-40h)",30,IF(C18="M (10-20h)",15,IF(C18="S (<10h)",5,""))))) -> 30 | I18: Ausarbeitung Sebastian - End 03 | J18: =IF($E18="Q12026",COUNTIF($E$3:$E18,"Q12026"),"") | K18: =IF($E18="Q22026",COUNTIF($E$3:$E18,"Q22026"),"") | L18: =IF($E18="Q32026",COUNTIF($E$3:$E18,"Q32026"),"") -> 14 | M18: =IF($E18="Q42026",COUNTIF($E$3:$E18,"Q42026"),"") | N18: =IF($E18="Backlog",COUNTIF($E$3:$E18,"Backlog"),"")
A19: 5 | B19: Loaylty | Bonussystem 2.0 | C19: XXL (>160h) | D19: Innovation | E19: Q32026 | F19: Must | G19: WEB | H19: =IF(C19="XXL (>160h)",168,IF(C19="XL (>40h)",48,IF(C19="L (20-40h)",30,IF(C19="M (10-20h)",15,IF(C19="S (<10h)",5,""))))) -> 168 | J19: =IF($E19="Q12026",COUNTIF($E$3:$E19,"Q12026"),"") | K19: =IF($E19="Q22026",COUNTIF($E$3:$E19,"Q22026"),"") | L19: =IF($E19="Q32026",COUNTIF($E$3:$E19,"Q32026"),"") -> 15 | M19: =IF($E19="Q42026",COUNTIF($E$3:$E19,"Q42026"),"") | N19: =IF($E19="Backlog",COUNTIF($E$3:$E19,"Backlog"),"")
A20: 6 | B20: Wallet-Anbindung iOS & Android | Web Gutscheine und Tickets | C20: XL (>40h) | D20: Innovation | E20: Q32026 | F20: Should | G20: WEB | H20: =IF(C20="XXL (>160h)",168,IF(C20="XL (>40h)",48,IF(C20="L (20-40h)",30,IF(C20="M (10-20h)",15,IF(C20="S (<10h)",5,""))))) -> 48 | J20: =IF($E20="Q12026",COUNTIF($E$3:$E20,"Q12026"),"") | K20: =IF($E20="Q22026",COUNTIF($E$3:$E20,"Q22026"),"") | L20: =IF($E20="Q32026",COUNTIF($E$3:$E20,"Q32026"),"") -> 16 | M20: =IF($E20="Q42026",COUNTIF($E$3:$E20,"Q42026"),"") | N20: =IF($E20="Backlog",COUNTIF($E$3:$E20,"Backlog"),"")
A21: 10 | B21: API | Externer Kundenstamm | C21: L (20-40h) | D21: Strengthen | E21: Q32026 | F21: Could | G21: WEB | H21: =IF(C21="XXL (>160h)",168,IF(C21="XL (>40h)",48,IF(C21="L (20-40h)",30,IF(C21="M (10-20h)",15,IF(C21="S (<10h)",5,""))))) -> 30 | I21: Bidirektinaler Austausch der Registrierungen und Couponsdaten zwischen HS Kundenstamm und FW CRM | J21: =IF($E21="Q12026",COUNTIF($E$3:$E21,"Q12026"),"") | K21: =IF($E21="Q22026",COUNTIF($E$3:$E21,"Q22026"),"") | L21: =IF($E21="Q32026",COUNTIF($E$3:$E21,"Q32026"),"") -> 17 | M21: =IF($E21="Q42026",COUNTIF($E$3:$E21,"Q42026"),"") | N21: =IF($E21="Backlog",COUNTIF($E$3:$E21,"Backlog"),"")
A22: 8 | B22: TWINT / Konstantin / HILTL | C22: M (10-20h) | D22: Repair | E22: Q32026 | F22: Must | G22: WEB | H22: =IF(C22="XXL (>160h)",168,IF(C22="XL (>40h)",48,IF(C22="L (20-40h)",30,IF(C22="M (10-20h)",15,IF(C22="S (<10h)",5,""))))) -> 15 | J22: =IF($E22="Q12026",COUNTIF($E$3:$E22,"Q12026"),"") | K22: =IF($E22="Q22026",COUNTIF($E$3:$E22,"Q22026"),"") | L22: =IF($E22="Q32026",COUNTIF($E$3:$E22,"Q32026"),"") -> 18 | M22: =IF($E22="Q42026",COUNTIF($E$3:$E22,"Q42026"),"") | N22: =IF($E22="Backlog",COUNTIF($E$3:$E22,"Backlog"),"")
A23: 10 | B23: OpenTable API | C23: M (10-20h) | D23: Innovation | E23: Q32026 | F23: Could | G23: WEB | H23: =IF(C23="XXL (>160h)",168,IF(C23="XL (>40h)",48,IF(C23="L (20-40h)",30,IF(C23="M (10-20h)",15,IF(C23="S (<10h)",5,""))))) -> 15 | I23: Fertig von HS! Abstimmung auf der Internorga -> liegt bei Erich & Co. | J23: =IF($E23="Q12026",COUNTIF($E$3:$E23,"Q12026"),"") | K23: =IF($E23="Q22026",COUNTIF($E$3:$E23,"Q22026"),"") | L23: =IF($E23="Q32026",COUNTIF($E$3:$E23,"Q32026"),"") -> 19 | M23: =IF($E23="Q42026",COUNTIF($E$3:$E23,"Q42026"),"") | N23: =IF($E23="Backlog",COUNTIF($E$3:$E23,"Backlog"),"")
A24: 11 | B24: UHD | Incident Feedback an Kunde | C24: L (20-40h) | D24: Strengthen | E24: Q32026 | F24: Must | G24: WEB | H24: =IF(C24="XXL (>160h)",168,IF(C24="XL (>40h)",48,IF(C24="L (20-40h)",30,IF(C24="M (10-20h)",15,IF(C24="S (<10h)",5,""))))) -> 30 | I24: Start der Ausarbeitung in Q2 -> Marco | J24: =IF($E24="Q12026",COUNTIF($E$3:$E24,"Q12026"),"") | K24: =IF($E24="Q22026",COUNTIF($E$3:$E24,"Q22026"),"") | L24: =IF($E24="Q32026",COUNTIF($E$3:$E24,"Q32026"),"") -> 20 | M24: =IF($E24="Q42026",COUNTIF($E$3:$E24,"Q42026"),"") | N24: =IF($E24="Backlog",COUNTIF($E$3:$E24,"Backlog"),"")
A25: 14 | B25: HeyRosi -> API | C25: M (10-20h) | D25: Innovation | E25: Q32026 | F25: Should | G25: WEB | H25: =IF(C25="XXL (>160h)",168,IF(C25="XL (>40h)",48,IF(C25="L (20-40h)",30,IF(C25="M (10-20h)",15,IF(C25="S (<10h)",5,""))))) -> 15 | I25: Reservierung fertig! Internorga | erst danach Planung für Bestellung -> Q3 | J25: =IF($E25="Q12026",COUNTIF($E$3:$E25,"Q12026"),"") | K25: =IF($E25="Q22026",COUNTIF($E$3:$E25,"Q22026"),"") | L25: =IF($E25="Q32026",COUNTIF($E$3:$E25,"Q32026"),"") -> 21 | M25: =IF($E25="Q42026",COUNTIF($E$3:$E25,"Q42026"),"") | N25: =IF($E25="Backlog",COUNTIF($E$3:$E25,"Backlog"),"")
A26: 15 | B26: Landingpage zur Registrierung | C26: M (10-20h) | D26: Strengthen | E26: Q32026 | F26: Must | G26: WEB | H26: =IF(C26="XXL (>160h)",168,IF(C26="XL (>40h)",48,IF(C26="L (20-40h)",30,IF(C26="M (10-20h)",15,IF(C26="S (<10h)",5,""))))) -> 15 | J26: =IF($E26="Q12026",COUNTIF($E$3:$E26,"Q12026"),"") | K26: =IF($E26="Q22026",COUNTIF($E$3:$E26,"Q22026"),"") | L26: =IF($E26="Q32026",COUNTIF($E$3:$E26,"Q32026"),"") -> 22 | M26: =IF($E26="Q42026",COUNTIF($E$3:$E26,"Q42026"),"") | N26: =IF($E26="Backlog",COUNTIF($E$3:$E26,"Backlog"),"")
A27: 19 | B27: UI / Code - Portalmodernisierung | Benutzer | C27: XXL (>160h) | D27: Strengthen | E27: Q32026 | F27: Should | G27: WEB | H27: =IF(C27="XXL (>160h)",168,IF(C27="XL (>40h)",48,IF(C27="L (20-40h)",30,IF(C27="M (10-20h)",15,IF(C27="S (<10h)",5,""))))) -> 168 | J27: =IF($E27="Q12026",COUNTIF($E$3:$E27,"Q12026"),"") | K27: =IF($E27="Q22026",COUNTIF($E$3:$E27,"Q22026"),"") | L27: =IF($E27="Q32026",COUNTIF($E$3:$E27,"Q32026"),"") -> 23 | M27: =IF($E27="Q42026",COUNTIF($E$3:$E27,"Q42026"),"") | N27: =IF($E27="Backlog",COUNTIF($E$3:$E27,"Backlog"),"")
A28: 26 | B28: Einmal einlösbare Coupons für die YourApp | C28: XL (>40h) | D28: Strengthen | E28: Q32026 | F28: Must | G28: WEB | H28: =IF(C28="XXL (>160h)",168,IF(C28="XL (>40h)",48,IF(C28="L (20-40h)",30,IF(C28="M (10-20h)",15,IF(C28="S (<10h)",5,""))))) -> 48 | I28: Erst nach -> ID 9 SOT/Webshop & POS | J28: =IF($E28="Q12026",COUNTIF($E$3:$E28,"Q12026"),"") | K28: =IF($E28="Q22026",COUNTIF($E$3:$E28,"Q22026"),"") | L28: =IF($E28="Q32026",COUNTIF($E$3:$E28,"Q32026"),"") -> 24 | M28: =IF($E28="Q42026",COUNTIF($E$3:$E28,"Q42026"),"") | N28: =IF($E28="Backlog",COUNTIF($E$3:$E28,"Backlog"),"")
A29: 27 | H29: =IF(C29="XXL (>160h)",168,IF(C29="XL (>40h)",48,IF(C29="L (20-40h)",30,IF(C29="M (10-20h)",15,IF(C29="S (<10h)",5,""))))) | J29: =IF($E29="Q12026",COUNTIF($E$3:$E29,"Q12026"),"") | K29: =IF($E29="Q22026",COUNTIF($E$3:$E29,"Q22026"),"") | L29: =IF($E29="Q32026",COUNTIF($E$3:$E29,"Q32026"),"") | M29: =IF($E29="Q42026",COUNTIF($E$3:$E29,"Q42026"),"") | N29: =IF($E29="Backlog",COUNTIF($E$3:$E29,"Backlog"),"")
A30: 28 | H30: =IF(C30="XXL (>160h)",168,IF(C30="XL (>40h)",48,IF(C30="L (20-40h)",30,IF(C30="M (10-20h)",15,IF(C30="S (<10h)",5,""))))) | J30: =IF($E30="Q12026",COUNTIF($E$3:$E30,"Q12026"),"") | K30: =IF($E30="Q22026",COUNTIF($E$3:$E30,"Q22026"),"") | L30: =IF($E30="Q32026",COUNTIF($E$3:$E30,"Q32026"),"") | M30: =IF($E30="Q42026",COUNTIF($E$3:$E30,"Q42026"),"") | N30: =IF($E30="Backlog",COUNTIF($E$3:$E30,"Backlog"),"")
A31: 29 | H31: =IF(C31="XXL (>160h)",168,IF(C31="XL (>40h)",48,IF(C31="L (20-40h)",30,IF(C31="M (10-20h)",15,IF(C31="S (<10h)",5,""))))) | J31: =IF($E31="Q12026",COUNTIF($E$3:$E31,"Q12026"),"") | K31: =IF($E31="Q22026",COUNTIF($E$3:$E31,"Q22026"),"") | L31: =IF($E31="Q32026",COUNTIF($E$3:$E31,"Q32026"),"") | M31: =IF($E31="Q42026",COUNTIF($E$3:$E31,"Q42026"),"") | N31: =IF($E31="Backlog",COUNTIF($E$3:$E31,"Backlog"),"")
A32: 30 | H32: =IF(C32="XXL (>160h)",168,IF(C32="XL (>40h)",48,IF(C32="L (20-40h)",30,IF(C32="M (10-20h)",15,IF(C32="S (<10h)",5,""))))) | J32: =IF($E32="Q12026",COUNTIF($E$3:$E32,"Q12026"),"") | K32: =IF($E32="Q22026",COUNTIF($E$3:$E32,"Q22026"),"") | L32: =IF($E32="Q32026",COUNTIF($E$3:$E32,"Q32026"),"") | M32: =IF($E32="Q42026",COUNTIF($E$3:$E32,"Q42026"),"") | N32: =IF($E32="Backlog",COUNTIF($E$3:$E32,"Backlog"),"")
A33: 31 | H33: =IF(C33="XXL (>160h)",168,IF(C33="XL (>40h)",48,IF(C33="L (20-40h)",30,IF(C33="M (10-20h)",15,IF(C33="S (<10h)",5,""))))) | J33: =IF($E33="Q12026",COUNTIF($E$3:$E33,"Q12026"),"") | K33: =IF($E33="Q22026",COUNTIF($E$3:$E33,"Q22026"),"") | L33: =IF($E33="Q32026",COUNTIF($E$3:$E33,"Q32026"),"") | M33: =IF($E33="Q42026",COUNTIF($E$3:$E33,"Q42026"),"") | N33: =IF($E33="Backlog",COUNTIF($E$3:$E33,"Backlog"),"")
A34: 32 | H34: =IF(C34="XXL (>160h)",168,IF(C34="XL (>40h)",48,IF(C34="L (20-40h)",30,IF(C34="M (10-20h)",15,IF(C34="S (<10h)",5,""))))) | J34: =IF($E34="Q12026",COUNTIF($E$3:$E34,"Q12026"),"") | K34: =IF($E34="Q22026",COUNTIF($E$3:$E34,"Q22026"),"") | L34: =IF($E34="Q32026",COUNTIF($E$3:$E34,"Q32026"),"") | M34: =IF($E34="Q42026",COUNTIF($E$3:$E34,"Q42026"),"") | N34: =IF($E34="Backlog",COUNTIF($E$3:$E34,"Backlog"),"")
A35: 33 | H35: =IF(C35="XXL (>160h)",168,IF(C35="XL (>40h)",48,IF(C35="L (20-40h)",30,IF(C35="M (10-20h)",15,IF(C35="S (<10h)",5,""))))) | J35: =IF($E35="Q12026",COUNTIF($E$3:$E35,"Q12026"),"") | K35: =IF($E35="Q22026",COUNTIF($E$3:$E35,"Q22026"),"") | L35: =IF($E35="Q32026",COUNTIF($E$3:$E35,"Q32026"),"") | M35: =IF($E35="Q42026",COUNTIF($E$3:$E35,"Q42026"),"") | N35: =IF($E35="Backlog",COUNTIF($E$3:$E35,"Backlog"),"")
A36: 34 | H36: =IF(C36="XXL (>160h)",168,IF(C36="XL (>40h)",48,IF(C36="L (20-40h)",30,IF(C36="M (10-20h)",15,IF(C36="S (<10h)",5,""))))) | J36: =IF($E36="Q12026",COUNTIF($E$3:$E36,"Q12026"),"") | K36: =IF($E36="Q22026",COUNTIF($E$3:$E36,"Q22026"),"") | L36: =IF($E36="Q32026",COUNTIF($E$3:$E36,"Q32026"),"") | M36: =IF($E36="Q42026",COUNTIF($E$3:$E36,"Q42026"),"") | N36: =IF($E36="Backlog",COUNTIF($E$3:$E36,"Backlog"),"")
A37: 35 | H37: =IF(C37="XXL (>160h)",168,IF(C37="XL (>40h)",48,IF(C37="L (20-40h)",30,IF(C37="M (10-20h)",15,IF(C37="S (<10h)",5,""))))) | J37: =IF($E37="Q12026",COUNTIF($E$3:$E37,"Q12026"),"") | K37: =IF($E37="Q22026",COUNTIF($E$3:$E37,"Q22026"),"") | L37: =IF($E37="Q32026",COUNTIF($E$3:$E37,"Q32026"),"") | M37: =IF($E37="Q42026",COUNTIF($E$3:$E37,"Q42026"),"") | N37: =IF($E37="Backlog",COUNTIF($E$3:$E37,"Backlog"),"")
A38: 36 | H38: =IF(C38="XXL (>160h)",168,IF(C38="XL (>40h)",48,IF(C38="L (20-40h)",30,IF(C38="M (10-20h)",15,IF(C38="S (<10h)",5,""))))) | J38: =IF($E38="Q12026",COUNTIF($E$3:$E38,"Q12026"),"") | K38: =IF($E38="Q22026",COUNTIF($E$3:$E38,"Q22026"),"") | L38: =IF($E38="Q32026",COUNTIF($E$3:$E38,"Q32026"),"") | M38: =IF($E38="Q42026",COUNTIF($E$3:$E38,"Q42026"),"") | N38: =IF($E38="Backlog",COUNTIF($E$3:$E38,"Backlog"),"")
A39: 37 | H39: =IF(C39="XXL (>160h)",168,IF(C39="XL (>40h)",48,IF(C39="L (20-40h)",30,IF(C39="M (10-20h)",15,IF(C39="S (<10h)",5,""))))) | J39: =IF($E39="Q12026",COUNTIF($E$3:$E39,"Q12026"),"") | K39: =IF($E39="Q22026",COUNTIF($E$3:$E39,"Q22026"),"") | L39: =IF($E39="Q32026",COUNTIF($E$3:$E39,"Q32026"),"") | M39: =IF($E39="Q42026",COUNTIF($E$3:$E39,"Q42026"),"") | N39: =IF($E39="Backlog",COUNTIF($E$3:$E39,"Backlog"),"")
A40: 38 | H40: =IF(C40="XXL (>160h)",168,IF(C40="XL (>40h)",48,IF(C40="L (20-40h)",30,IF(C40="M (10-20h)",15,IF(C40="S (<10h)",5,""))))) | J40: =IF($E40="Q12026",COUNTIF($E$3:$E40,"Q12026"),"") | K40: =IF($E40="Q22026",COUNTIF($E$3:$E40,"Q22026"),"") | L40: =IF($E40="Q32026",COUNTIF($E$3:$E40,"Q32026"),"") | M40: =IF($E40="Q42026",COUNTIF($E$3:$E40,"Q42026"),"") | N40: =IF($E40="Backlog",COUNTIF($E$3:$E40,"Backlog"),"")
... A82: 80 | H82: =IF(C82="XXL (>160h)",168,IF(C82="XL (>40h)",48,IF(C82="L (20-40h)",30,IF(C82="M (10-20h)",15,IF(C82="S (<10h)",5,""))))) | J82: =IF($E82="Q12026",COUNTIF($E$3:$E82,"Q12026"),"") | K82: =IF($E82="Q22026",COUNTIF($E$3:$E82,"Q22026"),"") | L82: =IF($E82="Q32026",COUNTIF($E$3:$E82,"Q32026"),"") | M82: =IF($E82="Q42026",COUNTIF($E$3:$E82,"Q42026"),"") | N82: =IF($E82="Backlog",COUNTIF($E$3:$E82,"Backlog"),"")
A83: ∑ Geschätzte Stunden gesamt | H83: =SUM(H3:H82) -> 1317
A85: Value: 🟢 Strengthen = strategische Stärkung | 🔵 Innovation = neue Fähigkeiten | 🔴 Repair = Fehler/Schulden beheben
A86: MoSCoW: Must = Pflicht · Should = Soll · Could = Optional · Won't = Ausgeschlossen | Team: WEB · Desktop · W->D · D->W (anteilig je 50% auf beide Teams)
A87: Größen: S <10h · M 10–20h · L 20–40h · XL >40h · XXL >160h | Stunden = automatisch aus Größe | Kapazitäten (blaue Felder) = manuell

Sheet Q42026
A1: Q42026
A2: # | B2: Projekttitel | C2: Größe | D2: Value-Bucket | E2: Quartal | F2: MoSCoW | G2: Team | H2: Std. | I2: Bemerkungen
A3: 1 | B3: ReFund Zahlung POS | Refund bei Adyen | Pfand-Gutschrift bei Kartenzahlung | E3: Q42026 | H3: =IF(C3="XXL (>160h)",168,IF(C3="XL (>40h)",48,IF(C3="L (20-40h)",30,IF(C3="M (10-20h)",15,IF(C3="S (<10h)",5,""))))) | J3: =IF($E3="Q12026",COUNTIF($E$3:$E3,"Q12026"),"") | K3: =IF($E3="Q22026",COUNTIF($E$3:$E3,"Q22026"),"") | L3: =IF($E3="Q32026",COUNTIF($E$3:$E3,"Q32026"),"") | M3: =IF($E3="Q42026",COUNTIF($E$3:$E3,"Q42026"),"") -> 1 | N3: =IF($E3="Backlog",COUNTIF($E$3:$E3,"Backlog"),"")
A4: 2 | B4: Abholmonitor (ggf. extern) | API | E4: Q42026 | H4: =IF(C4="XXL (>160h)",168,IF(C4="XL (>40h)",48,IF(C4="L (20-40h)",30,IF(C4="M (10-20h)",15,IF(C4="S (<10h)",5,""))))) | J4: =IF($E4="Q12026",COUNTIF($E$3:$E4,"Q12026"),"") | K4: =IF($E4="Q22026",COUNTIF($E$3:$E4,"Q22026"),"") | L4: =IF($E4="Q32026",COUNTIF($E$3:$E4,"Q32026"),"") | M4: =IF($E4="Q42026",COUNTIF($E$3:$E4,"Q42026"),"") -> 2 | N4: =IF($E4="Backlog",COUNTIF($E$3:$E4,"Backlog"),"")
A5: 3 | B5: Portal & POS - UX Update (1) | E5: Q42026 | H5: =IF(C5="XXL (>160h)",168,IF(C5="XL (>40h)",48,IF(C5="L (20-40h)",30,IF(C5="M (10-20h)",15,IF(C5="S (<10h)",5,""))))) | J5: =IF($E5="Q12026",COUNTIF($E$3:$E5,"Q12026"),"") | K5: =IF($E5="Q22026",COUNTIF($E$3:$E5,"Q22026"),"") | L5: =IF($E5="Q32026",COUNTIF($E$3:$E5,"Q32026"),"") | M5: =IF($E5="Q42026",COUNTIF($E$3:$E5,"Q42026"),"") -> 3 | N5: =IF($E5="Backlog",COUNTIF($E$3:$E5,"Backlog"),"")
A6: 4 | B6: Artikelbestandteile im eCom abwählen | E6: Q42026 | H6: =IF(C6="XXL (>160h)",168,IF(C6="XL (>40h)",48,IF(C6="L (20-40h)",30,IF(C6="M (10-20h)",15,IF(C6="S (<10h)",5,""))))) | J6: =IF($E6="Q12026",COUNTIF($E$3:$E6,"Q12026"),"") | K6: =IF($E6="Q22026",COUNTIF($E$3:$E6,"Q22026"),"") | L6: =IF($E6="Q32026",COUNTIF($E$3:$E6,"Q32026"),"") | M6: =IF($E6="Q42026",COUNTIF($E$3:$E6,"Q42026"),"") -> 4 | N6: =IF($E6="Backlog",COUNTIF($E$3:$E6,"Backlog"),"")
A7: 5 | B7: KPI Dashboard mit KI | E7: Q42026 | H7: =IF(C7="XXL (>160h)",168,IF(C7="XL (>40h)",48,IF(C7="L (20-40h)",30,IF(C7="M (10-20h)",15,IF(C7="S (<10h)",5,""))))) | J7: =IF($E7="Q12026",COUNTIF($E$3:$E7,"Q12026"),"") | K7: =IF($E7="Q22026",COUNTIF($E$3:$E7,"Q22026"),"") | L7: =IF($E7="Q32026",COUNTIF($E$3:$E7,"Q32026"),"") | M7: =IF($E7="Q42026",COUNTIF($E$3:$E7,"Q42026"),"") -> 5 | N7: =IF($E7="Backlog",COUNTIF($E$3:$E7,"Backlog"),"")
A8: 6 | B8: Loyalty (4) | DataWarehouse und KI NOCH NICHT GEPLANT | E8: Q42026 | H8: =IF(C8="XXL (>160h)",168,IF(C8="XL (>40h)",48,IF(C8="L (20-40h)",30,IF(C8="M (10-20h)",15,IF(C8="S (<10h)",5,""))))) | J8: =IF($E8="Q12026",COUNTIF($E$3:$E8,"Q12026"),"") | K8: =IF($E8="Q22026",COUNTIF($E$3:$E8,"Q22026"),"") | L8: =IF($E8="Q32026",COUNTIF($E$3:$E8,"Q32026"),"") | M8: =IF($E8="Q42026",COUNTIF($E$3:$E8,"Q42026"),"") -> 6 | N8: =IF($E8="Backlog",COUNTIF($E$3:$E8,"Backlog"),"")
A9: 7 | B9: Jouney Gaps (3) | E9: Q42026 | H9: =IF(C9="XXL (>160h)",168,IF(C9="XL (>40h)",48,IF(C9="L (20-40h)",30,IF(C9="M (10-20h)",15,IF(C9="S (<10h)",5,""))))) | J9: =IF($E9="Q12026",COUNTIF($E$3:$E9,"Q12026"),"") | K9: =IF($E9="Q22026",COUNTIF($E$3:$E9,"Q22026"),"") | L9: =IF($E9="Q32026",COUNTIF($E$3:$E9,"Q32026"),"") | M9: =IF($E9="Q42026",COUNTIF($E$3:$E9,"Q42026"),"") -> 7 | N9: =IF($E9="Backlog",COUNTIF($E$3:$E9,"Backlog"),"")
A10: 8 | B10: Artikelgenaue Übergabe an PMS-Interface (MEWS) | D10: Strengthen | E10: Q42026 | F10: Should | H10: =IF(C10="XXL (>160h)",168,IF(C10="XL (>40h)",48,IF(C10="L (20-40h)",30,IF(C10="M (10-20h)",15,IF(C10="S (<10h)",5,""))))) | J10: =IF($E10="Q12026",COUNTIF($E$3:$E10,"Q12026"),"") | K10: =IF($E10="Q22026",COUNTIF($E$3:$E10,"Q22026"),"") | L10: =IF($E10="Q32026",COUNTIF($E$3:$E10,"Q32026"),"") | M10: =IF($E10="Q42026",COUNTIF($E$3:$E10,"Q42026"),"") -> 8 | N10: =IF($E10="Backlog",COUNTIF($E$3:$E10,"Backlog"),"")
A11: 9 | B11: ePOS Campaigns | D11: Repair | E11: Q42026 | F11: Should | H11: =IF(C11="XXL (>160h)",168,IF(C11="XL (>40h)",48,IF(C11="L (20-40h)",30,IF(C11="M (10-20h)",15,IF(C11="S (<10h)",5,""))))) | J11: =IF($E11="Q12026",COUNTIF($E$3:$E11,"Q12026"),"") | K11: =IF($E11="Q22026",COUNTIF($E$3:$E11,"Q22026"),"") | L11: =IF($E11="Q32026",COUNTIF($E$3:$E11,"Q32026"),"") | M11: =IF($E11="Q42026",COUNTIF($E$3:$E11,"Q42026"),"") -> 9 | N11: =IF($E11="Backlog",COUNTIF($E$3:$E11,"Backlog"),"")
A12: 10 | B12: Deaktivierung von Order Channel an POS | D12: Innovation | E12: Q42026 | F12: Should | H12: =IF(C12="XXL (>160h)",168,IF(C12="XL (>40h)",48,IF(C12="L (20-40h)",30,IF(C12="M (10-20h)",15,IF(C12="S (<10h)",5,""))))) | I12: Kochlöffel!!! | J12: =IF($E12="Q12026",COUNTIF($E$3:$E12,"Q12026"),"") | K12: =IF($E12="Q22026",COUNTIF($E$3:$E12,"Q22026"),"") | L12: =IF($E12="Q32026",COUNTIF($E$3:$E12,"Q32026"),"") | M12: =IF($E12="Q42026",COUNTIF($E$3:$E12,"Q42026"),"") -> 10 | N12: =IF($E12="Backlog",COUNTIF($E$3:$E12,"Backlog"),"")
A13: 11 | B13: Accounting in YourAPP | D13: Innovation | E13: Q42026 | F13: Could | H13: =IF(C13="XXL (>160h)",168,IF(C13="XL (>40h)",48,IF(C13="L (20-40h)",30,IF(C13="M (10-20h)",15,IF(C13="S (<10h)",5,""))))) | I13: KHATIA??? | J13: =IF($E13="Q12026",COUNTIF($E$3:$E13,"Q12026"),"") | K13: =IF($E13="Q22026",COUNTIF($E$3:$E13,"Q22026"),"") | L13: =IF($E13="Q32026",COUNTIF($E$3:$E13,"Q32026"),"") | M13: =IF($E13="Q42026",COUNTIF($E$3:$E13,"Q42026"),"") -> 11 | N13: =IF($E13="Backlog",COUNTIF($E$3:$E13,"Backlog"),"")
A14: 12 | B14: Signum Orga-Soft API erweitern | D14: Strengthen | E14: Q42026 | H14: =IF(C14="XXL (>160h)",168,IF(C14="XL (>40h)",48,IF(C14="L (20-40h)",30,IF(C14="M (10-20h)",15,IF(C14="S (<10h)",5,""))))) | J14: =IF($E14="Q12026",COUNTIF($E$3:$E14,"Q12026"),"") | K14: =IF($E14="Q22026",COUNTIF($E$3:$E14,"Q22026"),"") | L14: =IF($E14="Q32026",COUNTIF($E$3:$E14,"Q32026"),"") | M14: =IF($E14="Q42026",COUNTIF($E$3:$E14,"Q42026"),"") -> 12 | N14: =IF($E14="Backlog",COUNTIF($E$3:$E14,"Backlog"),"")
A15: 13 | B15: Loyalty (3) | Couopons 2.0 NOCH NICHT GEPLANT | D15: Innovation | E15: Q42026 | H15: =IF(C15="XXL (>160h)",168,IF(C15="XL (>40h)",48,IF(C15="L (20-40h)",30,IF(C15="M (10-20h)",15,IF(C15="S (<10h)",5,""))))) | J15: =IF($E15="Q12026",COUNTIF($E$3:$E15,"Q12026"),"") | K15: =IF($E15="Q22026",COUNTIF($E$3:$E15,"Q22026"),"") | L15: =IF($E15="Q32026",COUNTIF($E$3:$E15,"Q32026"),"") | M15: =IF($E15="Q42026",COUNTIF($E$3:$E15,"Q42026"),"") -> 13 | N15: =IF($E15="Backlog",COUNTIF($E$3:$E15,"Backlog"),"")
A16: 14 | B16: Data Warehouse | D16: Strengthen | E16: Q42026 | H16: =IF(C16="XXL (>160h)",168,IF(C16="XL (>40h)",48,IF(C16="L (20-40h)",30,IF(C16="M (10-20h)",15,IF(C16="S (<10h)",5,""))))) | J16: =IF($E16="Q12026",COUNTIF($E$3:$E16,"Q12026"),"") | K16: =IF($E16="Q22026",COUNTIF($E$3:$E16,"Q22026"),"") | L16: =IF($E16="Q32026",COUNTIF($E$3:$E16,"Q32026"),"") | M16: =IF($E16="Q42026",COUNTIF($E$3:$E16,"Q42026"),"") -> 14 | N16: =IF($E16="Backlog",COUNTIF($E$3:$E16,"Backlog"),"")
A17: 15 | B17: Paypal V2 | D17: Strengthen | E17: Q42026 | H17: =IF(C17="XXL (>160h)",168,IF(C17="XL (>40h)",48,IF(C17="L (20-40h)",30,IF(C17="M (10-20h)",15,IF(C17="S (<10h)",5,""))))) | J17: =IF($E17="Q12026",COUNTIF($E$3:$E17,"Q12026"),"") | K17: =IF($E17="Q22026",COUNTIF($E$3:$E17,"Q22026"),"") | L17: =IF($E17="Q32026",COUNTIF($E$3:$E17,"Q32026"),"") | M17: =IF($E17="Q42026",COUNTIF($E$3:$E17,"Q42026"),"") -> 15 | N17: =IF($E17="Backlog",COUNTIF($E$3:$E17,"Backlog"),"")
A18: 16 | B18: App-Systemstart beschleunigen / Code aktualisieren | D18: Strengthen | E18: Q42026 | H18: =IF(C18="XXL (>160h)",168,IF(C18="XL (>40h)",48,IF(C18="L (20-40h)",30,IF(C18="M (10-20h)",15,IF(C18="S (<10h)",5,""))))) | J18: =IF($E18="Q12026",COUNTIF($E$3:$E18,"Q12026"),"") | K18: =IF($E18="Q22026",COUNTIF($E$3:$E18,"Q22026"),"") | L18: =IF($E18="Q32026",COUNTIF($E$3:$E18,"Q32026"),"") | M18: =IF($E18="Q42026",COUNTIF($E$3:$E18,"Q42026"),"") -> 16 | N18: =IF($E18="Backlog",COUNTIF($E$3:$E18,"Backlog"),"")
A19: 17 | B19: SIG - WAWI - Schnittstelle (Foodnotify / Apicbase) -> CDS & Vapiano | D19: Innovation | E19: Q42026 | H19: =IF(C19="XXL (>160h)",168,IF(C19="XL (>40h)",48,IF(C19="L (20-40h)",30,IF(C19="M (10-20h)",15,IF(C19="S (<10h)",5,""))))) | I19: ??? | J19: =IF($E19="Q12026",COUNTIF($E$3:$E19,"Q12026"),"") | K19: =IF($E19="Q22026",COUNTIF($E$3:$E19,"Q22026"),"") | L19: =IF($E19="Q32026",COUNTIF($E$3:$E19,"Q32026"),"") | M19: =IF($E19="Q42026",COUNTIF($E$3:$E19,"Q42026"),"") -> 17 | N19: =IF($E19="Backlog",COUNTIF($E$3:$E19,"Backlog"),"")
A20: 18 | B20: NoCOO Code am SOT mit optionalem Ausdruck / weitere Informationen müssen ergänzt werden (Superhelden, etc.) -> Bewerten Q3 | D20: Strengthen | E20: Q42026 | H20: =IF(C20="XXL (>160h)",168,IF(C20="XL (>40h)",48,IF(C20="L (20-40h)",30,IF(C20="M (10-20h)",15,IF(C20="S (<10h)",5,""))))) | J20: =IF($E20="Q12026",COUNTIF($E$3:$E20,"Q12026"),"") | K20: =IF($E20="Q22026",COUNTIF($E$3:$E20,"Q22026"),"") | L20: =IF($E20="Q32026",COUNTIF($E$3:$E20,"Q32026"),"") | M20: =IF($E20="Q42026",COUNTIF($E$3:$E20,"Q42026"),"") -> 18 | N20: =IF($E20="Backlog",COUNTIF($E$3:$E20,"Backlog"),"")
A21: 19 | B21: Borland Code Migrieren in Visual Studio - bis Q4 muss das umgesetzt werden | D21: Strengthen | E21: Q42026 | H21: =IF(C21="XXL (>160h)",168,IF(C21="XL (>40h)",48,IF(C21="L (20-40h)",30,IF(C21="M (10-20h)",15,IF(C21="S (<10h)",5,""))))) | J21: =IF($E21="Q12026",COUNTIF($E$3:$E21,"Q12026"),"") | K21: =IF($E21="Q22026",COUNTIF($E$3:$E21,"Q22026"),"") | L21: =IF($E21="Q32026",COUNTIF($E$3:$E21,"Q32026"),"") | M21: =IF($E21="Q42026",COUNTIF($E$3:$E21,"Q42026"),"") -> 19 | N21: =IF($E21="Backlog",COUNTIF($E$3:$E21,"Backlog"),"")
A22: 20 | B22: 64 Bit Konvertierung | D22: Strengthen | E22: Q42026 | H22: =IF(C22="XXL (>160h)",168,IF(C22="XL (>40h)",48,IF(C22="L (20-40h)",30,IF(C22="M (10-20h)",15,IF(C22="S (<10h)",5,""))))) | I22: 2027 | J22: =IF($E22="Q12026",COUNTIF($E$3:$E22,"Q12026"),"") | K22: =IF($E22="Q22026",COUNTIF($E$3:$E22,"Q22026"),"") | L22: =IF($E22="Q32026",COUNTIF($E$3:$E22,"Q32026"),"") | M22: =IF($E22="Q42026",COUNTIF($E$3:$E22,"Q42026"),"") -> 20 | N22: =IF($E22="Backlog",COUNTIF($E$3:$E22,"Backlog"),"")
A23: 21 | B23: Webshop und erweiterte Zeitsteuerung (Artikel nicht verfügbar, bei Bestellung morgens für Mittags) -> CDS | D23: Strengthen | E23: Q42026 | H23: =IF(C23="XXL (>160h)",168,IF(C23="XL (>40h)",48,IF(C23="L (20-40h)",30,IF(C23="M (10-20h)",15,IF(C23="S (<10h)",5,""))))) | I23: Q3 Release | J23: =IF($E23="Q12026",COUNTIF($E$3:$E23,"Q12026"),"") | K23: =IF($E23="Q22026",COUNTIF($E$3:$E23,"Q22026"),"") | L23: =IF($E23="Q32026",COUNTIF($E$3:$E23,"Q32026"),"") | M23: =IF($E23="Q42026",COUNTIF($E$3:$E23,"Q42026"),"") -> 21 | N23: =IF($E23="Backlog",COUNTIF($E$3:$E23,"Backlog"),"")
A24: 22 | B24: Digital Signage (Api) | D24: Innovation | E24: Q42026 | H24: =IF(C24="XXL (>160h)",168,IF(C24="XL (>40h)",48,IF(C24="L (20-40h)",30,IF(C24="M (10-20h)",15,IF(C24="S (<10h)",5,""))))) | I24: Kochlöffel!!! | J24: =IF($E24="Q12026",COUNTIF($E$3:$E24,"Q12026"),"") | K24: =IF($E24="Q22026",COUNTIF($E$3:$E24,"Q22026"),"") | L24: =IF($E24="Q32026",COUNTIF($E$3:$E24,"Q32026"),"") | M24: =IF($E24="Q42026",COUNTIF($E$3:$E24,"Q42026"),"") -> 22 | N24: =IF($E24="Backlog",COUNTIF($E$3:$E24,"Backlog"),"")
A25: 23 | B25: 2-Faktor-Authentifizierung / Portal | D25: Strengthen | E25: Q42026 | H25: =IF(C25="XXL (>160h)",168,IF(C25="XL (>40h)",48,IF(C25="L (20-40h)",30,IF(C25="M (10-20h)",15,IF(C25="S (<10h)",5,""))))) | I25: Webshop | J25: =IF($E25="Q12026",COUNTIF($E$3:$E25,"Q12026"),"") | K25: =IF($E25="Q22026",COUNTIF($E$3:$E25,"Q22026"),"") | L25: =IF($E25="Q32026",COUNTIF($E$3:$E25,"Q32026"),"") | M25: =IF($E25="Q42026",COUNTIF($E$3:$E25,"Q42026"),"") -> 23 | N25: =IF($E25="Backlog",COUNTIF($E$3:$E25,"Backlog"),"")
A26: 24 | B26: UHD - RMA Digitalisieren | D26: Strengthen | E26: Q42026 | H26: =IF(C26="XXL (>160h)",168,IF(C26="XL (>40h)",48,IF(C26="L (20-40h)",30,IF(C26="M (10-20h)",15,IF(C26="S (<10h)",5,""))))) | I26: Ausarbeitung Sebastian | J26: =IF($E26="Q12026",COUNTIF($E$3:$E26,"Q12026"),"") | K26: =IF($E26="Q22026",COUNTIF($E$3:$E26,"Q22026"),"") | L26: =IF($E26="Q32026",COUNTIF($E$3:$E26,"Q32026"),"") | M26: =IF($E26="Q42026",COUNTIF($E$3:$E26,"Q42026"),"") -> 24 | N26: =IF($E26="Backlog",COUNTIF($E$3:$E26,"Backlog"),"")
A27: 25 | B27: Miles & More - Integration | H27: =IF(C27="XXL (>160h)",168,IF(C27="XL (>40h)",48,IF(C27="L (20-40h)",30,IF(C27="M (10-20h)",15,IF(C27="S (<10h)",5,""))))) | I27: ??? | J27: =IF($E27="Q12026",COUNTIF($E$3:$E27,"Q12026"),"") | K27: =IF($E27="Q22026",COUNTIF($E$3:$E27,"Q22026"),"") | L27: =IF($E27="Q32026",COUNTIF($E$3:$E27,"Q32026"),"") | M27: =IF($E27="Q42026",COUNTIF($E$3:$E27,"Q42026"),"") | N27: =IF($E27="Backlog",COUNTIF($E$3:$E27,"Backlog"),"")
A28: 26 | B28: Incident-Nr: 685474 | Fehler bei Bedienerwechsel | H28: =IF(C28="XXL (>160h)",168,IF(C28="XL (>40h)",48,IF(C28="L (20-40h)",30,IF(C28="M (10-20h)",15,IF(C28="S (<10h)",5,""))))) | I28: Fertig! | J28: =IF($E28="Q12026",COUNTIF($E$3:$E28,"Q12026"),"") | K28: =IF($E28="Q22026",COUNTIF($E$3:$E28,"Q22026"),"") | L28: =IF($E28="Q32026",COUNTIF($E$3:$E28,"Q32026"),"") | M28: =IF($E28="Q42026",COUNTIF($E$3:$E28,"Q42026"),"") | N28: =IF($E28="Backlog",COUNTIF($E$3:$E28,"Backlog"),"")
A29: 27 | B29: MobileEntry in das ePOS mobilePRO integrieren | E29: Q42026 | H29: =IF(C29="XXL (>160h)",168,IF(C29="XL (>40h)",48,IF(C29="L (20-40h)",30,IF(C29="M (10-20h)",15,IF(C29="S (<10h)",5,""))))) | J29: =IF($E29="Q12026",COUNTIF($E$3:$E29,"Q12026"),"") | K29: =IF($E29="Q22026",COUNTIF($E$3:$E29,"Q22026"),"") | L29: =IF($E29="Q32026",COUNTIF($E$3:$E29,"Q32026"),"") | M29: =IF($E29="Q42026",COUNTIF($E$3:$E29,"Q42026"),"") -> 25 | N29: =IF($E29="Backlog",COUNTIF($E$3:$E29,"Backlog"),"")
A30: 28 | H30: =IF(C30="XXL (>160h)",168,IF(C30="XL (>40h)",48,IF(C30="L (20-40h)",30,IF(C30="M (10-20h)",15,IF(C30="S (<10h)",5,""))))) | J30: =IF($E30="Q12026",COUNTIF($E$3:$E30,"Q12026"),"") | K30: =IF($E30="Q22026",COUNTIF($E$3:$E30,"Q22026"),"") | L30: =IF($E30="Q32026",COUNTIF($E$3:$E30,"Q32026"),"") | M30: =IF($E30="Q42026",COUNTIF($E$3:$E30,"Q42026"),"") | N30: =IF($E30="Backlog",COUNTIF($E$3:$E30,"Backlog"),"")
A31: 29 | H31: =IF(C31="XXL (>160h)",168,IF(C31="XL (>40h)",48,IF(C31="L (20-40h)",30,IF(C31="M (10-20h)",15,IF(C31="S (<10h)",5,""))))) | J31: =IF($E31="Q12026",COUNTIF($E$3:$E31,"Q12026"),"") | K31: =IF($E31="Q22026",COUNTIF($E$3:$E31,"Q22026"),"") | L31: =IF($E31="Q32026",COUNTIF($E$3:$E31,"Q32026"),"") | M31: =IF($E31="Q42026",COUNTIF($E$3:$E31,"Q42026"),"") | N31: =IF($E31="Backlog",COUNTIF($E$3:$E31,"Backlog"),"")
A32: 30 | H32: =IF(C32="XXL (>160h)",168,IF(C32="XL (>40h)",48,IF(C32="L (20-40h)",30,IF(C32="M (10-20h)",15,IF(C32="S (<10h)",5,""))))) | J32: =IF($E32="Q12026",COUNTIF($E$3:$E32,"Q12026"),"") | K32: =IF($E32="Q22026",COUNTIF($E$3:$E32,"Q22026"),"") | L32: =IF($E32="Q32026",COUNTIF($E$3:$E32,"Q32026"),"") | M32: =IF($E32="Q42026",COUNTIF($E$3:$E32,"Q42026"),"") | N32: =IF($E32="Backlog",COUNTIF($E$3:$E32,"Backlog"),"")
A33: 31 | H33: =IF(C33="XXL (>160h)",168,IF(C33="XL (>40h)",48,IF(C33="L (20-40h)",30,IF(C33="M (10-20h)",15,IF(C33="S (<10h)",5,""))))) | J33: =IF($E33="Q12026",COUNTIF($E$3:$E33,"Q12026"),"") | K33: =IF($E33="Q22026",COUNTIF($E$3:$E33,"Q22026"),"") | L33: =IF($E33="Q32026",COUNTIF($E$3:$E33,"Q32026"),"") | M33: =IF($E33="Q42026",COUNTIF($E$3:$E33,"Q42026"),"") | N33: =IF($E33="Backlog",COUNTIF($E$3:$E33,"Backlog"),"")
A34: 32 | H34: =IF(C34="XXL (>160h)",168,IF(C34="XL (>40h)",48,IF(C34="L (20-40h)",30,IF(C34="M (10-20h)",15,IF(C34="S (<10h)",5,""))))) | J34: =IF($E34="Q12026",COUNTIF($E$3:$E34,"Q12026"),"") | K34: =IF($E34="Q22026",COUNTIF($E$3:$E34,"Q22026"),"") | L34: =IF($E34="Q32026",COUNTIF($E$3:$E34,"Q32026"),"") | M34: =IF($E34="Q42026",COUNTIF($E$3:$E34,"Q42026"),"") | N34: =IF($E34="Backlog",COUNTIF($E$3:$E34,"Backlog"),"")
A35: 33 | H35: =IF(C35="XXL (>160h)",168,IF(C35="XL (>40h)",48,IF(C35="L (20-40h)",30,IF(C35="M (10-20h)",15,IF(C35="S (<10h)",5,""))))) | J35: =IF($E35="Q12026",COUNTIF($E$3:$E35,"Q12026"),"") | K35: =IF($E35="Q22026",COUNTIF($E$3:$E35,"Q22026"),"") | L35: =IF($E35="Q32026",COUNTIF($E$3:$E35,"Q32026"),"") | M35: =IF($E35="Q42026",COUNTIF($E$3:$E35,"Q42026"),"") | N35: =IF($E35="Backlog",COUNTIF($E$3:$E35,"Backlog"),"")
A36: 34 | H36: =IF(C36="XXL (>160h)",168,IF(C36="XL (>40h)",48,IF(C36="L (20-40h)",30,IF(C36="M (10-20h)",15,IF(C36="S (<10h)",5,""))))) | J36: =IF($E36="Q12026",COUNTIF($E$3:$E36,"Q12026"),"") | K36: =IF($E36="Q22026",COUNTIF($E$3:$E36,"Q22026"),"") | L36: =IF($E36="Q32026",COUNTIF($E$3:$E36,"Q32026"),"") | M36: =IF($E36="Q42026",COUNTIF($E$3:$E36,"Q42026"),"") | N36: =IF($E36="Backlog",COUNTIF($E$3:$E36,"Backlog"),"")
A37: 35 | H37: =IF(C37="XXL (>160h)",168,IF(C37="XL (>40h)",48,IF(C37="L (20-40h)",30,IF(C37="M (10-20h)",15,IF(C37="S (<10h)",5,""))))) | J37: =IF($E37="Q12026",COUNTIF($E$3:$E37,"Q12026"),"") | K37: =IF($E37="Q22026",COUNTIF($E$3:$E37,"Q22026"),"") | L37: =IF($E37="Q32026",COUNTIF($E$3:$E37,"Q32026"),"") | M37: =IF($E37="Q42026",COUNTIF($E$3:$E37,"Q42026"),"") | N37: =IF($E37="Backlog",COUNTIF($E$3:$E37,"Backlog"),"")
A38: 36 | H38: =IF(C38="XXL (>160h)",168,IF(C38="XL (>40h)",48,IF(C38="L (20-40h)",30,IF(C38="M (10-20h)",15,IF(C38="S (<10h)",5,""))))) | J38: =IF($E38="Q12026",COUNTIF($E$3:$E38,"Q12026"),"") | K38: =IF($E38="Q22026",COUNTIF($E$3:$E38,"Q22026"),"") | L38: =IF($E38="Q32026",COUNTIF($E$3:$E38,"Q32026"),"") | M38: =IF($E38="Q42026",COUNTIF($E$3:$E38,"Q42026"),"") | N38: =IF($E38="Backlog",COUNTIF($E$3:$E38,"Backlog"),"")
A39: 37 | H39: =IF(C39="XXL (>160h)",168,IF(C39="XL (>40h)",48,IF(C39="L (20-40h)",30,IF(C39="M (10-20h)",15,IF(C39="S (<10h)",5,""))))) | J39: =IF($E39="Q12026",COUNTIF($E$3:$E39,"Q12026"),"") | K39: =IF($E39="Q22026",COUNTIF($E$3:$E39,"Q22026"),"") | L39: =IF($E39="Q32026",COUNTIF($E$3:$E39,"Q32026"),"") | M39: =IF($E39="Q42026",COUNTIF($E$3:$E39,"Q42026"),"") | N39: =IF($E39="Backlog",COUNTIF($E$3:$E39,"Backlog"),"")
A40: 38 | H40: =IF(C40="XXL (>160h)",168,IF(C40="XL (>40h)",48,IF(C40="L (20-40h)",30,IF(C40="M (10-20h)",15,IF(C40="S (<10h)",5,""))))) | J40: =IF($E40="Q12026",COUNTIF($E$3:$E40,"Q12026"),"") | K40: =IF($E40="Q22026",COUNTIF($E$3:$E40,"Q22026"),"") | L40: =IF($E40="Q32026",COUNTIF($E$3:$E40,"Q32026"),"") | M40: =IF($E40="Q42026",COUNTIF($E$3:$E40,"Q42026"),"") | N40: =IF($E40="Backlog",COUNTIF($E$3:$E40,"Backlog"),"")
A41: 39 | H41: =IF(C41="XXL (>160h)",168,IF(C41="XL (>40h)",48,IF(C41="L (20-40h)",30,IF(C41="M (10-20h)",15,IF(C41="S (<10h)",5,""))))) | J41: =IF($E41="Q12026",COUNTIF($E$3:$E41,"Q12026"),"") | K41: =IF($E41="Q22026",COUNTIF($E$3:$E41,"Q22026"),"") | L41: =IF($E41="Q32026",COUNTIF($E$3:$E41,"Q32026"),"") | M41: =IF($E41="Q42026",COUNTIF($E$3:$E41,"Q42026"),"") | N41: =IF($E41="Backlog",COUNTIF($E$3:$E41,"Backlog"),"")
... A82: 80 | H82: =IF(C82="XXL (>160h)",168,IF(C82="XL (>40h)",48,IF(C82="L (20-40h)",30,IF(C82="M (10-20h)",15,IF(C82="S (<10h)",5,""))))) | J82: =IF($E82="Q12026",COUNTIF($E$3:$E82,"Q12026"),"") | K82: =IF($E82="Q22026",COUNTIF($E$3:$E82,"Q22026"),"") | L82: =IF($E82="Q32026",COUNTIF($E$3:$E82,"Q32026"),"") | M82: =IF($E82="Q42026",COUNTIF($E$3:$E82,"Q42026"),"") | N82: =IF($E82="Backlog",COUNTIF($E$3:$E82,"Backlog"),"")
A83: ∑ Geschätzte Stunden gesamt | H83: =SUM(H3:H82) -> 0
A85: Value: 🟢 Strengthen = strategische Stärkung | 🔵 Innovation = neue Fähigkeiten | 🔴 Repair = Fehler/Schulden beheben
A86: MoSCoW: Must = Pflicht · Should = Soll · Could = Optional · Won't = Ausgeschlossen | Team: WEB · Desktop · W->D · D->W (anteilig je 50% auf beide Teams)
A87: Größen: S <10h · M 10–20h · L 20–40h · XL >40h · XXL >160h | Stunden = automatisch aus Größe | Kapazitäten (blaue Felder) = manuell

Sheet DATA2026
A1: Quartal | B1: Titel | C1: Größe | D1: Value | E1: Stunden | F1: MoSCoW | G1: Team | H1: Quelle | I1: helper_Q12026 | J1: helper_Q22026 | K1: helper_Q32026 | L1: helper_Q42026 | M1: helper_Backlog
A2: =IF(AND('Q12026'!B3<>"",'Q12026'!E3<>""),'Q12026'!E3,"") | B2: =IF(AND('Q12026'!B3<>"",'Q12026'!E3<>""),'Q12026'!B3,"") | C2: =IF(AND('Q12026'!B3<>"",'Q12026'!E3<>""),'Q12026'!C3,"") | D2: =IF(AND('Q12026'!B3<>"",'Q12026'!E3<>""),'Q12026'!D3,"") | E2: =IF(AND('Q12026'!B3<>"",'Q12026'!E3<>""),'Q12026'!H3,"") | F2: =IF(AND('Q12026'!B3<>"",'Q12026'!E3<>""),'Q12026'!F3,"") | G2: =IF(AND('Q12026'!B3<>"",'Q12026'!E3<>""),'Q12026'!G3,"") | H2: =IF(AND('Q12026'!B3<>"",'Q12026'!E3<>""),"Q12026","") | I2: =IF(A2="Q12026",COUNTIF($A$2:$A2,"Q12026"),"") | J2: =IF(A2="Q22026",COUNTIF($A$2:$A2,"Q22026"),"") | K2: =IF(A2="Q32026",COUNTIF($A$2:$A2,"Q32026"),"") | L2: =IF(A2="Q42026",COUNTIF($A$2:$A2,"Q42026"),"") | M2: =IF(A2="Backlog",COUNTIF($A$2:$A2,"Backlog"),"")
A3: =IF(AND('Q12026'!B4<>"",'Q12026'!E4<>""),'Q12026'!E4,"") | B3: =IF(AND('Q12026'!B4<>"",'Q12026'!E4<>""),'Q12026'!B4,"") | C3: =IF(AND('Q12026'!B4<>"",'Q12026'!E4<>""),'Q12026'!C4,"") | D3: =IF(AND('Q12026'!B4<>"",'Q12026'!E4<>""),'Q12026'!D4,"") | E3: =IF(AND('Q12026'!B4<>"",'Q12026'!E4<>""),'Q12026'!H4,"") | F3: =IF(AND('Q12026'!B4<>"",'Q12026'!E4<>""),'Q12026'!F4,"") | G3: =IF(AND('Q12026'!B4<>"",'Q12026'!E4<>""),'Q12026'!G4,"") | H3: =IF(AND('Q12026'!B4<>"",'Q12026'!E4<>""),"Q12026","") | I3: =IF(A3="Q12026",COUNTIF($A$2:$A3,"Q12026"),"") | J3: =IF(A3="Q22026",COUNTIF($A$2:$A3,"Q22026"),"") | K3: =IF(A3="Q32026",COUNTIF($A$2:$A3,"Q32026"),"") | L3: =IF(A3="Q42026",COUNTIF($A$2:$A3,"Q42026"),"") | M3: =IF(A3="Backlog",COUNTIF($A$2:$A3,"Backlog"),"")
A4: =IF(AND('Q12026'!B5<>"",'Q12026'!E5<>""),'Q12026'!E5,"") | B4: =IF(AND('Q12026'!B5<>"",'Q12026'!E5<>""),'Q12026'!B5,"") | C4: =IF(AND('Q12026'!B5<>"",'Q12026'!E5<>""),'Q12026'!C5,"") | D4: =IF(AND('Q12026'!B5<>"",'Q12026'!E5<>""),'Q12026'!D5,"") | E4: =IF(AND('Q12026'!B5<>"",'Q12026'!E5<>""),'Q12026'!H5,"") | F4: =IF(AND('Q12026'!B5<>"",'Q12026'!E5<>""),'Q12026'!F5,"") | G4: =IF(AND('Q12026'!B5<>"",'Q12026'!E5<>""),'Q12026'!G5,"") | H4: =IF(AND('Q12026'!B5<>"",'Q12026'!E5<>""),"Q12026","") | I4: =IF(A4="Q12026",COUNTIF($A$2:$A4,"Q12026"),"") | J4: =IF(A4="Q22026",COUNTIF($A$2:$A4,"Q22026"),"") | K4: =IF(A4="Q32026",COUNTIF($A$2:$A4,"Q32026"),"") | L4: =IF(A4="Q42026",COUNTIF($A$2:$A4,"Q42026"),"") | M4: =IF(A4="Backlog",COUNTIF($A$2:$A4,"Backlog"),"")
A5: =IF(AND('Q12026'!B6<>"",'Q12026'!E6<>""),'Q12026'!E6,"") | B5: =IF(AND('Q12026'!B6<>"",'Q12026'!E6<>""),'Q12026'!B6,"") | C5: =IF(AND('Q12026'!B6<>"",'Q12026'!E6<>""),'Q12026'!C6,"") | D5: =IF(AND('Q12026'!B6<>"",'Q12026'!E6<>""),'Q12026'!D6,"") | E5: =IF(AND('Q12026'!B6<>"",'Q12026'!E6<>""),'Q12026'!H6,"") | F5: =IF(AND('Q12026'!B6<>"",'Q12026'!E6<>""),'Q12026'!F6,"") | G5: =IF(AND('Q12026'!B6<>"",'Q12026'!E6<>""),'Q12026'!G6,"") | H5: =IF(AND('Q12026'!B6<>"",'Q12026'!E6<>""),"Q12026","") | I5: =IF(A5="Q12026",COUNTIF($A$2:$A5,"Q12026"),"") | J5: =IF(A5="Q22026",COUNTIF($A$2:$A5,"Q22026"),"") | K5: =IF(A5="Q32026",COUNTIF($A$2:$A5,"Q32026"),"") | L5: =IF(A5="Q42026",COUNTIF($A$2:$A5,"Q42026"),"") | M5: =IF(A5="Backlog",COUNTIF($A$2:$A5,"Backlog"),"")
A6: =IF(AND('Q12026'!B7<>"",'Q12026'!E7<>""),'Q12026'!E7,"") | B6: =IF(AND('Q12026'!B7<>"",'Q12026'!E7<>""),'Q12026'!B7,"") | C6: =IF(AND('Q12026'!B7<>"",'Q12026'!E7<>""),'Q12026'!C7,"") | D6: =IF(AND('Q12026'!B7<>"",'Q12026'!E7<>""),'Q12026'!D7,"") | E6: =IF(AND('Q12026'!B7<>"",'Q12026'!E7<>""),'Q12026'!H7,"") | F6: =IF(AND('Q12026'!B7<>"",'Q12026'!E7<>""),'Q12026'!F7,"") | G6: =IF(AND('Q12026'!B7<>"",'Q12026'!E7<>""),'Q12026'!G7,"") | H6: =IF(AND('Q12026'!B7<>"",'Q12026'!E7<>""),"Q12026","") | I6: =IF(A6="Q12026",COUNTIF($A$2:$A6,"Q12026"),"") | J6: =IF(A6="Q22026",COUNTIF($A$2:$A6,"Q22026"),"") | K6: =IF(A6="Q32026",COUNTIF($A$2:$A6,"Q32026"),"") | L6: =IF(A6="Q42026",COUNTIF($A$2:$A6,"Q42026"),"") | M6: =IF(A6="Backlog",COUNTIF($A$2:$A6,"Backlog"),"")
A7: =IF(AND('Q12026'!B8<>"",'Q12026'!E8<>""),'Q12026'!E8,"") | B7: =IF(AND('Q12026'!B8<>"",'Q12026'!E8<>""),'Q12026'!B8,"") | C7: =IF(AND('Q12026'!B8<>"",'Q12026'!E8<>""),'Q12026'!C8,"") | D7: =IF(AND('Q12026'!B8<>"",'Q12026'!E8<>""),'Q12026'!D8,"") | E7: =IF(AND('Q12026'!B8<>"",'Q12026'!E8<>""),'Q12026'!H8,"") | F7: =IF(AND('Q12026'!B8<>"",'Q12026'!E8<>""),'Q12026'!F8,"") | G7: =IF(AND('Q12026'!B8<>"",'Q12026'!E8<>""),'Q12026'!G8,"") | H7: =IF(AND('Q12026'!B8<>"",'Q12026'!E8<>""),"Q12026","") | I7: =IF(A7="Q12026",COUNTIF($A$2:$A7,"Q12026"),"") | J7: =IF(A7="Q22026",COUNTIF($A$2:$A7,"Q22026"),"") | K7: =IF(A7="Q32026",COUNTIF($A$2:$A7,"Q32026"),"") | L7: =IF(A7="Q42026",COUNTIF($A$2:$A7,"Q42026"),"") | M7: =IF(A7="Backlog",COUNTIF($A$2:$A7,"Backlog"),"")
A8: =IF(AND('Q12026'!B9<>"",'Q12026'!E9<>""),'Q12026'!E9,"") | B8: =IF(AND('Q12026'!B9<>"",'Q12026'!E9<>""),'Q12026'!B9,"") | C8: =IF(AND('Q12026'!B9<>"",'Q12026'!E9<>""),'Q12026'!C9,"") | D8: =IF(AND('Q12026'!B9<>"",'Q12026'!E9<>""),'Q12026'!D9,"") | E8: =IF(AND('Q12026'!B9<>"",'Q12026'!E9<>""),'Q12026'!H9,"") | F8: =IF(AND('Q12026'!B9<>"",'Q12026'!E9<>""),'Q12026'!F9,"") | G8: =IF(AND('Q12026'!B9<>"",'Q12026'!E9<>""),'Q12026'!G9,"") | H8: =IF(AND('Q12026'!B9<>"",'Q12026'!E9<>""),"Q12026","") | I8: =IF(A8="Q12026",COUNTIF($A$2:$A8,"Q12026"),"") | J8: =IF(A8="Q22026",COUNTIF($A$2:$A8,"Q22026"),"") | K8: =IF(A8="Q32026",COUNTIF($A$2:$A8,"Q32026"),"") | L8: =IF(A8="Q42026",COUNTIF($A$2:$A8,"Q42026"),"") | M8: =IF(A8="Backlog",COUNTIF($A$2:$A8,"Backlog"),"")
A9: =IF(AND('Q12026'!B10<>"",'Q12026'!E10<>""),'Q12026'!E10,"") | B9: =IF(AND('Q12026'!B10<>"",'Q12026'!E10<>""),'Q12026'!B10,"") | C9: =IF(AND('Q12026'!B10<>"",'Q12026'!E10<>""),'Q12026'!C10,"") | D9: =IF(AND('Q12026'!B10<>"",'Q12026'!E10<>""),'Q12026'!D10,"") | E9: =IF(AND('Q12026'!B10<>"",'Q12026'!E10<>""),'Q12026'!H10,"") | F9: =IF(AND('Q12026'!B10<>"",'Q12026'!E10<>""),'Q12026'!F10,"") | G9: =IF(AND('Q12026'!B10<>"",'Q12026'!E10<>""),'Q12026'!G10,"") | H9: =IF(AND('Q12026'!B10<>"",'Q12026'!E10<>""),"Q12026","") | I9: =IF(A9="Q12026",COUNTIF($A$2:$A9,"Q12026"),"") | J9: =IF(A9="Q22026",COUNTIF($A$2:$A9,"Q22026"),"") | K9: =IF(A9="Q32026",COUNTIF($A$2:$A9,"Q32026"),"") | L9: =IF(A9="Q42026",COUNTIF($A$2:$A9,"Q42026"),"") | M9: =IF(A9="Backlog",COUNTIF($A$2:$A9,"Backlog"),"")
A10: =IF(AND('Q12026'!B11<>"",'Q12026'!E11<>""),'Q12026'!E11,"") | B10: =IF(AND('Q12026'!B11<>"",'Q12026'!E11<>""),'Q12026'!B11,"") | C10: =IF(AND('Q12026'!B11<>"",'Q12026'!E11<>""),'Q12026'!C11,"") | D10: =IF(AND('Q12026'!B11<>"",'Q12026'!E11<>""),'Q12026'!D11,"") | E10: =IF(AND('Q12026'!B11<>"",'Q12026'!E11<>""),'Q12026'!H11,"") | F10: =IF(AND('Q12026'!B11<>"",'Q12026'!E11<>""),'Q12026'!F11,"") | G10: =IF(AND('Q12026'!B11<>"",'Q12026'!E11<>""),'Q12026'!G11,"") | H10: =IF(AND('Q12026'!B11<>"",'Q12026'!E11<>""),"Q12026","") | I10: =IF(A10="Q12026",COUNTIF($A$2:$A10,"Q12026"),"") | J10: =IF(A10="Q22026",COUNTIF($A$2:$A10,"Q22026"),"") | K10: =IF(A10="Q32026",COUNTIF($A$2:$A10,"Q32026"),"") | L10: =IF(A10="Q42026",COUNTIF($A$2:$A10,"Q42026"),"") | M10: =IF(A10="Backlog",COUNTIF($A$2:$A10,"Backlog"),"")
A11: =IF(AND('Q12026'!B12<>"",'Q12026'!E12<>""),'Q12026'!E12,"") | B11: =IF(AND('Q12026'!B12<>"",'Q12026'!E12<>""),'Q12026'!B12,"") | C11: =IF(AND('Q12026'!B12<>"",'Q12026'!E12<>""),'Q12026'!C12,"") | D11: =IF(AND('Q12026'!B12<>"",'Q12026'!E12<>""),'Q12026'!D12,"") | E11: =IF(AND('Q12026'!B12<>"",'Q12026'!E12<>""),'Q12026'!H12,"") | F11: =IF(AND('Q12026'!B12<>"",'Q12026'!E12<>""),'Q12026'!F12,"") | G11: =IF(AND('Q12026'!B12<>"",'Q12026'!E12<>""),'Q12026'!G12,"") | H11: =IF(AND('Q12026'!B12<>"",'Q12026'!E12<>""),"Q12026","") | I11: =IF(A11="Q12026",COUNTIF($A$2:$A11,"Q12026"),"") | J11: =IF(A11="Q22026",COUNTIF($A$2:$A11,"Q22026"),"") | K11: =IF(A11="Q32026",COUNTIF($A$2:$A11,"Q32026"),"") | L11: =IF(A11="Q42026",COUNTIF($A$2:$A11,"Q42026"),"") | M11: =IF(A11="Backlog",COUNTIF($A$2:$A11,"Backlog"),"")
A12: =IF(AND('Q12026'!B13<>"",'Q12026'!E13<>""),'Q12026'!E13,"") | B12: =IF(AND('Q12026'!B13<>"",'Q12026'!E13<>""),'Q12026'!B13,"") | C12: =IF(AND('Q12026'!B13<>"",'Q12026'!E13<>""),'Q12026'!C13,"") | D12: =IF(AND('Q12026'!B13<>"",'Q12026'!E13<>""),'Q12026'!D13,"") | E12: =IF(AND('Q12026'!B13<>"",'Q12026'!E13<>""),'Q12026'!H13,"") | F12: =IF(AND('Q12026'!B13<>"",'Q12026'!E13<>""),'Q12026'!F13,"") | G12: =IF(AND('Q12026'!B13<>"",'Q12026'!E13<>""),'Q12026'!G13,"") | H12: =IF(AND('Q12026'!B13<>"",'Q12026'!E13<>""),"Q12026","") | I12: =IF(A12="Q12026",COUNTIF($A$2:$A12,"Q12026"),"") | J12: =IF(A12="Q22026",COUNTIF($A$2:$A12,"Q22026"),"") | K12: =IF(A12="Q32026",COUNTIF($A$2:$A12,"Q32026"),"") | L12: =IF(A12="Q42026",COUNTIF($A$2:$A12,"Q42026"),"") | M12: =IF(A12="Backlog",COUNTIF($A$2:$A12,"Backlog"),"")
A13: =IF(AND('Q12026'!B14<>"",'Q12026'!E14<>""),'Q12026'!E14,"") | B13: =IF(AND('Q12026'!B14<>"",'Q12026'!E14<>""),'Q12026'!B14,"") | C13: =IF(AND('Q12026'!B14<>"",'Q12026'!E14<>""),'Q12026'!C14,"") | D13: =IF(AND('Q12026'!B14<>"",'Q12026'!E14<>""),'Q12026'!D14,"") | E13: =IF(AND('Q12026'!B14<>"",'Q12026'!E14<>""),'Q12026'!H14,"") | F13: =IF(AND('Q12026'!B14<>"",'Q12026'!E14<>""),'Q12026'!F14,"") | G13: =IF(AND('Q12026'!B14<>"",'Q12026'!E14<>""),'Q12026'!G14,"") | H13: =IF(AND('Q12026'!B14<>"",'Q12026'!E14<>""),"Q12026","") | I13: =IF(A13="Q12026",COUNTIF($A$2:$A13,"Q12026"),"") | J13: =IF(A13="Q22026",COUNTIF($A$2:$A13,"Q22026"),"") | K13: =IF(A13="Q32026",COUNTIF($A$2:$A13,"Q32026"),"") | L13: =IF(A13="Q42026",COUNTIF($A$2:$A13,"Q42026"),"") | M13: =IF(A13="Backlog",COUNTIF($A$2:$A13,"Backlog"),"")
... A81: =IF(AND('Q12026'!B82<>"",'Q12026'!E82<>""),'Q12026'!E82,"") | B81: =IF(AND('Q12026'!B82<>"",'Q12026'!E82<>""),'Q12026'!B82,"") | C81: =IF(AND('Q12026'!B82<>"",'Q12026'!E82<>""),'Q12026'!C82,"") | D81: =IF(AND('Q12026'!B82<>"",'Q12026'!E82<>""),'Q12026'!D82,"") | E81: =IF(AND('Q12026'!B82<>"",'Q12026'!E82<>""),'Q12026'!H82,"") | F81: =IF(AND('Q12026'!B82<>"",'Q12026'!E82<>""),'Q12026'!F82,"") | G81: =IF(AND('Q12026'!B82<>"",'Q12026'!E82<>""),'Q12026'!G82,"") | H81: =IF(AND('Q12026'!B82<>"",'Q12026'!E82<>""),"Q12026","") | I81: =IF(A81="Q12026",COUNTIF($A$2:$A81,"Q12026"),"") | J81: =IF(A81="Q22026",COUNTIF($A$2:$A81,"Q22026"),"") | K81: =IF(A81="Q32026",COUNTIF($A$2:$A81,"Q32026"),"") | L81: =IF(A81="Q42026",COUNTIF($A$2:$A81,"Q42026"),"") | M81: =IF(A81="Backlog",COUNTIF($A$2:$A81,"Backlog"),"")
A82: =IF(AND('Q22026'!B3<>"",'Q22026'!E3<>""),'Q22026'!E3,"") -> Q22026 | B82: =IF(AND('Q22026'!B3<>"",'Q22026'!E3<>""),'Q22026'!B3,"") -> Apple iOS SDK Anforderungen | C82: =IF(AND('Q22026'!B3<>"",'Q22026'!E3<>""),'Q22026'!C3,"") -> XL (>40h) | D82: =IF(AND('Q22026'!B3<>"",'Q22026'!E3<>""),'Q22026'!D3,"") -> Repair | E82: =IF(AND('Q22026'!B3<>"",'Q22026'!E3<>""),'Q22026'!H3,"") -> 48 | F82: =IF(AND('Q22026'!B3<>"",'Q22026'!E3<>""),'Q22026'!F3,"") -> Must | G82: =IF(AND('Q22026'!B3<>"",'Q22026'!E3<>""),'Q22026'!G3,"") -> WEB | H82: =IF(AND('Q22026'!B3<>"",'Q22026'!E3<>""),"Q22026","") -> Q22026 | I82: =IF(A82="Q12026",COUNTIF($A$2:$A82,"Q12026"),"") | J82: =IF(A82="Q22026",COUNTIF($A$2:$A82,"Q22026"),"") -> 1 | K82: =IF(A82="Q32026",COUNTIF($A$2:$A82,"Q32026"),"") | L82: =IF(A82="Q42026",COUNTIF($A$2:$A82,"Q42026"),"") | M82: =IF(A82="Backlog",COUNTIF($A$2:$A82,"Backlog"),"")
A83: =IF(AND('Q22026'!B4<>"",'Q22026'!E4<>""),'Q22026'!E4,"") -> Q22026 | B83: =IF(AND('Q22026'!B4<>"",'Q22026'!E4<>""),'Q22026'!B4,"") -> mobilePeople.de - Vulnerabilitys Portal Live | C83: =IF(AND('Q22026'!B4<>"",'Q22026'!E4<>""),'Q22026'!C4,"") -> XL (>40h) | D83: =IF(AND('Q22026'!B4<>"",'Q22026'!E4<>""),'Q22026'!D4,"") -> Repair | E83: =IF(AND('Q22026'!B4<>"",'Q22026'!E4<>""),'Q22026'!H4,"") -> 48 | F83: =IF(AND('Q22026'!B4<>"",'Q22026'!E4<>""),'Q22026'!F4,"") -> Must | G83: =IF(AND('Q22026'!B4<>"",'Q22026'!E4<>""),'Q22026'!G4,"") -> WEB | H83: =IF(AND('Q22026'!B4<>"",'Q22026'!E4<>""),"Q22026","") -> Q22026 | I83: =IF(A83="Q12026",COUNTIF($A$2:$A83,"Q12026"),"") | J83: =IF(A83="Q22026",COUNTIF($A$2:$A83,"Q22026"),"") -> 2 | K83: =IF(A83="Q32026",COUNTIF($A$2:$A83,"Q32026"),"") | L83: =IF(A83="Q42026",COUNTIF($A$2:$A83,"Q42026"),"") | M83: =IF(A83="Backlog",COUNTIF($A$2:$A83,"Backlog"),"")
A84: =IF(AND('Q22026'!B5<>"",'Q22026'!E5<>""),'Q22026'!E5,"") -> Q22026 | B84: =IF(AND('Q22026'!B5<>"",'Q22026'!E5<>""),'Q22026'!B5,"") -> Webshop mit Newsletter Zustimmung | C84: =IF(AND('Q22026'!B5<>"",'Q22026'!E5<>""),'Q22026'!C5,"") -> M (10-20h) | D84: =IF(AND('Q22026'!B5<>"",'Q22026'!E5<>""),'Q22026'!D5,"") -> Strengthen | E84: =IF(AND('Q22026'!B5<>"",'Q22026'!E5<>""),'Q22026'!H5,"") -> 15 | F84: =IF(AND('Q22026'!B5<>"",'Q22026'!E5<>""),'Q22026'!F5,"") -> Should | G84: =IF(AND('Q22026'!B5<>"",'Q22026'!E5<>""),'Q22026'!G5,"") -> WEB | H84: =IF(AND('Q22026'!B5<>"",'Q22026'!E5<>""),"Q22026","") -> Q22026 | I84: =IF(A84="Q12026",COUNTIF($A$2:$A84,"Q12026"),"") | J84: =IF(A84="Q22026",COUNTIF($A$2:$A84,"Q22026"),"") -> 3 | K84: =IF(A84="Q32026",COUNTIF($A$2:$A84,"Q32026"),"") | L84: =IF(A84="Q42026",COUNTIF($A$2:$A84,"Q42026"),"") | M84: =IF(A84="Backlog",COUNTIF($A$2:$A84,"Backlog"),"")
A85: =IF(AND('Q22026'!B6<>"",'Q22026'!E6<>""),'Q22026'!E6,"") -> Q22026 | B85: =IF(AND('Q22026'!B6<>"",'Q22026'!E6<>""),'Q22026'!B6,"") -> Ticketshop mit Kalender & Anzahl | C85: =IF(AND('Q22026'!B6<>"",'Q22026'!E6<>""),'Q22026'!C6,"") -> M (10-20h) | D85: =IF(AND('Q22026'!B6<>"",'Q22026'!E6<>""),'Q22026'!D6,"") -> Strengthen | E85: =IF(AND('Q22026'!B6<>"",'Q22026'!E6<>""),'Q22026'!H6,"") -> 15 | F85: =IF(AND('Q22026'!B6<>"",'Q22026'!E6<>""),'Q22026'!F6,"") -> Must | G85: =IF(AND('Q22026'!B6<>"",'Q22026'!E6<>""),'Q22026'!G6,"") -> WEB | H85: =IF(AND('Q22026'!B6<>"",'Q22026'!E6<>""),"Q22026","") -> Q22026 | I85: =IF(A85="Q12026",COUNTIF($A$2:$A85,"Q12026"),"") | J85: =IF(A85="Q22026",COUNTIF($A$2:$A85,"Q22026"),"") -> 4 | K85: =IF(A85="Q32026",COUNTIF($A$2:$A85,"Q32026"),"") | L85: =IF(A85="Q42026",COUNTIF($A$2:$A85,"Q42026"),"") | M85: =IF(A85="Backlog",COUNTIF($A$2:$A85,"Backlog"),"")
A86: =IF(AND('Q22026'!B7<>"",'Q22026'!E7<>""),'Q22026'!E7,"") -> Q22026 | B86: =IF(AND('Q22026'!B7<>"",'Q22026'!E7<>""),'Q22026'!B7,"") -> Optimierung SOT Sync | C86: =IF(AND('Q22026'!B7<>"",'Q22026'!E7<>""),'Q22026'!C7,"") -> L (20-40h) | D86: =IF(AND('Q22026'!B7<>"",'Q22026'!E7<>""),'Q22026'!D7,"") -> Repair | E86: =IF(AND('Q22026'!B7<>"",'Q22026'!E7<>""),'Q22026'!H7,"") -> 30 | F86: =IF(AND('Q22026'!B7<>"",'Q22026'!E7<>""),'Q22026'!F7,"") -> Must | G86: =IF(AND('Q22026'!B7<>"",'Q22026'!E7<>""),'Q22026'!G7,"") -> WEB | H86: =IF(AND('Q22026'!B7<>"",'Q22026'!E7<>""),"Q22026","") -> Q22026 | I86: =IF(A86="Q12026",COUNTIF($A$2:$A86,"Q12026"),"") | J86: =IF(A86="Q22026",COUNTIF($A$2:$A86,"Q22026"),"") -> 5 | K86: =IF(A86="Q32026",COUNTIF($A$2:$A86,"Q32026"),"") | L86: =IF(A86="Q42026",COUNTIF($A$2:$A86,"Q42026"),"") | M86: =IF(A86="Backlog",COUNTIF($A$2:$A86,"Backlog"),"")
A87: =IF(AND('Q22026'!B8<>"",'Q22026'!E8<>""),'Q22026'!E8,"") | B87: =IF(AND('Q22026'!B8<>"",'Q22026'!E8<>""),'Q22026'!B8,"") | C87: =IF(AND('Q22026'!B8<>"",'Q22026'!E8<>""),'Q22026'!C8,"") | D87: =IF(AND('Q22026'!B8<>"",'Q22026'!E8<>""),'Q22026'!D8,"") | E87: =IF(AND('Q22026'!B8<>"",'Q22026'!E8<>""),'Q22026'!H8,"") | F87: =IF(AND('Q22026'!B8<>"",'Q22026'!E8<>""),'Q22026'!F8,"") | G87: =IF(AND('Q22026'!B8<>"",'Q22026'!E8<>""),'Q22026'!G8,"") | H87: =IF(AND('Q22026'!B8<>"",'Q22026'!E8<>""),"Q22026","") | I87: =IF(A87="Q12026",COUNTIF($A$2:$A87,"Q12026"),"") | J87: =IF(A87="Q22026",COUNTIF($A$2:$A87,"Q22026"),"") | K87: =IF(A87="Q32026",COUNTIF($A$2:$A87,"Q32026"),"") | L87: =IF(A87="Q42026",COUNTIF($A$2:$A87,"Q42026"),"") | M87: =IF(A87="Backlog",COUNTIF($A$2:$A87,"Backlog"),"")
A88: =IF(AND('Q22026'!B9<>"",'Q22026'!E9<>""),'Q22026'!E9,"") | B88: =IF(AND('Q22026'!B9<>"",'Q22026'!E9<>""),'Q22026'!B9,"") | C88: =IF(AND('Q22026'!B9<>"",'Q22026'!E9<>""),'Q22026'!C9,"") | D88: =IF(AND('Q22026'!B9<>"",'Q22026'!E9<>""),'Q22026'!D9,"") | E88: =IF(AND('Q22026'!B9<>"",'Q22026'!E9<>""),'Q22026'!H9,"") | F88: =IF(AND('Q22026'!B9<>"",'Q22026'!E9<>""),'Q22026'!F9,"") | G88: =IF(AND('Q22026'!B9<>"",'Q22026'!E9<>""),'Q22026'!G9,"") | H88: =IF(AND('Q22026'!B9<>"",'Q22026'!E9<>""),"Q22026","") | I88: =IF(A88="Q12026",COUNTIF($A$2:$A88,"Q12026"),"") | J88: =IF(A88="Q22026",COUNTIF($A$2:$A88,"Q22026"),"") | K88: =IF(A88="Q32026",COUNTIF($A$2:$A88,"Q32026"),"") | L88: =IF(A88="Q42026",COUNTIF($A$2:$A88,"Q42026"),"") | M88: =IF(A88="Backlog",COUNTIF($A$2:$A88,"Backlog"),"")
A89: =IF(AND('Q22026'!B10<>"",'Q22026'!E10<>""),'Q22026'!E10,"") | B89: =IF(AND('Q22026'!B10<>"",'Q22026'!E10<>""),'Q22026'!B10,"") | C89: =IF(AND('Q22026'!B10<>"",'Q22026'!E10<>""),'Q22026'!C10,"") | D89: =IF(AND('Q22026'!B10<>"",'Q22026'!E10<>""),'Q22026'!D10,"") | E89: =IF(AND('Q22026'!B10<>"",'Q22026'!E10<>""),'Q22026'!H10,"") | F89: =IF(AND('Q22026'!B10<>"",'Q22026'!E10<>""),'Q22026'!F10,"") | G89: =IF(AND('Q22026'!B10<>"",'Q22026'!E10<>""),'Q22026'!G10,"") | H89: =IF(AND('Q22026'!B10<>"",'Q22026'!E10<>""),"Q22026","") | I89: =IF(A89="Q12026",COUNTIF($A$2:$A89,"Q12026"),"") | J89: =IF(A89="Q22026",COUNTIF($A$2:$A89,"Q22026"),"") | K89: =IF(A89="Q32026",COUNTIF($A$2:$A89,"Q32026"),"") | L89: =IF(A89="Q42026",COUNTIF($A$2:$A89,"Q42026"),"") | M89: =IF(A89="Backlog",COUNTIF($A$2:$A89,"Backlog"),"")
A90: =IF(AND('Q22026'!B11<>"",'Q22026'!E11<>""),'Q22026'!E11,"") -> Q22026 | B90: =IF(AND('Q22026'!B11<>"",'Q22026'!E11<>""),'Q22026'!B11,"") -> UHD | AI Agent - Support | C90: =IF(AND('Q22026'!B11<>"",'Q22026'!E11<>""),'Q22026'!C11,"") -> L (20-40h) | D90: =IF(AND('Q22026'!B11<>"",'Q22026'!E11<>""),'Q22026'!D11,"") -> Strengthen | E90: =IF(AND('Q22026'!B11<>"",'Q22026'!E11<>""),'Q22026'!H11,"") -> 30 | F90: =IF(AND('Q22026'!B11<>"",'Q22026'!E11<>""),'Q22026'!F11,"") -> Must | G90: =IF(AND('Q22026'!B11<>"",'Q22026'!E11<>""),'Q22026'!G11,"") -> WEB | H90: =IF(AND('Q22026'!B11<>"",'Q22026'!E11<>""),"Q22026","") -> Q22026 | I90: =IF(A90="Q12026",COUNTIF($A$2:$A90,"Q12026"),"") | J90: =IF(A90="Q22026",COUNTIF($A$2:$A90,"Q22026"),"") -> 6 | K90: =IF(A90="Q32026",COUNTIF($A$2:$A90,"Q32026"),"") | L90: =IF(A90="Q42026",COUNTIF($A$2:$A90,"Q42026"),"") | M90: =IF(A90="Backlog",COUNTIF($A$2:$A90,"Backlog"),"")
A91: =IF(AND('Q22026'!B12<>"",'Q22026'!E12<>""),'Q22026'!E12,"") | B91: =IF(AND('Q22026'!B12<>"",'Q22026'!E12<>""),'Q22026'!B12,"") | C91: =IF(AND('Q22026'!B12<>"",'Q22026'!E12<>""),'Q22026'!C12,"") | D91: =IF(AND('Q22026'!B12<>"",'Q22026'!E12<>""),'Q22026'!D12,"") | E91: =IF(AND('Q22026'!B12<>"",'Q22026'!E12<>""),'Q22026'!H12,"") | F91: =IF(AND('Q22026'!B12<>"",'Q22026'!E12<>""),'Q22026'!F12,"") | G91: =IF(AND('Q22026'!B12<>"",'Q22026'!E12<>""),'Q22026'!G12,"") | H91: =IF(AND('Q22026'!B12<>"",'Q22026'!E12<>""),"Q22026","") | I91: =IF(A91="Q12026",COUNTIF($A$2:$A91,"Q12026"),"") | J91: =IF(A91="Q22026",COUNTIF($A$2:$A91,"Q22026"),"") | K91: =IF(A91="Q32026",COUNTIF($A$2:$A91,"Q32026"),"") | L91: =IF(A91="Q42026",COUNTIF($A$2:$A91,"Q42026"),"") | M91: =IF(A91="Backlog",COUNTIF($A$2:$A91,"Backlog"),"")
A92: =IF(AND('Q22026'!B13<>"",'Q22026'!E13<>""),'Q22026'!E13,"") | B92: =IF(AND('Q22026'!B13<>"",'Q22026'!E13<>""),'Q22026'!B13,"") | C92: =IF(AND('Q22026'!B13<>"",'Q22026'!E13<>""),'Q22026'!C13,"") | D92: =IF(AND('Q22026'!B13<>"",'Q22026'!E13<>""),'Q22026'!D13,"") | E92: =IF(AND('Q22026'!B13<>"",'Q22026'!E13<>""),'Q22026'!H13,"") | F92: =IF(AND('Q22026'!B13<>"",'Q22026'!E13<>""),'Q22026'!F13,"") | G92: =IF(AND('Q22026'!B13<>"",'Q22026'!E13<>""),'Q22026'!G13,"") | H92: =IF(AND('Q22026'!B13<>"",'Q22026'!E13<>""),"Q22026","") | I92: =IF(A92="Q12026",COUNTIF($A$2:$A92,"Q12026"),"") | J92: =IF(A92="Q22026",COUNTIF($A$2:$A92,"Q22026"),"") | K92: =IF(A92="Q32026",COUNTIF($A$2:$A92,"Q32026"),"") | L92: =IF(A92="Q42026",COUNTIF($A$2:$A92,"Q42026"),"") | M92: =IF(A92="Backlog",COUNTIF($A$2:$A92,"Backlog"),"")
A93: =IF(AND('Q22026'!B14<>"",'Q22026'!E14<>""),'Q22026'!E14,"") -> Q22026 | B93: =IF(AND('Q22026'!B14<>"",'Q22026'!E14<>""),'Q22026'!B14,"") -> 3rd Party - Google Log In für APP | C93: =IF(AND('Q22026'!B14<>"",'Q22026'!E14<>""),'Q22026'!C14,"") -> M (10-20h) | D93: =IF(AND('Q22026'!B14<>"",'Q22026'!E14<>""),'Q22026'!D14,"") -> Repair | E93: =IF(AND('Q22026'!B14<>"",'Q22026'!E14<>""),'Q22026'!H14,"") -> 15 | F93: =IF(AND('Q22026'!B14<>"",'Q22026'!E14<>""),'Q22026'!F14,"") -> Must | G93: =IF(AND('Q22026'!B14<>"",'Q22026'!E14<>""),'Q22026'!G14,"") -> WEB | H93: =IF(AND('Q22026'!B14<>"",'Q22026'!E14<>""),"Q22026","") -> Q22026 | I93: =IF(A93="Q12026",COUNTIF($A$2:$A93,"Q12026"),"") | J93: =IF(A93="Q22026",COUNTIF($A$2:$A93,"Q22026"),"") -> 7 | K93: =IF(A93="Q32026",COUNTIF($A$2:$A93,"Q32026"),"") | L93: =IF(A93="Q42026",COUNTIF($A$2:$A93,"Q42026"),"") | M93: =IF(A93="Backlog",COUNTIF($A$2:$A93,"Backlog"),"")
... A161: =IF(AND('Q22026'!B82<>"",'Q22026'!E82<>""),'Q22026'!E82,"") | B161: =IF(AND('Q22026'!B82<>"",'Q22026'!E82<>""),'Q22026'!B82,"") | C161: =IF(AND('Q22026'!B82<>"",'Q22026'!E82<>""),'Q22026'!C82,"") | D161: =IF(AND('Q22026'!B82<>"",'Q22026'!E82<>""),'Q22026'!D82,"") | E161: =IF(AND('Q22026'!B82<>"",'Q22026'!E82<>""),'Q22026'!H82,"") | F161: =IF(AND('Q22026'!B82<>"",'Q22026'!E82<>""),'Q22026'!F82,"") | G161: =IF(AND('Q22026'!B82<>"",'Q22026'!E82<>""),'Q22026'!G82,"") | H161: =IF(AND('Q22026'!B82<>"",'Q22026'!E82<>""),"Q22026","") | I161: =IF(A161="Q12026",COUNTIF($A$2:$A161,"Q12026"),"") | J161: =IF(A161="Q22026",COUNTIF($A$2:$A161,"Q22026"),"") | K161: =IF(A161="Q32026",COUNTIF($A$2:$A161,"Q32026"),"") | L161: =IF(A161="Q42026",COUNTIF($A$2:$A161,"Q42026"),"") | M161: =IF(A161="Backlog",COUNTIF($A$2:$A161,"Backlog"),"")
A162: =IF(AND('Q32026'!B3<>"",'Q32026'!E3<>""),'Q32026'!E3,"") -> Q32026 | B162: =IF(AND('Q32026'!B3<>"",'Q32026'!E3<>""),'Q32026'!B3,"") -> GitHub - Umstellung | C162: =IF(AND('Q32026'!B3<>"",'Q32026'!E3<>""),'Q32026'!C3,"") -> L (20-40h) | D162: =IF(AND('Q32026'!B3<>"",'Q32026'!E3<>""),'Q32026'!D3,"") -> Strengthen | E162: =IF(AND('Q32026'!B3<>"",'Q32026'!E3<>""),'Q32026'!H3,"") -> 30 | F162: =IF(AND('Q32026'!B3<>"",'Q32026'!E3<>""),'Q32026'!F3,"") -> Must | G162: =IF(AND('Q32026'!B3<>"",'Q32026'!E3<>""),'Q32026'!G3,"") -> D->W | H162: =IF(AND('Q32026'!B3<>"",'Q32026'!E3<>""),"Q32026","") -> Q32026 | I162: =IF(A162="Q12026",COUNTIF($A$2:$A162,"Q12026"),"") | J162: =IF(A162="Q22026",COUNTIF($A$2:$A162,"Q22026"),"") | K162: =IF(A162="Q32026",COUNTIF($A$2:$A162,"Q32026"),"") -> 1 | L162: =IF(A162="Q42026",COUNTIF($A$2:$A162,"Q42026"),"") | M162: =IF(A162="Backlog",COUNTIF($A$2:$A162,"Backlog"),"")
